Workbook

Sheet Red
A1: GENERADOR DE MODELOS DE REDES SINTÉTICAS DE FINANCIACIÓN DEL TERRORISMO | S1: Marina Sarti Pineda - marzo 2026
A3: TIPOS DE NODO | E3: NODOS | J3: ENLACES ENTRE NODOS
A4: Tipo | B4: Descripción | C4: Capa | E4: NodoID | F4: Nombre | G4: Tipo | H4: Activo | J4: EdgeID | K4: Nodo Origen | L4: Nodo Destino | M4: Tipo de Enlace | N4: Activo | O4: Tipo de Justificación | P4: Coste | Q4: Eficiencia | R4: Exposición | S4: Capacidad | T4: Resiliencia | U4: Fuente GAFI | V4: Observaciones | W4: Peso | X4: Coste (peso) | Y4: Eficiencia (peso) | Z4: Exposición (peso) | AA4: Capacidad (peso) | AB4: Resiliencia (peso) | AC4: ValorOperativo (peso)
A5: O | B5: Origen | C5: 1 | E5: O1 | F5: Coerción y cobros forzosos | G5: O | H5: 1 | J5: E051 | K5: G1 | L5: D | M5: principal | N5: 1 | O5: T | P5: Bajo | Q5: Alto | R5: Medio | S5: Alto | T5: Medio | U5: GAFI - FT risks | V5: Tesorería central → destino | W5: =IFERROR(_xlfn.XLOOKUP(tblEnlaces[[#This Row],[Eficiencia]],tblPesosCoste[Valor],#REF!),0)+IFERROR(_xlfn.XLOOKUP(tblEnlaces[[#This Row],[Capacidad]],tblPesosCoste[Valor],#REF!),0)+IFERROR(_xlfn.XLOOKUP(tblEnlaces[[#This Row],[Resiliencia]],tblPesosCoste[Valor],#REF!),0)+IFERROR(_xlfn.XLOOKUP(tblEnlaces[[#This Row],[Coste]],tblPesosCoste[Valor],tblPesosCoste[Coste]),0)+IFERROR(_xlfn.XLOOKUP(tblEnlaces[[#This Row],[Exposición]],tblPesosCoste[Valor],#REF!),0) -> 5 | X5: =IFERROR(_xlfn.XLOOKUP(tblEnlaces[[#This Row],[Coste]],tblPesosCoste[Valor],tblPesosCoste[Coste],0),0) -> 5 | Y5: =IFERROR(_xlfn.XLOOKUP(tblEnlaces[[#This Row],[Eficiencia]],tblPesosValorOperativo[Valor],tblPesosValorOperativo[Eficiencia],0),0) -> 5 | Z5: =IFERROR(_xlfn.XLOOKUP(tblEnlaces[[#This Row],[Exposición]],tblPesosValorOperativo[Valor],tblPesosValorOperativo[Exposición],0),0) -> 3 | AA5: =IFERROR(_xlfn.XLOOKUP(tblEnlaces[[#This Row],[Capacidad]],tblPesosValorOperativo[Valor],tblPesosValorOperativo[Capacidad],0),0) -> 5 | AB5: =IFERROR(_xlfn.XLOOKUP(tblEnlaces[[#This Row],[Resiliencia]],tblPesosValorOperativo[Valor],tblPesosValorOperativo[Resiliencia],0),0) -> 3 | AC5: =tblEnlaces[[#This Row],[Eficiencia (peso)]]+tblEnlaces[[#This Row],[Exposición (peso)]]+tblEnlaces[[#This Row],[Capacidad (peso)]]+tblEnlaces[[#This Row],[Resiliencia (peso)]] -> 16
A6: I | B6: Intermediario | C6: 2 | E6: O2 | F6: Contrabando / tráfico / comercio ilícito | G6: O | H6: 1 | J6: E012 | K6: O4 | L6: I4 | M6: principal | N6: 1 | O6: T | P6: Bajo | Q6: Alto | R6: Medio | S6: Medio | T6: Medio | U6: GAFI - FT risks | V6: Microfinanciación y dinero móvil | W6: =IFERROR(_xlfn.XLOOKUP(tblEnlaces[[#This Row],[Eficiencia]],tblPesosCoste[Valor],#REF!),0)+IFERROR(_xlfn.XLOOKUP(tblEnlaces[[#This Row],[Capacidad]],tblPesosCoste[Valor],#REF!),0)+IFERROR(_xlfn.XLOOKUP(tblEnlaces[[#This Row],[Resiliencia]],tblPesosCoste[Valor],#REF!),0)+IFERROR(_xlfn.XLOOKUP(tblEnlaces[[#This Row],[Coste]],tblPesosCoste[Valor],tblPesosCoste[Coste]),0)+IFERROR(_xlfn.XLOOKUP(tblEnlaces[[#This Row],[Exposición]],tblPesosCoste[Valor],#REF!),0) -> 5 | X6: =IFERROR(_xlfn.XLOOKUP(tblEnlaces[[#This Row],[Coste]],tblPesosCoste[Valor],tblPesosCoste[Coste],0),0) -> 5 | Y6: =IFERROR(_xlfn.XLOOKUP(tblEnlaces[[#This Row],[Eficiencia]],tblPesosValorOperativo[Valor],tblPesosValorOperativo[Eficiencia],0),0) -> 5 | Z6: =IFERROR(_xlfn.XLOOKUP(tblEnlaces[[#This Row],[Exposición]],tblPesosValorOperativo[Valor],tblPesosValorOperativo[Exposición],0),0) -> 3 | AA6: =IFERROR(_xlfn.XLOOKUP(tblEnlaces[[#This Row],[Capacidad]],tblPesosValorOperativo[Valor],tblPesosValorOperativo[Capacidad],0),0) -> 3 | AB6: =IFERROR(_xlfn.XLOOKUP(tblEnlaces[[#This Row],[Resiliencia]],tblPesosValorOperativo[Valor],tblPesosValorOperativo[Resiliencia],0),0) -> 3 | AC6: =tblEnlaces[[#This Row],[Eficiencia (peso)]]+tblEnlaces[[#This Row],[Exposición (peso)]]+tblEnlaces[[#This Row],[Capacidad (peso)]]+tblEnlaces[[#This Row],[Resiliencia (peso)]] -> 14
A7: G | B7: Gestión | C7: 3 | E7: O3 | F7: Explotación de recursos naturales | G7: O | H7: 1 | J7: E046 | K7: G2 | L7: D | M7: principal | N7: 1 | O7: T | P7: Bajo | Q7: Alto | R7: Medio | S7: Medio | T7: Medio | U7: GAFI - FT risks | V7: Células/centros regionales → destino | W7: =IFERROR(_xlfn.XLOOKUP(tblEnlaces[[#This Row],[Eficiencia]],tblPesosCoste[Valor],#REF!),0)+IFERROR(_xlfn.XLOOKUP(tblEnlaces[[#This Row],[Capacidad]],tblPesosCoste[Valor],#REF!),0)+IFERROR(_xlfn.XLOOKUP(tblEnlaces[[#This Row],[Resiliencia]],tblPesosCoste[Valor],#REF!),0)+IFERROR(_xlfn.XLOOKUP(tblEnlaces[[#This Row],[Coste]],tblPesosCoste[Valor],tblPesosCoste[Coste]),0)+IFERROR(_xlfn.XLOOKUP(tblEnlaces[[#This Row],[Exposición]],tblPesosCoste[Valor],#REF!),0) -> 5 | X7: =IFERROR(_xlfn.XLOOKUP(tblEnlaces[[#This Row],[Coste]],tblPesosCoste[Valor],tblPesosCoste[Coste],0),0) -> 5 | Y7: =IFERROR(_xlfn.XLOOKUP(tblEnlaces[[#This Row],[Eficiencia]],tblPesosValorOperativo[Valor],tblPesosValorOperativo[Eficiencia],0),0) -> 5 | Z7: =IFERROR(_xlfn.XLOOKUP(tblEnlaces[[#This Row],[Exposición]],tblPesosValorOperativo[Valor],tblPesosValorOperativo[Exposición],0),0) -> 3 | AA7: =IFERROR(_xlfn.XLOOKUP(tblEnlaces[[#This Row],[Capacidad]],tblPesosValorOperativo[Valor],tblPesosValorOperativo[Capacidad],0),0) -> 3 | AB7: =IFERROR(_xlfn.XLOOKUP(tblEnlaces[[#This Row],[Resiliencia]],tblPesosValorOperativo[Valor],tblPesosValorOperativo[Resiliencia],0),0) -> 3 | AC7: =tblEnlaces[[#This Row],[Eficiencia (peso)]]+tblEnlaces[[#This Row],[Exposición (peso)]]+tblEnlaces[[#This Row],[Capacidad (peso)]]+tblEnlaces[[#This Row],[Resiliencia (peso)]] -> 14
A8: D | B8: Destino | C8: 4 | E8: O4 | F8: Autofinanciación lícita / microfinanciación | G8: O | H8: 1 | J8: E050 | K8: G3 | L8: D | M8: principal | N8: 1 | O8: T | P8: Bajo | Q8: Alto | R8: Medio | S8: Medio | T8: Medio | U8: GAFI - FT risks | V8: Facilitador → destino | W8: =IFERROR(_xlfn.XLOOKUP(tblEnlaces[[#This Row],[Eficiencia]],tblPesosCoste[Valor],#REF!),0)+IFERROR(_xlfn.XLOOKUP(tblEnlaces[[#This Row],[Capacidad]],tblPesosCoste[Valor],#REF!),0)+IFERROR(_xlfn.XLOOKUP(tblEnlaces[[#This Row],[Resiliencia]],tblPesosCoste[Valor],#REF!),0)+IFERROR(_xlfn.XLOOKUP(tblEnlaces[[#This Row],[Coste]],tblPesosCoste[Valor],tblPesosCoste[Coste]),0)+IFERROR(_xlfn.XLOOKUP(tblEnlaces[[#This Row],[Exposición]],tblPesosCoste[Valor],#REF!),0) -> 5 | X8: =IFERROR(_xlfn.XLOOKUP(tblEnlaces[[#This Row],[Coste]],tblPesosCoste[Valor],tblPesosCoste[Coste],0),0) -> 5 | Y8: =IFERROR(_xlfn.XLOOKUP(tblEnlaces[[#This Row],[Eficiencia]],tblPesosValorOperativo[Valor],tblPesosValorOperativo[Eficiencia],0),0) -> 5 | Z8: =IFERROR(_xlfn.XLOOKUP(tblEnlaces[[#This Row],[Exposición]],tblPesosValorOperativo[Valor],tblPesosValorOperativo[Exposición],0),0) -> 3 | AA8: =IFERROR(_xlfn.XLOOKUP(tblEnlaces[[#This Row],[Capacidad]],tblPesosValorOperativo[Valor],tblPesosValorOperativo[Capacidad],0),0) -> 3 | AB8: =IFERROR(_xlfn.XLOOKUP(tblEnlaces[[#This Row],[Resiliencia]],tblPesosValorOperativo[Valor],tblPesosValorOperativo[Resiliencia],0),0) -> 3 | AC8: =tblEnlaces[[#This Row],[Eficiencia (peso)]]+tblEnlaces[[#This Row],[Exposición (peso)]]+tblEnlaces[[#This Row],[Capacidad (peso)]]+tblEnlaces[[#This Row],[Resiliencia (peso)]] -> 14
E9: O5 | F9: Actividades económicas formales / negocios | G9: O | H9: 1 | J9: E041 | K9: G1 | L9: I6 | M9: principal | N9: 1 | O9: T | P9: Bajo-Medio | Q9: Alto | R9: Alto | S9: Alto | T9: Medio | U9: GAFI - FT risks | V9: Gestión central + banca | W9: =IFERROR(_xlfn.XLOOKUP(tblEnlaces[[#This Row],[Eficiencia]],tblPesosCoste[Valor],#REF!),0)+IFERROR(_xlfn.XLOOKUP(tblEnlaces[[#This Row],[Capacidad]],tblPesosCoste[Valor],#REF!),0)+IFERROR(_xlfn.XLOOKUP(tblEnlaces[[#This Row],[Resiliencia]],tblPesosCoste[Valor],#REF!),0)+IFERROR(_xlfn.XLOOKUP(tblEnlaces[[#This Row],[Coste]],tblPesosCoste[Valor],tblPesosCoste[Coste]),0)+IFERROR(_xlfn.XLOOKUP(tblEnlaces[[#This Row],[Exposición]],tblPesosCoste[Valor],#REF!),0) -> 4 | X9: =IFERROR(_xlfn.XLOOKUP(tblEnlaces[[#This Row],[Coste]],tblPesosCoste[Valor],tblPesosCoste[Coste],0),0) -> 4 | Y9: =IFERROR(_xlfn.XLOOKUP(tblEnlaces[[#This Row],[Eficiencia]],tblPesosValorOperativo[Valor],tblPesosValorOperativo[Eficiencia],0),0) -> 5 | Z9: =IFERROR(_xlfn.XLOOKUP(tblEnlaces[[#This Row],[Exposición]],tblPesosValorOperativo[Valor],tblPesosValorOperativo[Exposición],0),0) -> 1 | AA9: =IFERROR(_xlfn.XLOOKUP(tblEnlaces[[#This Row],[Capacidad]],tblPesosValorOperativo[Valor],tblPesosValorOperativo[Capacidad],0),0) -> 5 | AB9: =IFERROR(_xlfn.XLOOKUP(tblEnlaces[[#This Row],[Resiliencia]],tblPesosValorOperativo[Valor],tblPesosValorOperativo[Resiliencia],0),0) -> 3 | AC9: =tblEnlaces[[#This Row],[Eficiencia (peso)]]+tblEnlaces[[#This Row],[Exposición (peso)]]+tblEnlaces[[#This Row],[Capacidad (peso)]]+tblEnlaces[[#This Row],[Resiliencia (peso)]] -> 14
E10: O6 | F10: Donaciones / crowdfunding / apoyo online | G10: O | H10: 1 | J10: E004 | K10: O1 | L10: I4 | M10: secundario | N10: 1 | O10: T | P10: Bajo-Medio | Q10: Alto | R10: Medio | S10: Medio | T10: Medio | U10: GAFI - FT risks | V10: Cobros con dinero móvil | W10: =IFERROR(_xlfn.XLOOKUP(tblEnlaces[[#This Row],[Eficiencia]],tblPesosCoste[Valor],#REF!),0)+IFERROR(_xlfn.XLOOKUP(tblEnlaces[[#This Row],[Capacidad]],tblPesosCoste[Valor],#REF!),0)+IFERROR(_xlfn.XLOOKUP(tblEnlaces[[#This Row],[Resiliencia]],tblPesosCoste[Valor],#REF!),0)+IFERROR(_xlfn.XLOOKUP(tblEnlaces[[#This Row],[Coste]],tblPesosCoste[Valor],tblPesosCoste[Coste]),0)+IFERROR(_xlfn.XLOOKUP(tblEnlaces[[#This Row],[Exposición]],tblPesosCoste[Valor],#REF!),0) -> 4 | X10: =IFERROR(_xlfn.XLOOKUP(tblEnlaces[[#This Row],[Coste]],tblPesosCoste[Valor],tblPesosCoste[Coste],0),0) -> 4 | Y10: =IFERROR(_xlfn.XLOOKUP(tblEnlaces[[#This Row],[Eficiencia]],tblPesosValorOperativo[Valor],tblPesosValorOperativo[Eficiencia],0),0) -> 5 | Z10: =IFERROR(_xlfn.XLOOKUP(tblEnlaces[[#This Row],[Exposición]],tblPesosValorOperativo[Valor],tblPesosValorOperativo[Exposición],0),0) -> 3 | AA10: =IFERROR(_xlfn.XLOOKUP(tblEnlaces[[#This Row],[Capacidad]],tblPesosValorOperativo[Valor],tblPesosValorOperativo[Capacidad],0),0) -> 3 | AB10: =IFERROR(_xlfn.XLOOKUP(tblEnlaces[[#This Row],[Resiliencia]],tblPesosValorOperativo[Valor],tblPesosValorOperativo[Resiliencia],0),0) -> 3 | AC10: =tblEnlaces[[#This Row],[Eficiencia (peso)]]+tblEnlaces[[#This Row],[Exposición (peso)]]+tblEnlaces[[#This Row],[Capacidad (peso)]]+tblEnlaces[[#This Row],[Resiliencia (peso)]] -> 14
E11: I1 | F11: Efectivo | G11: I | H11: 1 | J11: E030 | K11: I4 | L11: G2 | M11: principal | N11: 1 | O11: T | P11: Bajo-Medio | Q11: Alto | R11: Medio | S11: Medio | T11: Medio | U11: GAFI - FT risks | V11: Dinero móvil y células | W11: =IFERROR(_xlfn.XLOOKUP(tblEnlaces[[#This Row],[Eficiencia]],tblPesosCoste[Valor],#REF!),0)+IFERROR(_xlfn.XLOOKUP(tblEnlaces[[#This Row],[Capacidad]],tblPesosCoste[Valor],#REF!),0)+IFERROR(_xlfn.XLOOKUP(tblEnlaces[[#This Row],[Resiliencia]],tblPesosCoste[Valor],#REF!),0)+IFERROR(_xlfn.XLOOKUP(tblEnlaces[[#This Row],[Coste]],tblPesosCoste[Valor],tblPesosCoste[Coste]),0)+IFERROR(_xlfn.XLOOKUP(tblEnlaces[[#This Row],[Exposición]],tblPesosCoste[Valor],#REF!),0) -> 4 | X11: =IFERROR(_xlfn.XLOOKUP(tblEnlaces[[#This Row],[Coste]],tblPesosCoste[Valor],tblPesosCoste[Coste],0),0) -> 4 | Y11: =IFERROR(_xlfn.XLOOKUP(tblEnlaces[[#This Row],[Eficiencia]],tblPesosValorOperativo[Valor],tblPesosValorOperativo[Eficiencia],0),0) -> 5 | Z11: =IFERROR(_xlfn.XLOOKUP(tblEnlaces[[#This Row],[Exposición]],tblPesosValorOperativo[Valor],tblPesosValorOperativo[Exposición],0),0) -> 3 | AA11: =IFERROR(_xlfn.XLOOKUP(tblEnlaces[[#This Row],[Capacidad]],tblPesosValorOperativo[Valor],tblPesosValorOperativo[Capacidad],0),0) -> 3 | AB11: =IFERROR(_xlfn.XLOOKUP(tblEnlaces[[#This Row],[Resiliencia]],tblPesosValorOperativo[Valor],tblPesosValorOperativo[Resiliencia],0),0) -> 3 | AC11: =tblEnlaces[[#This Row],[Eficiencia (peso)]]+tblEnlaces[[#This Row],[Exposición (peso)]]+tblEnlaces[[#This Row],[Capacidad (peso)]]+tblEnlaces[[#This Row],[Resiliencia (peso)]] -> 14
E12: I2 | F12: Hawala / HOSSP | G12: I | H12: 1 | J12: E045 | K12: G2 | L12: I4 | M12: principal | N12: 1 | O12: T | P12: Bajo-Medio | Q12: Alto | R12: Medio | S12: Medio | T12: Medio | U12: GAFI - FT risks | V12: Centros regionales y dinero móvil | W12: =IFERROR(_xlfn.XLOOKUP(tblEnlaces[[#This Row],[Eficiencia]],tblPesosCoste[Valor],#REF!),0)+IFERROR(_xlfn.XLOOKUP(tblEnlaces[[#This Row],[Capacidad]],tblPesosCoste[Valor],#REF!),0)+IFERROR(_xlfn.XLOOKUP(tblEnlaces[[#This Row],[Resiliencia]],tblPesosCoste[Valor],#REF!),0)+IFERROR(_xlfn.XLOOKUP(tblEnlaces[[#This Row],[Coste]],tblPesosCoste[Valor],tblPesosCoste[Coste]),0)+IFERROR(_xlfn.XLOOKUP(tblEnlaces[[#This Row],[Exposición]],tblPesosCoste[Valor],#REF!),0) -> 4 | X12: =IFERROR(_xlfn.XLOOKUP(tblEnlaces[[#This Row],[Coste]],tblPesosCoste[Valor],tblPesosCoste[Coste],0),0) -> 4 | Y12: =IFERROR(_xlfn.XLOOKUP(tblEnlaces[[#This Row],[Eficiencia]],tblPesosValorOperativo[Valor],tblPesosValorOperativo[Eficiencia],0),0) -> 5 | Z12: =IFERROR(_xlfn.XLOOKUP(tblEnlaces[[#This Row],[Exposición]],tblPesosValorOperativo[Valor],tblPesosValorOperativo[Exposición],0),0) -> 3 | AA12: =IFERROR(_xlfn.XLOOKUP(tblEnlaces[[#This Row],[Capacidad]],tblPesosValorOperativo[Valor],tblPesosValorOperativo[Capacidad],0),0) -> 3 | AB12: =IFERROR(_xlfn.XLOOKUP(tblEnlaces[[#This Row],[Resiliencia]],tblPesosValorOperativo[Valor],tblPesosValorOperativo[Resiliencia],0),0) -> 3 | AC12: =tblEnlaces[[#This Row],[Eficiencia (peso)]]+tblEnlaces[[#This Row],[Exposición (peso)]]+tblEnlaces[[#This Row],[Capacidad (peso)]]+tblEnlaces[[#This Row],[Resiliencia (peso)]] -> 14
E13: I3 | F13: MVTS / remesas | G13: I | H13: 1 | J13: E013 | K13: O4 | L13: I5 | M13: principal | N13: 1 | O13: T | P13: Bajo-Medio | Q13: Alto | R13: Medio-Alto | S13: Medio | T13: Medio | U13: GAFI - FT risks | V13: Microfinanciación y pagos online | W13: =IFERROR(_xlfn.XLOOKUP(tblEnlaces[[#This Row],[Eficiencia]],tblPesosCoste[Valor],#REF!),0)+IFERROR(_xlfn.XLOOKUP(tblEnlaces[[#This Row],[Capacidad]],tblPesosCoste[Valor],#REF!),0)+IFERROR(_xlfn.XLOOKUP(tblEnlaces[[#This Row],[Resiliencia]],tblPesosCoste[Valor],#REF!),0)+IFERROR(_xlfn.XLOOKUP(tblEnlaces[[#This Row],[Coste]],tblPesosCoste[Valor],tblPesosCoste[Coste]),0)+IFERROR(_xlfn.XLOOKUP(tblEnlaces[[#This Row],[Exposición]],tblPesosCoste[Valor],#REF!),0) -> 4 | X13: =IFERROR(_xlfn.XLOOKUP(tblEnlaces[[#This Row],[Coste]],tblPesosCoste[Valor],tblPesosCoste[Coste],0),0) -> 4 | Y13: =IFERROR(_xlfn.XLOOKUP(tblEnlaces[[#This Row],[Eficiencia]],tblPesosValorOperativo[Valor],tblPesosValorOperativo[Eficiencia],0),0) -> 5 | Z13: =IFERROR(_xlfn.XLOOKUP(tblEnlaces[[#This Row],[Exposición]],tblPesosValorOperativo[Valor],tblPesosValorOperativo[Exposición],0),0) -> 2 | AA13: =IFERROR(_xlfn.XLOOKUP(tblEnlaces[[#This Row],[Capacidad]],tblPesosValorOperativo[Valor],tblPesosValorOperativo[Capacidad],0),0) -> 3 | AB13: =IFERROR(_xlfn.XLOOKUP(tblEnlaces[[#This Row],[Resiliencia]],tblPesosValorOperativo[Valor],tblPesosValorOperativo[Resiliencia],0),0) -> 3 | AC13: =tblEnlaces[[#This Row],[Eficiencia (peso)]]+tblEnlaces[[#This Row],[Exposición (peso)]]+tblEnlaces[[#This Row],[Capacidad (peso)]]+tblEnlaces[[#This Row],[Resiliencia (peso)]] -> 13
E14: I4 | F14: Dinero móvil | G14: I | H14: 1 | J14: E017 | K14: O5 | L14: I5 | M14: secundario | N14: 1 | O14: T | P14: Bajo-Medio | Q14: Alto | R14: Medio-Alto | S14: Medio | T14: Medio | U14: GAFI - FT risks | V14: Pagos online en actividad comercial | W14: =IFERROR(_xlfn.XLOOKUP(tblEnlaces[[#This Row],[Eficiencia]],tblPesosCoste[Valor],#REF!),0)+IFERROR(_xlfn.XLOOKUP(tblEnlaces[[#This Row],[Capacidad]],tblPesosCoste[Valor],#REF!),0)+IFERROR(_xlfn.XLOOKUP(tblEnlaces[[#This Row],[Resiliencia]],tblPesosCoste[Valor],#REF!),0)+IFERROR(_xlfn.XLOOKUP(tblEnlaces[[#This Row],[Coste]],tblPesosCoste[Valor],tblPesosCoste[Coste]),0)+IFERROR(_xlfn.XLOOKUP(tblEnlaces[[#This Row],[Exposición]],tblPesosCoste[Valor],#REF!),0) -> 4 | X14: =IFERROR(_xlfn.XLOOKUP(tblEnlaces[[#This Row],[Coste]],tblPesosCoste[Valor],tblPesosCoste[Coste],0),0) -> 4 | Y14: =IFERROR(_xlfn.XLOOKUP(tblEnlaces[[#This Row],[Eficiencia]],tblPesosValorOperativo[Valor],tblPesosValorOperativo[Eficiencia],0),0) -> 5 | Z14: =IFERROR(_xlfn.XLOOKUP(tblEnlaces[[#This Row],[Exposición]],tblPesosValorOperativo[Valor],tblPesosValorOperativo[Exposición],0),0) -> 2 | AA14: =IFERROR(_xlfn.XLOOKUP(tblEnlaces[[#This Row],[Capacidad]],tblPesosValorOperativo[Valor],tblPesosValorOperativo[Capacidad],0),0) -> 3 | AB14: =IFERROR(_xlfn.XLOOKUP(tblEnlaces[[#This Row],[Resiliencia]],tblPesosValorOperativo[Valor],tblPesosValorOperativo[Resiliencia],0),0) -> 3 | AC14: =tblEnlaces[[#This Row],[Eficiencia (peso)]]+tblEnlaces[[#This Row],[Exposición (peso)]]+tblEnlaces[[#This Row],[Capacidad (peso)]]+tblEnlaces[[#This Row],[Resiliencia (peso)]] -> 13
E15: I5 | F15: Pagos online | G15: I | H15: 1 | J15: E020 | K15: O6 | L15: I5 | M15: principal | N15: 1 | O15: T | P15: Bajo-Medio | Q15: Alto | R15: Medio-Alto | S15: Medio | T15: Medio | U15: GAFI - FT risks | V15: Pagos integrados online | W15: =IFERROR(_xlfn.XLOOKUP(tblEnlaces[[#This Row],[Eficiencia]],tblPesosCoste[Valor],#REF!),0)+IFERROR(_xlfn.XLOOKUP(tblEnlaces[[#This Row],[Capacidad]],tblPesosCoste[Valor],#REF!),0)+IFERROR(_xlfn.XLOOKUP(tblEnlaces[[#This Row],[Resiliencia]],tblPesosCoste[Valor],#REF!),0)+IFERROR(_xlfn.XLOOKUP(tblEnlaces[[#This Row],[Coste]],tblPesosCoste[Valor],tblPesosCoste[Coste]),0)+IFERROR(_xlfn.XLOOKUP(tblEnlaces[[#This Row],[Exposición]],tblPesosCoste[Valor],#REF!),0) -> 4 | X15: =IFERROR(_xlfn.XLOOKUP(tblEnlaces[[#This Row],[Coste]],tblPesosCoste[Valor],tblPesosCoste[Coste],0),0) -> 4 | Y15: =IFERROR(_xlfn.XLOOKUP(tblEnlaces[[#This Row],[Eficiencia]],tblPesosValorOperativo[Valor],tblPesosValorOperativo[Eficiencia],0),0) -> 5 | Z15: =IFERROR(_xlfn.XLOOKUP(tblEnlaces[[#This Row],[Exposición]],tblPesosValorOperativo[Valor],tblPesosValorOperativo[Exposición],0),0) -> 2 | AA15: =IFERROR(_xlfn.XLOOKUP(tblEnlaces[[#This Row],[Capacidad]],tblPesosValorOperativo[Valor],tblPesosValorOperativo[Capacidad],0),0) -> 3 | AB15: =IFERROR(_xlfn.XLOOKUP(tblEnlaces[[#This Row],[Resiliencia]],tblPesosValorOperativo[Valor],tblPesosValorOperativo[Resiliencia],0),0) -> 3 | AC15: =tblEnlaces[[#This Row],[Eficiencia (peso)]]+tblEnlaces[[#This Row],[Exposición (peso)]]+tblEnlaces[[#This Row],[Capacidad (peso)]]+tblEnlaces[[#This Row],[Resiliencia (peso)]] -> 13
E16: I6 | F16: Servicios bancarios | G16: I | H16: 1 | J16: E031 | K16: I5 | L16: G2 | M16: principal | N16: 1 | O16: T | P16: Bajo-Medio | Q16: Alto | R16: Medio-Alto | S16: Medio | T16: Medio | U16: GAFI - FT risks | V16: Pagos online y estructuras descentralizadas | W16: =IFERROR(_xlfn.XLOOKUP(tblEnlaces[[#This Row],[Eficiencia]],tblPesosCoste[Valor],#REF!),0)+IFERROR(_xlfn.XLOOKUP(tblEnlaces[[#This Row],[Capacidad]],tblPesosCoste[Valor],#REF!),0)+IFERROR(_xlfn.XLOOKUP(tblEnlaces[[#This Row],[Resiliencia]],tblPesosCoste[Valor],#REF!),0)+IFERROR(_xlfn.XLOOKUP(tblEnlaces[[#This Row],[Coste]],tblPesosCoste[Valor],tblPesosCoste[Coste]),0)+IFERROR(_xlfn.XLOOKUP(tblEnlaces[[#This Row],[Exposición]],tblPesosCoste[Valor],#REF!),0) -> 4 | X16: =IFERROR(_xlfn.XLOOKUP(tblEnlaces[[#This Row],[Coste]],tblPesosCoste[Valor],tblPesosCoste[Coste],0),0) -> 4 | Y16: =IFERROR(_xlfn.XLOOKUP(tblEnlaces[[#This Row],[Eficiencia]],tblPesosValorOperativo[Valor],tblPesosValorOperativo[Eficiencia],0),0) -> 5 | Z16: =IFERROR(_xlfn.XLOOKUP(tblEnlaces[[#This Row],[Exposición]],tblPesosValorOperativo[Valor],tblPesosValorOperativo[Exposición],0),0) -> 2 | AA16: =IFERROR(_xlfn.XLOOKUP(tblEnlaces[[#This Row],[Capacidad]],tblPesosValorOperativo[Valor],tblPesosValorOperativo[Capacidad],0),0) -> 3 | AB16: =IFERROR(_xlfn.XLOOKUP(tblEnlaces[[#This Row],[Resiliencia]],tblPesosValorOperativo[Valor],tblPesosValorOperativo[Resiliencia],0),0) -> 3 | AC16: =tblEnlaces[[#This Row],[Eficiencia (peso)]]+tblEnlaces[[#This Row],[Exposición (peso)]]+tblEnlaces[[#This Row],[Capacidad (peso)]]+tblEnlaces[[#This Row],[Resiliencia (peso)]] -> 13
E17: I7 | F17: Tarjetas prepago / e-wallets | G17: I | H17: 1 | J17: E018 | K17: O5 | L17: I6 | M17: principal | N17: 1 | O17: T | P17: Medio | Q17: Alto | R17: Alto | S17: Alto | T17: Medio | U17: GAFI - FT risks | V17: Banca y transferencias | W17: =IFERROR(_xlfn.XLOOKUP(tblEnlaces[[#This Row],[Eficiencia]],tblPesosCoste[Valor],#REF!),0)+IFERROR(_xlfn.XLOOKUP(tblEnlaces[[#This Row],[Capacidad]],tblPesosCoste[Valor],#REF!),0)+IFERROR(_xlfn.XLOOKUP(tblEnlaces[[#This Row],[Resiliencia]],tblPesosCoste[Valor],#REF!),0)+IFERROR(_xlfn.XLOOKUP(tblEnlaces[[#This Row],[Coste]],tblPesosCoste[Valor],tblPesosCoste[Coste]),0)+IFERROR(_xlfn.XLOOKUP(tblEnlaces[[#This Row],[Exposición]],tblPesosCoste[Valor],#REF!),0) -> 3 | X17: =IFERROR(_xlfn.XLOOKUP(tblEnlaces[[#This Row],[Coste]],tblPesosCoste[Valor],tblPesosCoste[Coste],0),0) -> 3 | Y17: =IFERROR(_xlfn.XLOOKUP(tblEnlaces[[#This Row],[Eficiencia]],tblPesosValorOperativo[Valor],tblPesosValorOperativo[Eficiencia],0),0) -> 5 | Z17: =IFERROR(_xlfn.XLOOKUP(tblEnlaces[[#This Row],[Exposición]],tblPesosValorOperativo[Valor],tblPesosValorOperativo[Exposición],0),0) -> 1 | AA17: =IFERROR(_xlfn.XLOOKUP(tblEnlaces[[#This Row],[Capacidad]],tblPesosValorOperativo[Valor],tblPesosValorOperativo[Capacidad],0),0) -> 5 | AB17: =IFERROR(_xlfn.XLOOKUP(tblEnlaces[[#This Row],[Resiliencia]],tblPesosValorOperativo[Valor],tblPesosValorOperativo[Resiliencia],0),0) -> 3 | AC17: =tblEnlaces[[#This Row],[Eficiencia (peso)]]+tblEnlaces[[#This Row],[Exposición (peso)]]+tblEnlaces[[#This Row],[Capacidad (peso)]]+tblEnlaces[[#This Row],[Resiliencia (peso)]] -> 14
E18: I8 | F18: Plataformas digitales | G18: I | H18: 1 | J18: E033 | K18: I6 | L18: G1 | M18: principal | N18: 1 | O18: T | P18: Medio | Q18: Alto | R18: Alto | S18: Alto | T18: Medio | U18: GAFI - FT risks | V18: Banca y tesorería central | W18: =IFERROR(_xlfn.XLOOKUP(tblEnlaces[[#This Row],[Eficiencia]],tblPesosCoste[Valor],#REF!),0)+IFERROR(_xlfn.XLOOKUP(tblEnlaces[[#This Row],[Capacidad]],tblPesosCoste[Valor],#REF!),0)+IFERROR(_xlfn.XLOOKUP(tblEnlaces[[#This Row],[Resiliencia]],tblPesosCoste[Valor],#REF!),0)+IFERROR(_xlfn.XLOOKUP(tblEnlaces[[#This Row],[Coste]],tblPesosCoste[Valor],tblPesosCoste[Coste]),0)+IFERROR(_xlfn.XLOOKUP(tblEnlaces[[#This Row],[Exposición]],tblPesosCoste[Valor],#REF!),0) -> 3 | X18: =IFERROR(_xlfn.XLOOKUP(tblEnlaces[[#This Row],[Coste]],tblPesosCoste[Valor],tblPesosCoste[Coste],0),0) -> 3 | Y18: =IFERROR(_xlfn.XLOOKUP(tblEnlaces[[#This Row],[Eficiencia]],tblPesosValorOperativo[Valor],tblPesosValorOperativo[Eficiencia],0),0) -> 5 | Z18: =IFERROR(_xlfn.XLOOKUP(tblEnlaces[[#This Row],[Exposición]],tblPesosValorOperativo[Valor],tblPesosValorOperativo[Exposición],0),0) -> 1 | AA18: =IFERROR(_xlfn.XLOOKUP(tblEnlaces[[#This Row],[Capacidad]],tblPesosValorOperativo[Valor],tblPesosValorOperativo[Capacidad],0),0) -> 5 | AB18: =IFERROR(_xlfn.XLOOKUP(tblEnlaces[[#This Row],[Resiliencia]],tblPesosValorOperativo[Valor],tblPesosValorOperativo[Resiliencia],0),0) -> 3 | AC18: =tblEnlaces[[#This Row],[Eficiencia (peso)]]+tblEnlaces[[#This Row],[Exposición (peso)]]+tblEnlaces[[#This Row],[Capacidad (peso)]]+tblEnlaces[[#This Row],[Resiliencia (peso)]] -> 14
E19: I9 | F19: Activos virtuales | G19: I | H19: 1 | J19: E034 | K19: I6 | L19: G3 | M19: principal | N19: 1 | O19: E | P19: Medio | Q19: Alto | R19: Alto | S19: Alto | T19: Medio | U19: GAFI - FT risks | V19: Cuentas legítimas/entidades registradas | W19: =IFERROR(_xlfn.XLOOKUP(tblEnlaces[[#This Row],[Eficiencia]],tblPesosCoste[Valor],#REF!),0)+IFERROR(_xlfn.XLOOKUP(tblEnlaces[[#This Row],[Capacidad]],tblPesosCoste[Valor],#REF!),0)+IFERROR(_xlfn.XLOOKUP(tblEnlaces[[#This Row],[Resiliencia]],tblPesosCoste[Valor],#REF!),0)+IFERROR(_xlfn.XLOOKUP(tblEnlaces[[#This Row],[Coste]],tblPesosCoste[Valor],tblPesosCoste[Coste]),0)+IFERROR(_xlfn.XLOOKUP(tblEnlaces[[#This Row],[Exposición]],tblPesosCoste[Valor],#REF!),0) -> 3 | X19: =IFERROR(_xlfn.XLOOKUP(tblEnlaces[[#This Row],[Coste]],tblPesosCoste[Valor],tblPesosCoste[Coste],0),0) -> 3 | Y19: =IFERROR(_xlfn.XLOOKUP(tblEnlaces[[#This Row],[Eficiencia]],tblPesosValorOperativo[Valor],tblPesosValorOperativo[Eficiencia],0),0) -> 5 | Z19: =IFERROR(_xlfn.XLOOKUP(tblEnlaces[[#This Row],[Exposición]],tblPesosValorOperativo[Valor],tblPesosValorOperativo[Exposición],0),0) -> 1 | AA19: =IFERROR(_xlfn.XLOOKUP(tblEnlaces[[#This Row],[Capacidad]],tblPesosValorOperativo[Valor],tblPesosValorOperativo[Capacidad],0),0) -> 5 | AB19: =IFERROR(_xlfn.XLOOKUP(tblEnlaces[[#This Row],[Resiliencia]],tblPesosValorOperativo[Valor],tblPesosValorOperativo[Resiliencia],0),0) -> 3 | AC19: =tblEnlaces[[#This Row],[Eficiencia (peso)]]+tblEnlaces[[#This Row],[Exposición (peso)]]+tblEnlaces[[#This Row],[Capacidad (peso)]]+tblEnlaces[[#This Row],[Resiliencia (peso)]] -> 14
E20: G1 | F20: Tesorería central | G20: G | H20: 1 | J20: E048 | K20: G3 | L20: I6 | M20: principal | N20: 1 | O20: E | P20: Medio | Q20: Alto | R20: Alto | S20: Alto | T20: Medio | U20: GAFI - FT risks | V20: Facilitador → banca | W20: =IFERROR(_xlfn.XLOOKUP(tblEnlaces[[#This Row],[Eficiencia]],tblPesosCoste[Valor],#REF!),0)+IFERROR(_xlfn.XLOOKUP(tblEnlaces[[#This Row],[Capacidad]],tblPesosCoste[Valor],#REF!),0)+IFERROR(_xlfn.XLOOKUP(tblEnlaces[[#This Row],[Resiliencia]],tblPesosCoste[Valor],#REF!),0)+IFERROR(_xlfn.XLOOKUP(tblEnlaces[[#This Row],[Coste]],tblPesosCoste[Valor],tblPesosCoste[Coste]),0)+IFERROR(_xlfn.XLOOKUP(tblEnlaces[[#This Row],[Exposición]],tblPesosCoste[Valor],#REF!),0) -> 3 | X20: =IFERROR(_xlfn.XLOOKUP(tblEnlaces[[#This Row],[Coste]],tblPesosCoste[Valor],tblPesosCoste[Coste],0),0) -> 3 | Y20: =IFERROR(_xlfn.XLOOKUP(tblEnlaces[[#This Row],[Eficiencia]],tblPesosValorOperativo[Valor],tblPesosValorOperativo[Eficiencia],0),0) -> 5 | Z20: =IFERROR(_xlfn.XLOOKUP(tblEnlaces[[#This Row],[Exposición]],tblPesosValorOperativo[Valor],tblPesosValorOperativo[Exposición],0),0) -> 1 | AA20: =IFERROR(_xlfn.XLOOKUP(tblEnlaces[[#This Row],[Capacidad]],tblPesosValorOperativo[Valor],tblPesosValorOperativo[Capacidad],0),0) -> 5 | AB20: =IFERROR(_xlfn.XLOOKUP(tblEnlaces[[#This Row],[Resiliencia]],tblPesosValorOperativo[Valor],tblPesosValorOperativo[Resiliencia],0),0) -> 3 | AC20: =tblEnlaces[[#This Row],[Eficiencia (peso)]]+tblEnlaces[[#This Row],[Exposición (peso)]]+tblEnlaces[[#This Row],[Capacidad (peso)]]+tblEnlaces[[#This Row],[Resiliencia (peso)]] -> 14
... E23: D | F23: Destino operativo | G23: D | H23: 1 | J23: E023 | K23: I1 | L23: I2 | M23: principal | N23: 1 | O23: T | P23: Medio | Q23: Alto | R23: Bajo | S23: Medio | T23: Alto | U23: GAFI - FT risks | V23: Efectivo combinado con hawala | W23: =IFERROR(_xlfn.XLOOKUP(tblEnlaces[[#This Row],[Eficiencia]],tblPesosCoste[Valor],#REF!),0)+IFERROR(_xlfn.XLOOKUP(tblEnlaces[[#This Row],[Capacidad]],tblPesosCoste[Valor],#REF!),0)+IFERROR(_xlfn.XLOOKUP(tblEnlaces[[#This Row],[Resiliencia]],tblPesosCoste[Valor],#REF!),0)+IFERROR(_xlfn.XLOOKUP(tblEnlaces[[#This Row],[Coste]],tblPesosCoste[Valor],tblPesosCoste[Coste]),0)+IFERROR(_xlfn.XLOOKUP(tblEnlaces[[#This Row],[Exposición]],tblPesosCoste[Valor],#REF!),0) -> 3 | X23: =IFERROR(_xlfn.XLOOKUP(tblEnlaces[[#This Row],[Coste]],tblPesosCoste[Valor],tblPesosCoste[Coste],0),0) -> 3 | Y23: =IFERROR(_xlfn.XLOOKUP(tblEnlaces[[#This Row],[Eficiencia]],tblPesosValorOperativo[Valor],tblPesosValorOperativo[Eficiencia],0),0) -> 5 | Z23: =IFERROR(_xlfn.XLOOKUP(tblEnlaces[[#This Row],[Exposición]],tblPesosValorOperativo[Valor],tblPesosValorOperativo[Exposición],0),0) -> 5 | AA23: =IFERROR(_xlfn.XLOOKUP(tblEnlaces[[#This Row],[Capacidad]],tblPesosValorOperativo[Valor],tblPesosValorOperativo[Capacidad],0),0) -> 3 | AB23: =IFERROR(_xlfn.XLOOKUP(tblEnlaces[[#This Row],[Resiliencia]],tblPesosValorOperativo[Valor],tblPesosValorOperativo[Resiliencia],0),0) -> 5 | AC23: =tblEnlaces[[#This Row],[Eficiencia (peso)]]+tblEnlaces[[#This Row],[Exposición (peso)]]+tblEnlaces[[#This Row],[Capacidad (peso)]]+tblEnlaces[[#This Row],[Resiliencia (peso)]] -> 18
J24: E043 | K24: G2 | L24: I2 | M24: principal | N24: 1 | O24: E | P24: Medio | Q24: Alto | R24: Bajo | S24: Medio | T24: Alto | U24: GAFI - FT risks | V24: Centros regionales y hawala | W24: =IFERROR(_xlfn.XLOOKUP(tblEnlaces[[#This Row],[Eficiencia]],tblPesosCoste[Valor],#REF!),0)+IFERROR(_xlfn.XLOOKUP(tblEnlaces[[#This Row],[Capacidad]],tblPesosCoste[Valor],#REF!),0)+IFERROR(_xlfn.XLOOKUP(tblEnlaces[[#This Row],[Resiliencia]],tblPesosCoste[Valor],#REF!),0)+IFERROR(_xlfn.XLOOKUP(tblEnlaces[[#This Row],[Coste]],tblPesosCoste[Valor],tblPesosCoste[Coste]),0)+IFERROR(_xlfn.XLOOKUP(tblEnlaces[[#This Row],[Exposición]],tblPesosCoste[Valor],#REF!),0) -> 3 | X24: =IFERROR(_xlfn.XLOOKUP(tblEnlaces[[#This Row],[Coste]],tblPesosCoste[Valor],tblPesosCoste[Coste],0),0) -> 3 | Y24: =IFERROR(_xlfn.XLOOKUP(tblEnlaces[[#This Row],[Eficiencia]],tblPesosValorOperativo[Valor],tblPesosValorOperativo[Eficiencia],0),0) -> 5 | Z24: =IFERROR(_xlfn.XLOOKUP(tblEnlaces[[#This Row],[Exposición]],tblPesosValorOperativo[Valor],tblPesosValorOperativo[Exposición],0),0) -> 5 | AA24: =IFERROR(_xlfn.XLOOKUP(tblEnlaces[[#This Row],[Capacidad]],tblPesosValorOperativo[Valor],tblPesosValorOperativo[Capacidad],0),0) -> 3 | AB24: =IFERROR(_xlfn.XLOOKUP(tblEnlaces[[#This Row],[Resiliencia]],tblPesosValorOperativo[Valor],tblPesosValorOperativo[Resiliencia],0),0) -> 5 | AC24: =tblEnlaces[[#This Row],[Eficiencia (peso)]]+tblEnlaces[[#This Row],[Exposición (peso)]]+tblEnlaces[[#This Row],[Capacidad (peso)]]+tblEnlaces[[#This Row],[Resiliencia (peso)]] -> 18
J25: E053 | K25: I2 | L25: D | M25: secundario | N25: 1 | O25: E | P25: Medio | Q25: Alto | R25: Bajo | S25: Medio | T25: Medio-Alto | U25: GAFI - FT risks | V25: Hawala directa al receptor final | W25: =IFERROR(_xlfn.XLOOKUP(tblEnlaces[[#This Row],[Eficiencia]],tblPesosCoste[Valor],#REF!),0)+IFERROR(_xlfn.XLOOKUP(tblEnlaces[[#This Row],[Capacidad]],tblPesosCoste[Valor],#REF!),0)+IFERROR(_xlfn.XLOOKUP(tblEnlaces[[#This Row],[Resiliencia]],tblPesosCoste[Valor],#REF!),0)+IFERROR(_xlfn.XLOOKUP(tblEnlaces[[#This Row],[Coste]],tblPesosCoste[Valor],tblPesosCoste[Coste]),0)+IFERROR(_xlfn.XLOOKUP(tblEnlaces[[#This Row],[Exposición]],tblPesosCoste[Valor],#REF!),0) -> 3 | X25: =IFERROR(_xlfn.XLOOKUP(tblEnlaces[[#This Row],[Coste]],tblPesosCoste[Valor],tblPesosCoste[Coste],0),0) -> 3 | Y25: =IFERROR(_xlfn.XLOOKUP(tblEnlaces[[#This Row],[Eficiencia]],tblPesosValorOperativo[Valor],tblPesosValorOperativo[Eficiencia],0),0) -> 5 | Z25: =IFERROR(_xlfn.XLOOKUP(tblEnlaces[[#This Row],[Exposición]],tblPesosValorOperativo[Valor],tblPesosValorOperativo[Exposición],0),0) -> 5 | AA25: =IFERROR(_xlfn.XLOOKUP(tblEnlaces[[#This Row],[Capacidad]],tblPesosValorOperativo[Valor],tblPesosValorOperativo[Capacidad],0),0) -> 3 | AB25: =IFERROR(_xlfn.XLOOKUP(tblEnlaces[[#This Row],[Resiliencia]],tblPesosValorOperativo[Valor],tblPesosValorOperativo[Resiliencia],0),0) -> 4 | AC25: =tblEnlaces[[#This Row],[Eficiencia (peso)]]+tblEnlaces[[#This Row],[Exposición (peso)]]+tblEnlaces[[#This Row],[Capacidad (peso)]]+tblEnlaces[[#This Row],[Resiliencia (peso)]] -> 17
J26: E007 | K26: O2 | L26: I2 | M26: principal | N26: 1 | O26: T | P26: Medio | Q26: Alto | R26: Bajo | S26: Medio-Alto | T26: Alto | U26: GAFI - FT risks | V26: Flujos transfronterizos vía hawala/HOSSP | W26: =IFERROR(_xlfn.XLOOKUP(tblEnlaces[[#This Row],[Eficiencia]],tblPesosCoste[Valor],#REF!),0)+IFERROR(_xlfn.XLOOKUP(tblEnlaces[[#This Row],[Capacidad]],tblPesosCoste[Valor],#REF!),0)+IFERROR(_xlfn.XLOOKUP(tblEnlaces[[#This Row],[Resiliencia]],tblPesosCoste[Valor],#REF!),0)+IFERROR(_xlfn.XLOOKUP(tblEnlaces[[#This Row],[Coste]],tblPesosCoste[Valor],tblPesosCoste[Coste]),0)+IFERROR(_xlfn.XLOOKUP(tblEnlaces[[#This Row],[Exposición]],tblPesosCoste[Valor],#REF!),0) -> 3 | X26: =IFERROR(_xlfn.XLOOKUP(tblEnlaces[[#This Row],[Coste]],tblPesosCoste[Valor],tblPesosCoste[Coste],0),0) -> 3 | Y26: =IFERROR(_xlfn.XLOOKUP(tblEnlaces[[#This Row],[Eficiencia]],tblPesosValorOperativo[Valor],tblPesosValorOperativo[Eficiencia],0),0) -> 5 | Z26: =IFERROR(_xlfn.XLOOKUP(tblEnlaces[[#This Row],[Exposición]],tblPesosValorOperativo[Valor],tblPesosValorOperativo[Exposición],0),0) -> 5 | AA26: =IFERROR(_xlfn.XLOOKUP(tblEnlaces[[#This Row],[Capacidad]],tblPesosValorOperativo[Valor],tblPesosValorOperativo[Capacidad],0),0) -> 4 | AB26: =IFERROR(_xlfn.XLOOKUP(tblEnlaces[[#This Row],[Resiliencia]],tblPesosValorOperativo[Valor],tblPesosValorOperativo[Resiliencia],0),0) -> 5 | AC26: =tblEnlaces[[#This Row],[Eficiencia (peso)]]+tblEnlaces[[#This Row],[Exposición (peso)]]+tblEnlaces[[#This Row],[Capacidad (peso)]]+tblEnlaces[[#This Row],[Resiliencia (peso)]] -> 19
J27: E010 | K27: O3 | L27: I2 | M27: principal | N27: 1 | O27: E | P27: Medio | Q27: Alto | R27: Bajo | S27: Medio-Alto | T27: Alto | U27: GAFI - FT risks | V27: Recursos naturales → hawala en casos | W27: =IFERROR(_xlfn.XLOOKUP(tblEnlaces[[#This Row],[Eficiencia]],tblPesosCoste[Valor],#REF!),0)+IFERROR(_xlfn.XLOOKUP(tblEnlaces[[#This Row],[Capacidad]],tblPesosCoste[Valor],#REF!),0)+IFERROR(_xlfn.XLOOKUP(tblEnlaces[[#This Row],[Resiliencia]],tblPesosCoste[Valor],#REF!),0)+IFERROR(_xlfn.XLOOKUP(tblEnlaces[[#This Row],[Coste]],tblPesosCoste[Valor],tblPesosCoste[Coste]),0)+IFERROR(_xlfn.XLOOKUP(tblEnlaces[[#This Row],[Exposición]],tblPesosCoste[Valor],#REF!),0) -> 3 | X27: =IFERROR(_xlfn.XLOOKUP(tblEnlaces[[#This Row],[Coste]],tblPesosCoste[Valor],tblPesosCoste[Coste],0),0) -> 3 | Y27: =IFERROR(_xlfn.XLOOKUP(tblEnlaces[[#This Row],[Eficiencia]],tblPesosValorOperativo[Valor],tblPesosValorOperativo[Eficiencia],0),0) -> 5 | Z27: =IFERROR(_xlfn.XLOOKUP(tblEnlaces[[#This Row],[Exposición]],tblPesosValorOperativo[Valor],tblPesosValorOperativo[Exposición],0),0) -> 5 | AA27: =IFERROR(_xlfn.XLOOKUP(tblEnlaces[[#This Row],[Capacidad]],tblPesosValorOperativo[Valor],tblPesosValorOperativo[Capacidad],0),0) -> 4 | AB27: =IFERROR(_xlfn.XLOOKUP(tblEnlaces[[#This Row],[Resiliencia]],tblPesosValorOperativo[Valor],tblPesosValorOperativo[Resiliencia],0),0) -> 5 | AC27: =tblEnlaces[[#This Row],[Eficiencia (peso)]]+tblEnlaces[[#This Row],[Exposición (peso)]]+tblEnlaces[[#This Row],[Capacidad (peso)]]+tblEnlaces[[#This Row],[Resiliencia (peso)]] -> 19
B28: FLUJOS POSIBLES | J28: E027 | K28: I2 | L28: G2 | M28: principal | N28: 1 | O28: E | P28: Medio | Q28: Alto | R28: Bajo | S28: Medio-Alto | T28: Alto | U28: GAFI - FT risks | V28: Hawala y centros regionales | W28: =IFERROR(_xlfn.XLOOKUP(tblEnlaces[[#This Row],[Eficiencia]],tblPesosCoste[Valor],#REF!),0)+IFERROR(_xlfn.XLOOKUP(tblEnlaces[[#This Row],[Capacidad]],tblPesosCoste[Valor],#REF!),0)+IFERROR(_xlfn.XLOOKUP(tblEnlaces[[#This Row],[Resiliencia]],tblPesosCoste[Valor],#REF!),0)+IFERROR(_xlfn.XLOOKUP(tblEnlaces[[#This Row],[Coste]],tblPesosCoste[Valor],tblPesosCoste[Coste]),0)+IFERROR(_xlfn.XLOOKUP(tblEnlaces[[#This Row],[Exposición]],tblPesosCoste[Valor],#REF!),0) -> 3 | X28: =IFERROR(_xlfn.XLOOKUP(tblEnlaces[[#This Row],[Coste]],tblPesosCoste[Valor],tblPesosCoste[Coste],0),0) -> 3 | Y28: =IFERROR(_xlfn.XLOOKUP(tblEnlaces[[#This Row],[Eficiencia]],tblPesosValorOperativo[Valor],tblPesosValorOperativo[Eficiencia],0),0) -> 5 | Z28: =IFERROR(_xlfn.XLOOKUP(tblEnlaces[[#This Row],[Exposición]],tblPesosValorOperativo[Valor],tblPesosValorOperativo[Exposición],0),0) -> 5 | AA28: =IFERROR(_xlfn.XLOOKUP(tblEnlaces[[#This Row],[Capacidad]],tblPesosValorOperativo[Valor],tblPesosValorOperativo[Capacidad],0),0) -> 4 | AB28: =IFERROR(_xlfn.XLOOKUP(tblEnlaces[[#This Row],[Resiliencia]],tblPesosValorOperativo[Valor],tblPesosValorOperativo[Resiliencia],0),0) -> 5 | AC28: =tblEnlaces[[#This Row],[Eficiencia (peso)]]+tblEnlaces[[#This Row],[Exposición (peso)]]+tblEnlaces[[#This Row],[Capacidad (peso)]]+tblEnlaces[[#This Row],[Resiliencia (peso)]] -> 19
B29: Origen → Intermediario → Gestión → Intermediario → Destino | J29: E026 | K29: I2 | L29: G1 | M29: secundario | N29: 1 | O29: T | P29: Medio | Q29: Alto | R29: Bajo-Medio | S29: Medio | T29: Medio | U29: GAFI - FT risks | V29: Hawala alimenta gestión central | W29: =IFERROR(_xlfn.XLOOKUP(tblEnlaces[[#This Row],[Eficiencia]],tblPesosCoste[Valor],#REF!),0)+IFERROR(_xlfn.XLOOKUP(tblEnlaces[[#This Row],[Capacidad]],tblPesosCoste[Valor],#REF!),0)+IFERROR(_xlfn.XLOOKUP(tblEnlaces[[#This Row],[Resiliencia]],tblPesosCoste[Valor],#REF!),0)+IFERROR(_xlfn.XLOOKUP(tblEnlaces[[#This Row],[Coste]],tblPesosCoste[Valor],tblPesosCoste[Coste]),0)+IFERROR(_xlfn.XLOOKUP(tblEnlaces[[#This Row],[Exposición]],tblPesosCoste[Valor],#REF!),0) -> 3 | X29: =IFERROR(_xlfn.XLOOKUP(tblEnlaces[[#This Row],[Coste]],tblPesosCoste[Valor],tblPesosCoste[Coste],0),0) -> 3 | Y29: =IFERROR(_xlfn.XLOOKUP(tblEnlaces[[#This Row],[Eficiencia]],tblPesosValorOperativo[Valor],tblPesosValorOperativo[Eficiencia],0),0) -> 5 | Z29: =IFERROR(_xlfn.XLOOKUP(tblEnlaces[[#This Row],[Exposición]],tblPesosValorOperativo[Valor],tblPesosValorOperativo[Exposición],0),0) -> 4 | AA29: =IFERROR(_xlfn.XLOOKUP(tblEnlaces[[#This Row],[Capacidad]],tblPesosValorOperativo[Valor],tblPesosValorOperativo[Capacidad],0),0) -> 3 | AB29: =IFERROR(_xlfn.XLOOKUP(tblEnlaces[[#This Row],[Resiliencia]],tblPesosValorOperativo[Valor],tblPesosValorOperativo[Resiliencia],0),0) -> 3 | AC29: =tblEnlaces[[#This Row],[Eficiencia (peso)]]+tblEnlaces[[#This Row],[Exposición (peso)]]+tblEnlaces[[#This Row],[Capacidad (peso)]]+tblEnlaces[[#This Row],[Resiliencia (peso)]] -> 15
B30: (ej. Extorsión → efectivo → hawala → centro regional → efectivo → combatiente) | J30: E003 | K30: O1 | L30: I3 | M30: principal | N30: 1 | O30: E | P30: Medio | Q30: Alto | R30: Medio | S30: Medio | T30: Medio | U30: GAFI - FT risks | V30: Uso de MVTS/remesas en casos ISIL | W30: =IFERROR(_xlfn.XLOOKUP(tblEnlaces[[#This Row],[Eficiencia]],tblPesosCoste[Valor],#REF!),0)+IFERROR(_xlfn.XLOOKUP(tblEnlaces[[#This Row],[Capacidad]],tblPesosCoste[Valor],#REF!),0)+IFERROR(_xlfn.XLOOKUP(tblEnlaces[[#This Row],[Resiliencia]],tblPesosCoste[Valor],#REF!),0)+IFERROR(_xlfn.XLOOKUP(tblEnlaces[[#This Row],[Coste]],tblPesosCoste[Valor],tblPesosCoste[Coste]),0)+IFERROR(_xlfn.XLOOKUP(tblEnlaces[[#This Row],[Exposición]],tblPesosCoste[Valor],#REF!),0) -> 3 | X30: =IFERROR(_xlfn.XLOOKUP(tblEnlaces[[#This Row],[Coste]],tblPesosCoste[Valor],tblPesosCoste[Coste],0),0) -> 3 | Y30: =IFERROR(_xlfn.XLOOKUP(tblEnlaces[[#This Row],[Eficiencia]],tblPesosValorOperativo[Valor],tblPesosValorOperativo[Eficiencia],0),0) -> 5 | Z30: =IFERROR(_xlfn.XLOOKUP(tblEnlaces[[#This Row],[Exposición]],tblPesosValorOperativo[Valor],tblPesosValorOperativo[Exposición],0),0) -> 3 | AA30: =IFERROR(_xlfn.XLOOKUP(tblEnlaces[[#This Row],[Capacidad]],tblPesosValorOperativo[Valor],tblPesosValorOperativo[Capacidad],0),0) -> 3 | AB30: =IFERROR(_xlfn.XLOOKUP(tblEnlaces[[#This Row],[Resiliencia]],tblPesosValorOperativo[Valor],tblPesosValorOperativo[Resiliencia],0),0) -> 3 | AC30: =tblEnlaces[[#This Row],[Eficiencia (peso)]]+tblEnlaces[[#This Row],[Exposición (peso)]]+tblEnlaces[[#This Row],[Capacidad (peso)]]+tblEnlaces[[#This Row],[Resiliencia (peso)]] -> 14
J31: E008 | K31: O2 | L31: I3 | M31: secundario | N31: 1 | O31: T | P31: Medio | Q31: Alto | R31: Medio | S31: Medio | T31: Medio | U31: GAFI - FT risks | V31: Remesas/MVTS asociadas a beneficios delictivos | W31: =IFERROR(_xlfn.XLOOKUP(tblEnlaces[[#This Row],[Eficiencia]],tblPesosCoste[Valor],#REF!),0)+IFERROR(_xlfn.XLOOKUP(tblEnlaces[[#This Row],[Capacidad]],tblPesosCoste[Valor],#REF!),0)+IFERROR(_xlfn.XLOOKUP(tblEnlaces[[#This Row],[Resiliencia]],tblPesosCoste[Valor],#REF!),0)+IFERROR(_xlfn.XLOOKUP(tblEnlaces[[#This Row],[Coste]],tblPesosCoste[Valor],tblPesosCoste[Coste]),0)+IFERROR(_xlfn.XLOOKUP(tblEnlaces[[#This Row],[Exposición]],tblPesosCoste[Valor],#REF!),0) -> 3 | X31: =IFERROR(_xlfn.XLOOKUP(tblEnlaces[[#This Row],[Coste]],tblPesosCoste[Valor],tblPesosCoste[Coste],0),0) -> 3 | Y31: =IFERROR(_xlfn.XLOOKUP(tblEnlaces[[#This Row],[Eficiencia]],tblPesosValorOperativo[Valor],tblPesosValorOperativo[Eficiencia],0),0) -> 5 | Z31: =IFERROR(_xlfn.XLOOKUP(tblEnlaces[[#This Row],[Exposición]],tblPesosValorOperativo[Valor],tblPesosValorOperativo[Exposición],0),0) -> 3 | AA31: =IFERROR(_xlfn.XLOOKUP(tblEnlaces[[#This Row],[Capacidad]],tblPesosValorOperativo[Valor],tblPesosValorOperativo[Capacidad],0),0) -> 3 | AB31: =IFERROR(_xlfn.XLOOKUP(tblEnlaces[[#This Row],[Resiliencia]],tblPesosValorOperativo[Valor],tblPesosValorOperativo[Resiliencia],0),0) -> 3 | AC31: =tblEnlaces[[#This Row],[Eficiencia (peso)]]+tblEnlaces[[#This Row],[Exposición (peso)]]+tblEnlaces[[#This Row],[Capacidad (peso)]]+tblEnlaces[[#This Row],[Resiliencia (peso)]] -> 14
J32: E019 | K32: O6 | L32: I3 | M32: secundario | N32: 1 | O32: E | P32: Medio | Q32: Alto | R32: Medio | S32: Medio | T32: Medio | U32: GAFI - FT risks | V32: ISIL: MVTS/remesas | W32: =IFERROR(_xlfn.XLOOKUP(tblEnlaces[[#This Row],[Eficiencia]],tblPesosCoste[Valor],#REF!),0)+IFERROR(_xlfn.XLOOKUP(tblEnlaces[[#This Row],[Capacidad]],tblPesosCoste[Valor],#REF!),0)+IFERROR(_xlfn.XLOOKUP(tblEnlaces[[#This Row],[Resiliencia]],tblPesosCoste[Valor],#REF!),0)+IFERROR(_xlfn.XLOOKUP(tblEnlaces[[#This Row],[Coste]],tblPesosCoste[Valor],tblPesosCoste[Coste]),0)+IFERROR(_xlfn.XLOOKUP(tblEnlaces[[#This Row],[Exposición]],tblPesosCoste[Valor],#REF!),0) -> 3 | X32: =IFERROR(_xlfn.XLOOKUP(tblEnlaces[[#This Row],[Coste]],tblPesosCoste[Valor],tblPesosCoste[Coste],0),0) -> 3 | Y32: =IFERROR(_xlfn.XLOOKUP(tblEnlaces[[#This Row],[Eficiencia]],tblPesosValorOperativo[Valor],tblPesosValorOperativo[Eficiencia],0),0) -> 5 | Z32: =IFERROR(_xlfn.XLOOKUP(tblEnlaces[[#This Row],[Exposición]],tblPesosValorOperativo[Valor],tblPesosValorOperativo[Exposición],0),0) -> 3 | AA32: =IFERROR(_xlfn.XLOOKUP(tblEnlaces[[#This Row],[Capacidad]],tblPesosValorOperativo[Valor],tblPesosValorOperativo[Capacidad],0),0) -> 3 | AB32: =IFERROR(_xlfn.XLOOKUP(tblEnlaces[[#This Row],[Resiliencia]],tblPesosValorOperativo[Valor],tblPesosValorOperativo[Resiliencia],0),0) -> 3 | AC32: =tblEnlaces[[#This Row],[Eficiencia (peso)]]+tblEnlaces[[#This Row],[Exposición (peso)]]+tblEnlaces[[#This Row],[Capacidad (peso)]]+tblEnlaces[[#This Row],[Resiliencia (peso)]] -> 14
J33: E029 | K33: I3 | L33: G3 | M33: secundario | N33: 1 | O33: T | P33: Medio | Q33: Alto | R33: Medio | S33: Medio | T33: Medio | U33: GAFI - FT risks | V33: MVTS y facilitadores externos | W33: =IFERROR(_xlfn.XLOOKUP(tblEnlaces[[#This Row],[Eficiencia]],tblPesosCoste[Valor],#REF!),0)+IFERROR(_xlfn.XLOOKUP(tblEnlaces[[#This Row],[Capacidad]],tblPesosCoste[Valor],#REF!),0)+IFERROR(_xlfn.XLOOKUP(tblEnlaces[[#This Row],[Resiliencia]],tblPesosCoste[Valor],#REF!),0)+IFERROR(_xlfn.XLOOKUP(tblEnlaces[[#This Row],[Coste]],tblPesosCoste[Valor],tblPesosCoste[Coste]),0)+IFERROR(_xlfn.XLOOKUP(tblEnlaces[[#This Row],[Exposición]],tblPesosCoste[Valor],#REF!),0) -> 3 | X33: =IFERROR(_xlfn.XLOOKUP(tblEnlaces[[#This Row],[Coste]],tblPesosCoste[Valor],tblPesosCoste[Coste],0),0) -> 3 | Y33: =IFERROR(_xlfn.XLOOKUP(tblEnlaces[[#This Row],[Eficiencia]],tblPesosValorOperativo[Valor],tblPesosValorOperativo[Eficiencia],0),0) -> 5 | Z33: =IFERROR(_xlfn.XLOOKUP(tblEnlaces[[#This Row],[Exposición]],tblPesosValorOperativo[Valor],tblPesosValorOperativo[Exposición],0),0) -> 3 | AA33: =IFERROR(_xlfn.XLOOKUP(tblEnlaces[[#This Row],[Capacidad]],tblPesosValorOperativo[Valor],tblPesosValorOperativo[Capacidad],0),0) -> 3 | AB33: =IFERROR(_xlfn.XLOOKUP(tblEnlaces[[#This Row],[Resiliencia]],tblPesosValorOperativo[Valor],tblPesosValorOperativo[Resiliencia],0),0) -> 3 | AC33: =tblEnlaces[[#This Row],[Eficiencia (peso)]]+tblEnlaces[[#This Row],[Exposición (peso)]]+tblEnlaces[[#This Row],[Capacidad (peso)]]+tblEnlaces[[#This Row],[Resiliencia (peso)]] -> 14
J34: E044 | K34: G2 | L34: I3 | M34: principal | N34: 1 | O34: E | P34: Medio | Q34: Alto | R34: Medio | S34: Medio | T34: Medio | U34: GAFI - FT risks | V34: Centros regionales y MVTS | W34: =IFERROR(_xlfn.XLOOKUP(tblEnlaces[[#This Row],[Eficiencia]],tblPesosCoste[Valor],#REF!),0)+IFERROR(_xlfn.XLOOKUP(tblEnlaces[[#This Row],[Capacidad]],tblPesosCoste[Valor],#REF!),0)+IFERROR(_xlfn.XLOOKUP(tblEnlaces[[#This Row],[Resiliencia]],tblPesosCoste[Valor],#REF!),0)+IFERROR(_xlfn.XLOOKUP(tblEnlaces[[#This Row],[Coste]],tblPesosCoste[Valor],tblPesosCoste[Coste]),0)+IFERROR(_xlfn.XLOOKUP(tblEnlaces[[#This Row],[Exposición]],tblPesosCoste[Valor],#REF!),0) -> 3 | X34: =IFERROR(_xlfn.XLOOKUP(tblEnlaces[[#This Row],[Coste]],tblPesosCoste[Valor],tblPesosCoste[Coste],0),0) -> 3 | Y34: =IFERROR(_xlfn.XLOOKUP(tblEnlaces[[#This Row],[Eficiencia]],tblPesosValorOperativo[Valor],tblPesosValorOperativo[Eficiencia],0),0) -> 5 | Z34: =IFERROR(_xlfn.XLOOKUP(tblEnlaces[[#This Row],[Exposición]],tblPesosValorOperativo[Valor],tblPesosValorOperativo[Exposición],0),0) -> 3 | AA34: =IFERROR(_xlfn.XLOOKUP(tblEnlaces[[#This Row],[Capacidad]],tblPesosValorOperativo[Valor],tblPesosValorOperativo[Capacidad],0),0) -> 3 | AB34: =IFERROR(_xlfn.XLOOKUP(tblEnlaces[[#This Row],[Resiliencia]],tblPesosValorOperativo[Valor],tblPesosValorOperativo[Resiliencia],0),0) -> 3 | AC34: =tblEnlaces[[#This Row],[Eficiencia (peso)]]+tblEnlaces[[#This Row],[Exposición (peso)]]+tblEnlaces[[#This Row],[Capacidad (peso)]]+tblEnlaces[[#This Row],[Resiliencia (peso)]] -> 14
J35: E054 | K35: I3 | L35: D | M35: secundario | N35: 1 | O35: E | P35: Medio | Q35: Alto | R35: Medio | S35: Medio | T35: Medio | U35: GAFI - FT risks | V35: MVTS/remesas directas al receptor | W35: =IFERROR(_xlfn.XLOOKUP(tblEnlaces[[#This Row],[Eficiencia]],tblPesosCoste[Valor],#REF!),0)+IFERROR(_xlfn.XLOOKUP(tblEnlaces[[#This Row],[Capacidad]],tblPesosCoste[Valor],#REF!),0)+IFERROR(_xlfn.XLOOKUP(tblEnlaces[[#This Row],[Resiliencia]],tblPesosCoste[Valor],#REF!),0)+IFERROR(_xlfn.XLOOKUP(tblEnlaces[[#This Row],[Coste]],tblPesosCoste[Valor],tblPesosCoste[Coste]),0)+IFERROR(_xlfn.XLOOKUP(tblEnlaces[[#This Row],[Exposición]],tblPesosCoste[Valor],#REF!),0) -> 3 | X35: =IFERROR(_xlfn.XLOOKUP(tblEnlaces[[#This Row],[Coste]],tblPesosCoste[Valor],tblPesosCoste[Coste],0),0) -> 3 | Y35: =IFERROR(_xlfn.XLOOKUP(tblEnlaces[[#This Row],[Eficiencia]],tblPesosValorOperativo[Valor],tblPesosValorOperativo[Eficiencia],0),0) -> 5 | Z35: =IFERROR(_xlfn.XLOOKUP(tblEnlaces[[#This Row],[Exposición]],tblPesosValorOperativo[Valor],tblPesosValorOperativo[Exposición],0),0) -> 3 | AA35: =IFERROR(_xlfn.XLOOKUP(tblEnlaces[[#This Row],[Capacidad]],tblPesosValorOperativo[Valor],tblPesosValorOperativo[Capacidad],0),0) -> 3 | AB35: =IFERROR(_xlfn.XLOOKUP(tblEnlaces[[#This Row],[Resiliencia]],tblPesosValorOperativo[Valor],tblPesosValorOperativo[Resiliencia],0),0) -> 3 | AC35: =tblEnlaces[[#This Row],[Eficiencia (peso)]]+tblEnlaces[[#This Row],[Exposición (peso)]]+tblEnlaces[[#This Row],[Capacidad (peso)]]+tblEnlaces[[#This Row],[Resiliencia (peso)]] -> 14
J36: E011 | K36: O3 | L36: I3 | M36: principal | N36: 1 | O36: E | P36: Medio | Q36: Alto | R36: Medio | S36: Medio-Alto | T36: Medio | U36: GAFI - FT risks | V36: Recursos naturales → remesas online/MVTS | W36: =IFERROR(_xlfn.XLOOKUP(tblEnlaces[[#This Row],[Eficiencia]],tblPesosCoste[Valor],#REF!),0)+IFERROR(_xlfn.XLOOKUP(tblEnlaces[[#This Row],[Capacidad]],tblPesosCoste[Valor],#REF!),0)+IFERROR(_xlfn.XLOOKUP(tblEnlaces[[#This Row],[Resiliencia]],tblPesosCoste[Valor],#REF!),0)+IFERROR(_xlfn.XLOOKUP(tblEnlaces[[#This Row],[Coste]],tblPesosCoste[Valor],tblPesosCoste[Coste]),0)+IFERROR(_xlfn.XLOOKUP(tblEnlaces[[#This Row],[Exposición]],tblPesosCoste[Valor],#REF!),0) -> 3 | X36: =IFERROR(_xlfn.XLOOKUP(tblEnlaces[[#This Row],[Coste]],tblPesosCoste[Valor],tblPesosCoste[Coste],0),0) -> 3 | Y36: =IFERROR(_xlfn.XLOOKUP(tblEnlaces[[#This Row],[Eficiencia]],tblPesosValorOperativo[Valor],tblPesosValorOperativo[Eficiencia],0),0) -> 5 | Z36: =IFERROR(_xlfn.XLOOKUP(tblEnlaces[[#This Row],[Exposición]],tblPesosValorOperativo[Valor],tblPesosValorOperativo[Exposición],0),0) -> 3 | AA36: =IFERROR(_xlfn.XLOOKUP(tblEnlaces[[#This Row],[Capacidad]],tblPesosValorOperativo[Valor],tblPesosValorOperativo[Capacidad],0),0) -> 4 | AB36: =IFERROR(_xlfn.XLOOKUP(tblEnlaces[[#This Row],[Resiliencia]],tblPesosValorOperativo[Valor],tblPesosValorOperativo[Resiliencia],0),0) -> 3 | AC36: =tblEnlaces[[#This Row],[Eficiencia (peso)]]+tblEnlaces[[#This Row],[Exposición (peso)]]+tblEnlaces[[#This Row],[Capacidad (peso)]]+tblEnlaces[[#This Row],[Resiliencia (peso)]] -> 15
J37: E028 | K37: I3 | L37: G2 | M37: principal | N37: 1 | O37: E | P37: Medio | Q37: Alto | R37: Medio | S37: Medio-Alto | T37: Medio | U37: GAFI - FT risks | V37: MVTS/remesas y facilitadores regionales | W37: =IFERROR(_xlfn.XLOOKUP(tblEnlaces[[#This Row],[Eficiencia]],tblPesosCoste[Valor],#REF!),0)+IFERROR(_xlfn.XLOOKUP(tblEnlaces[[#This Row],[Capacidad]],tblPesosCoste[Valor],#REF!),0)+IFERROR(_xlfn.XLOOKUP(tblEnlaces[[#This Row],[Resiliencia]],tblPesosCoste[Valor],#REF!),0)+IFERROR(_xlfn.XLOOKUP(tblEnlaces[[#This Row],[Coste]],tblPesosCoste[Valor],tblPesosCoste[Coste]),0)+IFERROR(_xlfn.XLOOKUP(tblEnlaces[[#This Row],[Exposición]],tblPesosCoste[Valor],#REF!),0) -> 3 | X37: =IFERROR(_xlfn.XLOOKUP(tblEnlaces[[#This Row],[Coste]],tblPesosCoste[Valor],tblPesosCoste[Coste],0),0) -> 3 | Y37: =IFERROR(_xlfn.XLOOKUP(tblEnlaces[[#This Row],[Eficiencia]],tblPesosValorOperativo[Valor],tblPesosValorOperativo[Eficiencia],0),0) -> 5 | Z37: =IFERROR(_xlfn.XLOOKUP(tblEnlaces[[#This Row],[Exposición]],tblPesosValorOperativo[Valor],tblPesosValorOperativo[Exposición],0),0) -> 3 | AA37: =IFERROR(_xlfn.XLOOKUP(tblEnlaces[[#This Row],[Capacidad]],tblPesosValorOperativo[Valor],tblPesosValorOperativo[Capacidad],0),0) -> 4 | AB37: =IFERROR(_xlfn.XLOOKUP(tblEnlaces[[#This Row],[Resiliencia]],tblPesosValorOperativo[Valor],tblPesosValorOperativo[Resiliencia],0),0) -> 3 | AC37: =tblEnlaces[[#This Row],[Eficiencia (peso)]]+tblEnlaces[[#This Row],[Exposición (peso)]]+tblEnlaces[[#This Row],[Capacidad (peso)]]+tblEnlaces[[#This Row],[Resiliencia (peso)]] -> 15
J38: E032 | K38: I5 | L38: G3 | M38: principal | N38: 1 | O38: T | P38: Medio | Q38: Alto | R38: Medio-Alto | S38: Medio | T38: Medio | U38: GAFI - FT risks | V38: Pagos online y facilitadores | W38: =IFERROR(_xlfn.XLOOKUP(tblEnlaces[[#This Row],[Eficiencia]],tblPesosCoste[Valor],#REF!),0)+IFERROR(_xlfn.XLOOKUP(tblEnlaces[[#This Row],[Capacidad]],tblPesosCoste[Valor],#REF!),0)+IFERROR(_xlfn.XLOOKUP(tblEnlaces[[#This Row],[Resiliencia]],tblPesosCoste[Valor],#REF!),0)+IFERROR(_xlfn.XLOOKUP(tblEnlaces[[#This Row],[Coste]],tblPesosCoste[Valor],tblPesosCoste[Coste]),0)+IFERROR(_xlfn.XLOOKUP(tblEnlaces[[#This Row],[Exposición]],tblPesosCoste[Valor],#REF!),0) -> 3 | X38: =IFERROR(_xlfn.XLOOKUP(tblEnlaces[[#This Row],[Coste]],tblPesosCoste[Valor],tblPesosCoste[Coste],0),0) -> 3 | Y38: =IFERROR(_xlfn.XLOOKUP(tblEnlaces[[#This Row],[Eficiencia]],tblPesosValorOperativo[Valor],tblPesosValorOperativo[Eficiencia],0),0) -> 5 | Z38: =IFERROR(_xlfn.XLOOKUP(tblEnlaces[[#This Row],[Exposición]],tblPesosValorOperativo[Valor],tblPesosValorOperativo[Exposición],0),0) -> 2 | AA38: =IFERROR(_xlfn.XLOOKUP(tblEnlaces[[#This Row],[Capacidad]],tblPesosValorOperativo[Valor],tblPesosValorOperativo[Capacidad],0),0) -> 3 | AB38: =IFERROR(_xlfn.XLOOKUP(tblEnlaces[[#This Row],[Resiliencia]],tblPesosValorOperativo[Valor],tblPesosValorOperativo[Resiliencia],0),0) -> 3 | AC38: =tblEnlaces[[#This Row],[Eficiencia (peso)]]+tblEnlaces[[#This Row],[Exposición (peso)]]+tblEnlaces[[#This Row],[Capacidad (peso)]]+tblEnlaces[[#This Row],[Resiliencia (peso)]] -> 13
J39: E047 | K39: G3 | L39: I5 | M39: principal | N39: 1 | O39: T | P39: Medio | Q39: Alto | R39: Medio-Alto | S39: Medio | T39: Medio | U39: GAFI - FT risks | V39: Facilitador → pagos online | W39: =IFERROR(_xlfn.XLOOKUP(tblEnlaces[[#This Row],[Eficiencia]],tblPesosCoste[Valor],#REF!),0)+IFERROR(_xlfn.XLOOKUP(tblEnlaces[[#This Row],[Capacidad]],tblPesosCoste[Valor],#REF!),0)+IFERROR(_xlfn.XLOOKUP(tblEnlaces[[#This Row],[Resiliencia]],tblPesosCoste[Valor],#REF!),0)+IFERROR(_xlfn.XLOOKUP(tblEnlaces[[#This Row],[Coste]],tblPesosCoste[Valor],tblPesosCoste[Coste]),0)+IFERROR(_xlfn.XLOOKUP(tblEnlaces[[#This Row],[Exposición]],tblPesosCoste[Valor],#REF!),0) -> 3 | X39: =IFERROR(_xlfn.XLOOKUP(tblEnlaces[[#This Row],[Coste]],tblPesosCoste[Valor],tblPesosCoste[Coste],0),0) -> 3 | Y39: =IFERROR(_xlfn.XLOOKUP(tblEnlaces[[#This Row],[Eficiencia]],tblPesosValorOperativo[Valor],tblPesosValorOperativo[Eficiencia],0),0) -> 5 | Z39: =IFERROR(_xlfn.XLOOKUP(tblEnlaces[[#This Row],[Exposición]],tblPesosValorOperativo[Valor],tblPesosValorOperativo[Exposición],0),0) -> 2 | AA39: =IFERROR(_xlfn.XLOOKUP(tblEnlaces[[#This Row],[Capacidad]],tblPesosValorOperativo[Valor],tblPesosValorOperativo[Capacidad],0),0) -> 3 | AB39: =IFERROR(_xlfn.XLOOKUP(tblEnlaces[[#This Row],[Resiliencia]],tblPesosValorOperativo[Valor],tblPesosValorOperativo[Resiliencia],0),0) -> 3 | AC39: =tblEnlaces[[#This Row],[Eficiencia (peso)]]+tblEnlaces[[#This Row],[Exposición (peso)]]+tblEnlaces[[#This Row],[Capacidad (peso)]]+tblEnlaces[[#This Row],[Resiliencia (peso)]] -> 13
J40: E001 | K40: O1 | L40: I1 | M40: principal | N40: 1 | O40: T | P40: Bajo | Q40: Medio | R40: Bajo | S40: Alto | T40: Alto | U40: GAFI - FT risks | V40: Coerción/extorsión y uso intensivo de efectivo | W40: =IFERROR(_xlfn.XLOOKUP(tblEnlaces[[#This Row],[Eficiencia]],tblPesosCoste[Valor],#REF!),0)+IFERROR(_xlfn.XLOOKUP(tblEnlaces[[#This Row],[Capacidad]],tblPesosCoste[Valor],#REF!),0)+IFERROR(_xlfn.XLOOKUP(tblEnlaces[[#This Row],[Resiliencia]],tblPesosCoste[Valor],#REF!),0)+IFERROR(_xlfn.XLOOKUP(tblEnlaces[[#This Row],[Coste]],tblPesosCoste[Valor],tblPesosCoste[Coste]),0)+IFERROR(_xlfn.XLOOKUP(tblEnlaces[[#This Row],[Exposición]],tblPesosCoste[Valor],#REF!),0) -> 5 | X40: =IFERROR(_xlfn.XLOOKUP(tblEnlaces[[#This Row],[Coste]],tblPesosCoste[Valor],tblPesosCoste[Coste],0),0) -> 5 | Y40: =IFERROR(_xlfn.XLOOKUP(tblEnlaces[[#This Row],[Eficiencia]],tblPesosValorOperativo[Valor],tblPesosValorOperativo[Eficiencia],0),0) -> 3 | Z40: =IFERROR(_xlfn.XLOOKUP(tblEnlaces[[#This Row],[Exposición]],tblPesosValorOperativo[Valor],tblPesosValorOperativo[Exposición],0),0) -> 5 | AA40: =IFERROR(_xlfn.XLOOKUP(tblEnlaces[[#This Row],[Capacidad]],tblPesosValorOperativo[Valor],tblPesosValorOperativo[Capacidad],0),0) -> 5 | AB40: =IFERROR(_xlfn.XLOOKUP(tblEnlaces[[#This Row],[Resiliencia]],tblPesosValorOperativo[Valor],tblPesosValorOperativo[Resiliencia],0),0) -> 5 | AC40: =tblEnlaces[[#This Row],[Eficiencia (peso)]]+tblEnlaces[[#This Row],[Exposición (peso)]]+tblEnlaces[[#This Row],[Capacidad (peso)]]+tblEnlaces[[#This Row],[Resiliencia (peso)]] -> 18
J41: E042 | K41: G2 | L41: I1 | M41: principal | N41: 1 | O41: T | P41: Bajo | Q41: Medio | R41: Bajo | S41: Medio | T41: Alto | U41: GAFI - FT risks | V41: Centros regionales y efectivo | W41: =IFERROR(_xlfn.XLOOKUP(tblEnlaces[[#This Row],[Eficiencia]],tblPesosCoste[Valor],#REF!),0)+IFERROR(_xlfn.XLOOKUP(tblEnlaces[[#This Row],[Capacidad]],tblPesosCoste[Valor],#REF!),0)+IFERROR(_xlfn.XLOOKUP(tblEnlaces[[#This Row],[Resiliencia]],tblPesosCoste[Valor],#REF!),0)+IFERROR(_xlfn.XLOOKUP(tblEnlaces[[#This Row],[Coste]],tblPesosCoste[Valor],tblPesosCoste[Coste]),0)+IFERROR(_xlfn.XLOOKUP(tblEnlaces[[#This Row],[Exposición]],tblPesosCoste[Valor],#REF!),0) -> 5 | X41: =IFERROR(_xlfn.XLOOKUP(tblEnlaces[[#This Row],[Coste]],tblPesosCoste[Valor],tblPesosCoste[Coste],0),0) -> 5 | Y41: =IFERROR(_xlfn.XLOOKUP(tblEnlaces[[#This Row],[Eficiencia]],tblPesosValorOperativo[Valor],tblPesosValorOperativo[Eficiencia],0),0) -> 3 | Z41: =IFERROR(_xlfn.XLOOKUP(tblEnlaces[[#This Row],[Exposición]],tblPesosValorOperativo[Valor],tblPesosValorOperativo[Exposición],0),0) -> 5 | AA41: =IFERROR(_xlfn.XLOOKUP(tblEnlaces[[#This Row],[Capacidad]],tblPesosValorOperativo[Valor],tblPesosValorOperativo[Capacidad],0),0) -> 3 | AB41: =IFERROR(_xlfn.XLOOKUP(tblEnlaces[[#This Row],[Resiliencia]],tblPesosValorOperativo[Valor],tblPesosValorOperativo[Resiliencia],0),0) -> 5 | AC41: =tblEnlaces[[#This Row],[Eficiencia (peso)]]+tblEnlaces[[#This Row],[Exposición (peso)]]+tblEnlaces[[#This Row],[Capacidad (peso)]]+tblEnlaces[[#This Row],[Resiliencia (peso)]] -> 16
J42: E052 | K42: I1 | L42: D | M42: secundario | N42: 1 | O42: T | P42: Bajo | Q42: Medio | R42: Bajo | S42: Medio | T42: Medio-Alto | U42: GAFI - FT risks | V42: Ruta directa en redes descentralizadas | W42: =IFERROR(_xlfn.XLOOKUP(tblEnlaces[[#This Row],[Eficiencia]],tblPesosCoste[Valor],#REF!),0)+IFERROR(_xlfn.XLOOKUP(tblEnlaces[[#This Row],[Capacidad]],tblPesosCoste[Valor],#REF!),0)+IFERROR(_xlfn.XLOOKUP(tblEnlaces[[#This Row],[Resiliencia]],tblPesosCoste[Valor],#REF!),0)+IFERROR(_xlfn.XLOOKUP(tblEnlaces[[#This Row],[Coste]],tblPesosCoste[Valor],tblPesosCoste[Coste]),0)+IFERROR(_xlfn.XLOOKUP(tblEnlaces[[#This Row],[Exposición]],tblPesosCoste[Valor],#REF!),0) -> 5 | X42: =IFERROR(_xlfn.XLOOKUP(tblEnlaces[[#This Row],[Coste]],tblPesosCoste[Valor],tblPesosCoste[Coste],0),0) -> 5 | Y42: =IFERROR(_xlfn.XLOOKUP(tblEnlaces[[#This Row],[Eficiencia]],tblPesosValorOperativo[Valor],tblPesosValorOperativo[Eficiencia],0),0) -> 3 | Z42: =IFERROR(_xlfn.XLOOKUP(tblEnlaces[[#This Row],[Exposición]],tblPesosValorOperativo[Valor],tblPesosValorOperativo[Exposición],0),0) -> 5 | AA42: =IFERROR(_xlfn.XLOOKUP(tblEnlaces[[#This Row],[Capacidad]],tblPesosValorOperativo[Valor],tblPesosValorOperativo[Capacidad],0),0) -> 3 | AB42: =IFERROR(_xlfn.XLOOKUP(tblEnlaces[[#This Row],[Resiliencia]],tblPesosValorOperativo[Valor],tblPesosValorOperativo[Resiliencia],0),0) -> 4 | AC42: =tblEnlaces[[#This Row],[Eficiencia (peso)]]+tblEnlaces[[#This Row],[Exposición (peso)]]+tblEnlaces[[#This Row],[Capacidad (peso)]]+tblEnlaces[[#This Row],[Resiliencia (peso)]] -> 15
... J58: E024 | K58: I1 | L58: I4 | M58: secundario | N58: 1 | O58: T | P58: Medio | Q58: Medio-Alto | R58: Medio | S58: Medio | T58: Medio | U58: GAFI - FT risks | V58: Efectivo combinado con dinero móvil | W58: =IFERROR(_xlfn.XLOOKUP(tblEnlaces[[#This Row],[Eficiencia]],tblPesosCoste[Valor],#REF!),0)+IFERROR(_xlfn.XLOOKUP(tblEnlaces[[#This Row],[Capacidad]],tblPesosCoste[Valor],#REF!),0)+IFERROR(_xlfn.XLOOKUP(tblEnlaces[[#This Row],[Resiliencia]],tblPesosCoste[Valor],#REF!),0)+IFERROR(_xlfn.XLOOKUP(tblEnlaces[[#This Row],[Coste]],tblPesosCoste[Valor],tblPesosCoste[Coste]),0)+IFERROR(_xlfn.XLOOKUP(tblEnlaces[[#This Row],[Exposición]],tblPesosCoste[Valor],#REF!),0) -> 3 | X58: =IFERROR(_xlfn.XLOOKUP(tblEnlaces[[#This Row],[Coste]],tblPesosCoste[Valor],tblPesosCoste[Coste],0),0) -> 3 | Y58: =IFERROR(_xlfn.XLOOKUP(tblEnlaces[[#This Row],[Eficiencia]],tblPesosValorOperativo[Valor],tblPesosValorOperativo[Eficiencia],0),0) -> 4 | Z58: =IFERROR(_xlfn.XLOOKUP(tblEnlaces[[#This Row],[Exposición]],tblPesosValorOperativo[Valor],tblPesosValorOperativo[Exposición],0),0) -> 3 | AA58: =IFERROR(_xlfn.XLOOKUP(tblEnlaces[[#This Row],[Capacidad]],tblPesosValorOperativo[Valor],tblPesosValorOperativo[Capacidad],0),0) -> 3 | AB58: =IFERROR(_xlfn.XLOOKUP(tblEnlaces[[#This Row],[Resiliencia]],tblPesosValorOperativo[Valor],tblPesosValorOperativo[Resiliencia],0),0) -> 3 | AC58: =tblEnlaces[[#This Row],[Eficiencia (peso)]]+tblEnlaces[[#This Row],[Exposición (peso)]]+tblEnlaces[[#This Row],[Capacidad (peso)]]+tblEnlaces[[#This Row],[Resiliencia (peso)]] -> 13

Sheet Grafo Visual

Sheet MatrizDeAdyacencia
D2: =VLOOKUP(tblMatrizDeAdyacencia[[#Headers],[O1]],tblNodos[#All],2,FALSE) -> Coerción y cobros forzosos | E2: =VLOOKUP(tblMatrizDeAdyacencia[[#Headers],[O2]],tblNodos[#All],2,FALSE) -> Contrabando / tráfico / comercio ilícito | F2: =VLOOKUP(tblMatrizDeAdyacencia[[#Headers],[O3]],tblNodos[#All],2,FALSE) -> Explotación de recursos naturales | G2: =VLOOKUP(tblMatrizDeAdyacencia[[#Headers],[O4]],tblNodos[#All],2,FALSE) -> Autofinanciación lícita / microfinanciación | H2: =VLOOKUP(tblMatrizDeAdyacencia[[#Headers],[O5]],tblNodos[#All],2,FALSE) -> Actividades económicas formales / negocios | I2: =VLOOKUP(tblMatrizDeAdyacencia[[#Headers],[O6]],tblNodos[#All],2,FALSE) -> Donaciones / crowdfunding / apoyo online | J2: =VLOOKUP(tblMatrizDeAdyacencia[[#Headers],[I1]],tblNodos[#All],2,FALSE) -> Efectivo | K2: =VLOOKUP(tblMatrizDeAdyacencia[[#Headers],[I2]],tblNodos[#All],2,FALSE) -> Hawala / HOSSP | L2: =VLOOKUP(tblMatrizDeAdyacencia[[#Headers],[I3]],tblNodos[#All],2,FALSE) -> MVTS / remesas | M2: =VLOOKUP(tblMatrizDeAdyacencia[[#Headers],[I4]],tblNodos[#All],2,FALSE) -> Dinero móvil | N2: =VLOOKUP(tblMatrizDeAdyacencia[[#Headers],[I5]],tblNodos[#All],2,FALSE) -> Pagos online | O2: =VLOOKUP(tblMatrizDeAdyacencia[[#Headers],[I6]],tblNodos[#All],2,FALSE) -> Servicios bancarios | P2: =VLOOKUP(tblMatrizDeAdyacencia[[#Headers],[I7]],tblNodos[#All],2,FALSE) -> Tarjetas prepago / e-wallets | Q2: =VLOOKUP(tblMatrizDeAdyacencia[[#Headers],[I8]],tblNodos[#All],2,FALSE) -> Plataformas digitales | R2: =VLOOKUP(tblMatrizDeAdyacencia[[#Headers],[I9]],tblNodos[#All],2,FALSE) -> Activos virtuales | S2: =VLOOKUP(tblMatrizDeAdyacencia[[#Headers],[G1]],tblNodos[#All],2,FALSE) -> Tesorería central | T2: =VLOOKUP(tblMatrizDeAdyacencia[[#Headers],[G2]],tblNodos[#All],2,FALSE) -> Centro financiero regional / célula | U2: =VLOOKUP(tblMatrizDeAdyacencia[[#Headers],[G3]],tblNodos[#All],2,FALSE) -> Facilitador externo / entidad instrumental | V2: =VLOOKUP(tblMatrizDeAdyacencia[[#Headers],[D]],tblNodos[#All],2,FALSE) -> Destino operativo
B3: Nombre Nodo | C3: NodoOrigen \ NodoDestino | D3: O1 | E3: O2 | F3: O3 | G3: O4 | H3: O5 | I3: O6 | J3: I1 | K3: I2 | L3: I3 | M3: I4 | N3: I5 | O3: I6 | P3: I7 | Q3: I8 | R3: I9 | S3: G1 | T3: G2 | U3: G3 | V3: D
B4: =VLOOKUP(tblMatrizDeAdyacencia[[#This Row],[NodoOrigen \ NodoDestino]],tblNodos[#All],2,FALSE) -> Coerción y cobros forzosos | C4: O1 | D4: =IF(COUNTIFS(Red!$K$5:$K$58,$C4,Red!$L$5:$L$58,D$3,Red!$N$5:$N$58,1)>0,1,0) -> 0 | E4: =IF(COUNTIFS(Red!$K$5:$K$58,$C4,Red!$L$5:$L$58,E$3,Red!$N$5:$N$58,1)>0,1,0) -> 0 | F4: =IF(COUNTIFS(Red!$K$5:$K$58,$C4,Red!$L$5:$L$58,F$3,Red!$N$5:$N$58,1)>0,1,0) -> 0 | G4: =IF(COUNTIFS(Red!$K$5:$K$58,$C4,Red!$L$5:$L$58,G$3,Red!$N$5:$N$58,1)>0,1,0) -> 0 | H4: =IF(COUNTIFS(Red!$K$5:$K$58,$C4,Red!$L$5:$L$58,H$3,Red!$N$5:$N$58,1)>0,1,0) -> 0 | I4: =IF(COUNTIFS(Red!$K$5:$K$58,$C4,Red!$L$5:$L$58,I$3,Red!$N$5:$N$58,1)>0,1,0) -> 0 | J4: =IF(COUNTIFS(Red!$K$5:$K$58,$C4,Red!$L$5:$L$58,J$3,Red!$N$5:$N$58,1)>0,1,0) -> 1 | K4: =IF(COUNTIFS(Red!$K$5:$K$58,$C4,Red!$L$5:$L$58,K$3,Red!$N$5:$N$58,1)>0,1,0) -> 1 | ... V4: =IF(COUNTIFS(Red!$K$5:$K$58,$C4,Red!$L$5:$L$58,V$3,Red!$N$5:$N$58,1)>0,1,0) -> 0
B5: =VLOOKUP(tblMatrizDeAdyacencia[[#This Row],[NodoOrigen \ NodoDestino]],tblNodos[#All],2,FALSE) -> Contrabando / tráfico / comercio ilícito | C5: O2 | D5: =IF(COUNTIFS(Red!$K$5:$K$58,$C5,Red!$L$5:$L$58,D$3,Red!$N$5:$N$58,1)>0,1,0) -> 0 | E5: =IF(COUNTIFS(Red!$K$5:$K$58,$C5,Red!$L$5:$L$58,E$3,Red!$N$5:$N$58,1)>0,1,0) -> 0 | F5: =IF(COUNTIFS(Red!$K$5:$K$58,$C5,Red!$L$5:$L$58,F$3,Red!$N$5:$N$58,1)>0,1,0) -> 0 | G5: =IF(COUNTIFS(Red!$K$5:$K$58,$C5,Red!$L$5:$L$58,G$3,Red!$N$5:$N$58,1)>0,1,0) -> 0 | H5: =IF(COUNTIFS(Red!$K$5:$K$58,$C5,Red!$L$5:$L$58,H$3,Red!$N$5:$N$58,1)>0,1,0) -> 0 | I5: =IF(COUNTIFS(Red!$K$5:$K$58,$C5,Red!$L$5:$L$58,I$3,Red!$N$5:$N$58,1)>0,1,0) -> 0 | J5: =IF(COUNTIFS(Red!$K$5:$K$58,$C5,Red!$L$5:$L$58,J$3,Red!$N$5:$N$58,1)>0,1,0) -> 1 | K5: =IF(COUNTIFS(Red!$K$5:$K$58,$C5,Red!$L$5:$L$58,K$3,Red!$N$5:$N$58,1)>0,1,0) -> 1 | ... V5: =IF(COUNTIFS(Red!$K$5:$K$58,$C5,Red!$L$5:$L$58,V$3,Red!$N$5:$N$58,1)>0,1,0) -> 0
B6: =VLOOKUP(tblMatrizDeAdyacencia[[#This Row],[NodoOrigen \ NodoDestino]],tblNodos[#All],2,FALSE) -> Explotación de recursos naturales | C6: O3 | D6: =IF(COUNTIFS(Red!$K$5:$K$58,$C6,Red!$L$5:$L$58,D$3,Red!$N$5:$N$58,1)>0,1,0) -> 0 | E6: =IF(COUNTIFS(Red!$K$5:$K$58,$C6,Red!$L$5:$L$58,E$3,Red!$N$5:$N$58,1)>0,1,0) -> 0 | F6: =IF(COUNTIFS(Red!$K$5:$K$58,$C6,Red!$L$5:$L$58,F$3,Red!$N$5:$N$58,1)>0,1,0) -> 0 | G6: =IF(COUNTIFS(Red!$K$5:$K$58,$C6,Red!$L$5:$L$58,G$3,Red!$N$5:$N$58,1)>0,1,0) -> 0 | H6: =IF(COUNTIFS(Red!$K$5:$K$58,$C6,Red!$L$5:$L$58,H$3,Red!$N$5:$N$58,1)>0,1,0) -> 0 | I6: =IF(COUNTIFS(Red!$K$5:$K$58,$C6,Red!$L$5:$L$58,I$3,Red!$N$5:$N$58,1)>0,1,0) -> 0 | J6: =IF(COUNTIFS(Red!$K$5:$K$58,$C6,Red!$L$5:$L$58,J$3,Red!$N$5:$N$58,1)>0,1,0) -> 1 | K6: =IF(COUNTIFS(Red!$K$5:$K$58,$C6,Red!$L$5:$L$58,K$3,Red!$N$5:$N$58,1)>0,1,0) -> 1 | ... V6: =IF(COUNTIFS(Red!$K$5:$K$58,$C6,Red!$L$5:$L$58,V$3,Red!$N$5:$N$58,1)>0,1,0) -> 0
B7: =VLOOKUP(tblMatrizDeAdyacencia[[#This Row],[NodoOrigen \ NodoDestino]],tblNodos[#All],2,FALSE) -> Autofinanciación lícita / microfinanciación | C7: O4 | D7: =IF(COUNTIFS(Red!$K$5:$K$58,$C7,Red!$L$5:$L$58,D$3,Red!$N$5:$N$58,1)>0,1,0) -> 0 | E7: =IF(COUNTIFS(Red!$K$5:$K$58,$C7,Red!$L$5:$L$58,E$3,Red!$N$5:$N$58,1)>0,1,0) -> 0 | F7: =IF(COUNTIFS(Red!$K$5:$K$58,$C7,Red!$L$5:$L$58,F$3,Red!$N$5:$N$58,1)>0,1,0) -> 0 | G7: =IF(COUNTIFS(Red!$K$5:$K$58,$C7,Red!$L$5:$L$58,G$3,Red!$N$5:$N$58,1)>0,1,0) -> 0 | H7: =IF(COUNTIFS(Red!$K$5:$K$58,$C7,Red!$L$5:$L$58,H$3,Red!$N$5:$N$58,1)>0,1,0) -> 0 | I7: =IF(COUNTIFS(Red!$K$5:$K$58,$C7,Red!$L$5:$L$58,I$3,Red!$N$5:$N$58,1)>0,1,0) -> 0 | J7: =IF(COUNTIFS(Red!$K$5:$K$58,$C7,Red!$L$5:$L$58,J$3,Red!$N$5:$N$58,1)>0,1,0) -> 0 | K7: =IF(COUNTIFS(Red!$K$5:$K$58,$C7,Red!$L$5:$L$58,K$3,Red!$N$5:$N$58,1)>0,1,0) -> 0 | ... V7: =IF(COUNTIFS(Red!$K$5:$K$58,$C7,Red!$L$5:$L$58,V$3,Red!$N$5:$N$58,1)>0,1,0) -> 0
B8: =VLOOKUP(tblMatrizDeAdyacencia[[#This Row],[NodoOrigen \ NodoDestino]],tblNodos[#All],2,FALSE) -> Actividades económicas formales / negocios | C8: O5 | D8: =IF(COUNTIFS(Red!$K$5:$K$58,$C8,Red!$L$5:$L$58,D$3,Red!$N$5:$N$58,1)>0,1,0) -> 0 | E8: =IF(COUNTIFS(Red!$K$5:$K$58,$C8,Red!$L$5:$L$58,E$3,Red!$N$5:$N$58,1)>0,1,0) -> 0 | F8: =IF(COUNTIFS(Red!$K$5:$K$58,$C8,Red!$L$5:$L$58,F$3,Red!$N$5:$N$58,1)>0,1,0) -> 0 | G8: =IF(COUNTIFS(Red!$K$5:$K$58,$C8,Red!$L$5:$L$58,G$3,Red!$N$5:$N$58,1)>0,1,0) -> 0 | H8: =IF(COUNTIFS(Red!$K$5:$K$58,$C8,Red!$L$5:$L$58,H$3,Red!$N$5:$N$58,1)>0,1,0) -> 0 | I8: =IF(COUNTIFS(Red!$K$5:$K$58,$C8,Red!$L$5:$L$58,I$3,Red!$N$5:$N$58,1)>0,1,0) -> 0 | J8: =IF(COUNTIFS(Red!$K$5:$K$58,$C8,Red!$L$5:$L$58,J$3,Red!$N$5:$N$58,1)>0,1,0) -> 1 | K8: =IF(COUNTIFS(Red!$K$5:$K$58,$C8,Red!$L$5:$L$58,K$3,Red!$N$5:$N$58,1)>0,1,0) -> 0 | ... V8: =IF(COUNTIFS(Red!$K$5:$K$58,$C8,Red!$L$5:$L$58,V$3,Red!$N$5:$N$58,1)>0,1,0) -> 0
B9: =VLOOKUP(tblMatrizDeAdyacencia[[#This Row],[NodoOrigen \ NodoDestino]],tblNodos[#All],2,FALSE) -> Donaciones / crowdfunding / apoyo online | C9: O6 | D9: =IF(COUNTIFS(Red!$K$5:$K$58,$C9,Red!$L$5:$L$58,D$3,Red!$N$5:$N$58,1)>0,1,0) -> 0 | E9: =IF(COUNTIFS(Red!$K$5:$K$58,$C9,Red!$L$5:$L$58,E$3,Red!$N$5:$N$58,1)>0,1,0) -> 0 | F9: =IF(COUNTIFS(Red!$K$5:$K$58,$C9,Red!$L$5:$L$58,F$3,Red!$N$5:$N$58,1)>0,1,0) -> 0 | G9: =IF(COUNTIFS(Red!$K$5:$K$58,$C9,Red!$L$5:$L$58,G$3,Red!$N$5:$N$58,1)>0,1,0) -> 0 | H9: =IF(COUNTIFS(Red!$K$5:$K$58,$C9,Red!$L$5:$L$58,H$3,Red!$N$5:$N$58,1)>0,1,0) -> 0 | I9: =IF(COUNTIFS(Red!$K$5:$K$58,$C9,Red!$L$5:$L$58,I$3,Red!$N$5:$N$58,1)>0,1,0) -> 0 | J9: =IF(COUNTIFS(Red!$K$5:$K$58,$C9,Red!$L$5:$L$58,J$3,Red!$N$5:$N$58,1)>0,1,0) -> 0 | K9: =IF(COUNTIFS(Red!$K$5:$K$58,$C9,Red!$L$5:$L$58,K$3,Red!$N$5:$N$58,1)>0,1,0) -> 0 | ... V9: =IF(COUNTIFS(Red!$K$5:$K$58,$C9,Red!$L$5:$L$58,V$3,Red!$N$5:$N$58,1)>0,1,0) -> 0
B10: =VLOOKUP(tblMatrizDeAdyacencia[[#This Row],[NodoOrigen \ NodoDestino]],tblNodos[#All],2,FALSE) -> Efectivo | C10: I1 | D10: =IF(COUNTIFS(Red!$K$5:$K$58,$C10,Red!$L$5:$L$58,D$3,Red!$N$5:$N$58,1)>0,1,0) -> 0 | E10: =IF(COUNTIFS(Red!$K$5:$K$58,$C10,Red!$L$5:$L$58,E$3,Red!$N$5:$N$58,1)>0,1,0) -> 0 | F10: =IF(COUNTIFS(Red!$K$5:$K$58,$C10,Red!$L$5:$L$58,F$3,Red!$N$5:$N$58,1)>0,1,0) -> 0 | G10: =IF(COUNTIFS(Red!$K$5:$K$58,$C10,Red!$L$5:$L$58,G$3,Red!$N$5:$N$58,1)>0,1,0) -> 0 | H10: =IF(COUNTIFS(Red!$K$5:$K$58,$C10,Red!$L$5:$L$58,H$3,Red!$N$5:$N$58,1)>0,1,0) -> 0 | I10: =IF(COUNTIFS(Red!$K$5:$K$58,$C10,Red!$L$5:$L$58,I$3,Red!$N$5:$N$58,1)>0,1,0) -> 0 | J10: =IF(COUNTIFS(Red!$K$5:$K$58,$C10,Red!$L$5:$L$58,J$3,Red!$N$5:$N$58,1)>0,1,0) -> 0 | K10: =IF(COUNTIFS(Red!$K$5:$K$58,$C10,Red!$L$5:$L$58,K$3,Red!$N$5:$N$58,1)>0,1,0) -> 1 | ... V10: =IF(COUNTIFS(Red!$K$5:$K$58,$C10,Red!$L$5:$L$58,V$3,Red!$N$5:$N$58,1)>0,1,0) -> 1
B11: =VLOOKUP(tblMatrizDeAdyacencia[[#This Row],[NodoOrigen \ NodoDestino]],tblNodos[#All],2,FALSE) -> Hawala / HOSSP | C11: I2 | D11: =IF(COUNTIFS(Red!$K$5:$K$58,$C11,Red!$L$5:$L$58,D$3,Red!$N$5:$N$58,1)>0,1,0) -> 0 | E11: =IF(COUNTIFS(Red!$K$5:$K$58,$C11,Red!$L$5:$L$58,E$3,Red!$N$5:$N$58,1)>0,1,0) -> 0 | F11: =IF(COUNTIFS(Red!$K$5:$K$58,$C11,Red!$L$5:$L$58,F$3,Red!$N$5:$N$58,1)>0,1,0) -> 0 | G11: =IF(COUNTIFS(Red!$K$5:$K$58,$C11,Red!$L$5:$L$58,G$3,Red!$N$5:$N$58,1)>0,1,0) -> 0 | H11: =IF(COUNTIFS(Red!$K$5:$K$58,$C11,Red!$L$5:$L$58,H$3,Red!$N$5:$N$58,1)>0,1,0) -> 0 | I11: =IF(COUNTIFS(Red!$K$5:$K$58,$C11,Red!$L$5:$L$58,I$3,Red!$N$5:$N$58,1)>0,1,0) -> 0 | J11: =IF(COUNTIFS(Red!$K$5:$K$58,$C11,Red!$L$5:$L$58,J$3,Red!$N$5:$N$58,1)>0,1,0) -> 0 | K11: =IF(COUNTIFS(Red!$K$5:$K$58,$C11,Red!$L$5:$L$58,K$3,Red!$N$5:$N$58,1)>0,1,0) -> 0 | ... V11: =IF(COUNTIFS(Red!$K$5:$K$58,$C11,Red!$L$5:$L$58,V$3,Red!$N$5:$N$58,1)>0,1,0) -> 1
B12: =VLOOKUP(tblMatrizDeAdyacencia[[#This Row],[NodoOrigen \ NodoDestino]],tblNodos[#All],2,FALSE) -> MVTS / remesas | C12: I3 | D12: =IF(COUNTIFS(Red!$K$5:$K$58,$C12,Red!$L$5:$L$58,D$3,Red!$N$5:$N$58,1)>0,1,0) -> 0 | E12: =IF(COUNTIFS(Red!$K$5:$K$58,$C12,Red!$L$5:$L$58,E$3,Red!$N$5:$N$58,1)>0,1,0) -> 0 | F12: =IF(COUNTIFS(Red!$K$5:$K$58,$C12,Red!$L$5:$L$58,F$3,Red!$N$5:$N$58,1)>0,1,0) -> 0 | G12: =IF(COUNTIFS(Red!$K$5:$K$58,$C12,Red!$L$5:$L$58,G$3,Red!$N$5:$N$58,1)>0,1,0) -> 0 | H12: =IF(COUNTIFS(Red!$K$5:$K$58,$C12,Red!$L$5:$L$58,H$3,Red!$N$5:$N$58,1)>0,1,0) -> 0 | I12: =IF(COUNTIFS(Red!$K$5:$K$58,$C12,Red!$L$5:$L$58,I$3,Red!$N$5:$N$58,1)>0,1,0) -> 0 | J12: =IF(COUNTIFS(Red!$K$5:$K$58,$C12,Red!$L$5:$L$58,J$3,Red!$N$5:$N$58,1)>0,1,0) -> 0 | K12: =IF(COUNTIFS(Red!$K$5:$K$58,$C12,Red!$L$5:$L$58,K$3,Red!$N$5:$N$58,1)>0,1,0) -> 0 | ... V12: =IF(COUNTIFS(Red!$K$5:$K$58,$C12,Red!$L$5:$L$58,V$3,Red!$N$5:$N$58,1)>0,1,0) -> 1
B13: =VLOOKUP(tblMatrizDeAdyacencia[[#This Row],[NodoOrigen \ NodoDestino]],tblNodos[#All],2,FALSE) -> Dinero móvil | C13: I4 | D13: =IF(COUNTIFS(Red!$K$5:$K$58,$C13,Red!$L$5:$L$58,D$3,Red!$N$5:$N$58,1)>0,1,0) -> 0 | E13: =IF(COUNTIFS(Red!$K$5:$K$58,$C13,Red!$L$5:$L$58,E$3,Red!$N$5:$N$58,1)>0,1,0) -> 0 | F13: =IF(COUNTIFS(Red!$K$5:$K$58,$C13,Red!$L$5:$L$58,F$3,Red!$N$5:$N$58,1)>0,1,0) -> 0 | G13: =IF(COUNTIFS(Red!$K$5:$K$58,$C13,Red!$L$5:$L$58,G$3,Red!$N$5:$N$58,1)>0,1,0) -> 0 | H13: =IF(COUNTIFS(Red!$K$5:$K$58,$C13,Red!$L$5:$L$58,H$3,Red!$N$5:$N$58,1)>0,1,0) -> 0 | I13: =IF(COUNTIFS(Red!$K$5:$K$58,$C13,Red!$L$5:$L$58,I$3,Red!$N$5:$N$58,1)>0,1,0) -> 0 | J13: =IF(COUNTIFS(Red!$K$5:$K$58,$C13,Red!$L$5:$L$58,J$3,Red!$N$5:$N$58,1)>0,1,0) -> 0 | K13: =IF(COUNTIFS(Red!$K$5:$K$58,$C13,Red!$L$5:$L$58,K$3,Red!$N$5:$N$58,1)>0,1,0) -> 0 | ... V13: =IF(COUNTIFS(Red!$K$5:$K$58,$C13,Red!$L$5:$L$58,V$3,Red!$N$5:$N$58,1)>0,1,0) -> 0
B14: =VLOOKUP(tblMatrizDeAdyacencia[[#This Row],[NodoOrigen \ NodoDestino]],tblNodos[#All],2,FALSE) -> Pagos online | C14: I5 | D14: =IF(COUNTIFS(Red!$K$5:$K$58,$C14,Red!$L$5:$L$58,D$3,Red!$N$5:$N$58,1)>0,1,0) -> 0 | E14: =IF(COUNTIFS(Red!$K$5:$K$58,$C14,Red!$L$5:$L$58,E$3,Red!$N$5:$N$58,1)>0,1,0) -> 0 | F14: =IF(COUNTIFS(Red!$K$5:$K$58,$C14,Red!$L$5:$L$58,F$3,Red!$N$5:$N$58,1)>0,1,0) -> 0 | G14: =IF(COUNTIFS(Red!$K$5:$K$58,$C14,Red!$L$5:$L$58,G$3,Red!$N$5:$N$58,1)>0,1,0) -> 0 | H14: =IF(COUNTIFS(Red!$K$5:$K$58,$C14,Red!$L$5:$L$58,H$3,Red!$N$5:$N$58,1)>0,1,0) -> 0 | I14: =IF(COUNTIFS(Red!$K$5:$K$58,$C14,Red!$L$5:$L$58,I$3,Red!$N$5:$N$58,1)>0,1,0) -> 0 | J14: =IF(COUNTIFS(Red!$K$5:$K$58,$C14,Red!$L$5:$L$58,J$3,Red!$N$5:$N$58,1)>0,1,0) -> 0 | K14: =IF(COUNTIFS(Red!$K$5:$K$58,$C14,Red!$L$5:$L$58,K$3,Red!$N$5:$N$58,1)>0,1,0) -> 0 | ... V14: =IF(COUNTIFS(Red!$K$5:$K$58,$C14,Red!$L$5:$L$58,V$3,Red!$N$5:$N$58,1)>0,1,0) -> 0
B15: =VLOOKUP(tblMatrizDeAdyacencia[[#This Row],[NodoOrigen \ NodoDestino]],tblNodos[#All],2,FALSE) -> Servicios bancarios | C15: I6 | D15: =IF(COUNTIFS(Red!$K$5:$K$58,$C15,Red!$L$5:$L$58,D$3,Red!$N$5:$N$58,1)>0,1,0) -> 0 | E15: =IF(COUNTIFS(Red!$K$5:$K$58,$C15,Red!$L$5:$L$58,E$3,Red!$N$5:$N$58,1)>0,1,0) -> 0 | F15: =IF(COUNTIFS(Red!$K$5:$K$58,$C15,Red!$L$5:$L$58,F$3,Red!$N$5:$N$58,1)>0,1,0) -> 0 | G15: =IF(COUNTIFS(Red!$K$5:$K$58,$C15,Red!$L$5:$L$58,G$3,Red!$N$5:$N$58,1)>0,1,0) -> 0 | H15: =IF(COUNTIFS(Red!$K$5:$K$58,$C15,Red!$L$5:$L$58,H$3,Red!$N$5:$N$58,1)>0,1,0) -> 0 | I15: =IF(COUNTIFS(Red!$K$5:$K$58,$C15,Red!$L$5:$L$58,I$3,Red!$N$5:$N$58,1)>0,1,0) -> 0 | J15: =IF(COUNTIFS(Red!$K$5:$K$58,$C15,Red!$L$5:$L$58,J$3,Red!$N$5:$N$58,1)>0,1,0) -> 0 | K15: =IF(COUNTIFS(Red!$K$5:$K$58,$C15,Red!$L$5:$L$58,K$3,Red!$N$5:$N$58,1)>0,1,0) -> 0 | ... V15: =IF(COUNTIFS(Red!$K$5:$K$58,$C15,Red!$L$5:$L$58,V$3,Red!$N$5:$N$58,1)>0,1,0) -> 0
... B22: =VLOOKUP(tblMatrizDeAdyacencia[[#This Row],[NodoOrigen \ NodoDestino]],tblNodos[#All],2,FALSE) -> Destino operativo | C22: D | D22: =IF(COUNTIFS(Red!$K$5:$K$58,$C22,Red!$L$5:$L$58,D$3,Red!$N$5:$N$58,1)>0,1,0) -> 0 | E22: =IF(COUNTIFS(Red!$K$5:$K$58,$C22,Red!$L$5:$L$58,E$3,Red!$N$5:$N$58,1)>0,1,0) -> 0 | F22: =IF(COUNTIFS(Red!$K$5:$K$58,$C22,Red!$L$5:$L$58,F$3,Red!$N$5:$N$58,1)>0,1,0) -> 0 | G22: =IF(COUNTIFS(Red!$K$5:$K$58,$C22,Red!$L$5:$L$58,G$3,Red!$N$5:$N$58,1)>0,1,0) -> 0 | H22: =IF(COUNTIFS(Red!$K$5:$K$58,$C22,Red!$L$5:$L$58,H$3,Red!$N$5:$N$58,1)>0,1,0) -> 0 | I22: =IF(COUNTIFS(Red!$K$5:$K$58,$C22,Red!$L$5:$L$58,I$3,Red!$N$5:$N$58,1)>0,1,0) -> 0 | J22: =IF(COUNTIFS(Red!$K$5:$K$58,$C22,Red!$L$5:$L$58,J$3,Red!$N$5:$N$58,1)>0,1,0) -> 0 | K22: =IF(COUNTIFS(Red!$K$5:$K$58,$C22,Red!$L$5:$L$58,K$3,Red!$N$5:$N$58,1)>0,1,0) -> 0 | ... V22: =IF(COUNTIFS(Red!$K$5:$K$58,$C22,Red!$L$5:$L$58,V$3,Red!$N$5:$N$58,1)>0,1,0) -> 0
B25: La matriz es dirigida y binaria: 1 = enlace activo, 0 = no enlace.
B26: La hoja ENLACES es la fuente de verdad de la red.

Sheet MatrizPonderadaCostes
B2: Matriz Ponderada de Costes | D2: =VLOOKUP(tblMatrizPonderadaCostes[[#Headers],[O1]],tblNodos[#All],2,FALSE) -> Coerción y cobros forzosos | E2: =VLOOKUP(tblMatrizPonderadaCostes[[#Headers],[O2]],tblNodos[#All],2,FALSE) -> Contrabando / tráfico / comercio ilícito | F2: =VLOOKUP(tblMatrizPonderadaCostes[[#Headers],[O3]],tblNodos[#All],2,FALSE) -> Explotación de recursos naturales | G2: =VLOOKUP(tblMatrizPonderadaCostes[[#Headers],[O4]],tblNodos[#All],2,FALSE) -> Autofinanciación lícita / microfinanciación | H2: =VLOOKUP(tblMatrizPonderadaCostes[[#Headers],[O5]],tblNodos[#All],2,FALSE) -> Actividades económicas formales / negocios | I2: =VLOOKUP(tblMatrizPonderadaCostes[[#Headers],[O6]],tblNodos[#All],2,FALSE) -> Donaciones / crowdfunding / apoyo online | J2: =VLOOKUP(tblMatrizPonderadaCostes[[#Headers],[I1]],tblNodos[#All],2,FALSE) -> Efectivo | K2: =VLOOKUP(tblMatrizPonderadaCostes[[#Headers],[I2]],tblNodos[#All],2,FALSE) -> Hawala / HOSSP | L2: =VLOOKUP(tblMatrizPonderadaCostes[[#Headers],[I3]],tblNodos[#All],2,FALSE) -> MVTS / remesas | M2: =VLOOKUP(tblMatrizPonderadaCostes[[#Headers],[I4]],tblNodos[#All],2,FALSE) -> Dinero móvil | N2: =VLOOKUP(tblMatrizPonderadaCostes[[#Headers],[I5]],tblNodos[#All],2,FALSE) -> Pagos online | O2: =VLOOKUP(tblMatrizPonderadaCostes[[#Headers],[I6]],tblNodos[#All],2,FALSE) -> Servicios bancarios | P2: =VLOOKUP(tblMatrizPonderadaCostes[[#Headers],[I7]],tblNodos[#All],2,FALSE) -> Tarjetas prepago / e-wallets | Q2: =VLOOKUP(tblMatrizPonderadaCostes[[#Headers],[I8]],tblNodos[#All],2,FALSE) -> Plataformas digitales | R2: =VLOOKUP(tblMatrizPonderadaCostes[[#Headers],[I9]],tblNodos[#All],2,FALSE) -> Activos virtuales | S2: =VLOOKUP(tblMatrizPonderadaCostes[[#Headers],[G1]],tblNodos[#All],2,FALSE) -> Tesorería central | T2: =VLOOKUP(tblMatrizPonderadaCostes[[#Headers],[G2]],tblNodos[#All],2,FALSE) -> Centro financiero regional / célula | U2: =VLOOKUP(tblMatrizPonderadaCostes[[#Headers],[G3]],tblNodos[#All],2,FALSE) -> Facilitador externo / entidad instrumental | V2: =VLOOKUP(tblMatrizPonderadaCostes[[#Headers],[D]],tblNodos[#All],2,FALSE) -> Destino operativo
B3: Nombre Nodo | C3: NodoOrigen \ NodoDestino | D3: O1 | E3: O2 | F3: O3 | G3: O4 | H3: O5 | I3: O6 | J3: I1 | K3: I2 | L3: I3 | M3: I4 | N3: I5 | O3: I6 | P3: I7 | Q3: I8 | R3: I9 | S3: G1 | T3: G2 | U3: G3 | V3: D | Y3: Pesos por COSTE del Enlace
B4: =VLOOKUP(tblMatrizPonderadaCostes[[#This Row],[NodoOrigen \ NodoDestino]],tblNodos[#All],2,FALSE) -> Coerción y cobros forzosos | C4: O1 | D4: =IF(MatrizDeAdyacencia!D4=1,SUMIFS(tblEnlaces[Coste (peso)],tblEnlaces[Nodo Origen],$C4,tblEnlaces[Nodo Destino],D$3,tblEnlaces[Activo],1),0) -> 0 | E4: =IF(MatrizDeAdyacencia!E4=1,SUMIFS(tblEnlaces[Coste (peso)],tblEnlaces[Nodo Origen],$C4,tblEnlaces[Nodo Destino],E$3,tblEnlaces[Activo],1),0) -> 0 | F4: =IF(MatrizDeAdyacencia!F4=1,SUMIFS(tblEnlaces[Coste (peso)],tblEnlaces[Nodo Origen],$C4,tblEnlaces[Nodo Destino],F$3,tblEnlaces[Activo],1),0) -> 0 | G4: =IF(MatrizDeAdyacencia!G4=1,SUMIFS(tblEnlaces[Coste (peso)],tblEnlaces[Nodo Origen],$C4,tblEnlaces[Nodo Destino],G$3,tblEnlaces[Activo],1),0) -> 0 | H4: =IF(MatrizDeAdyacencia!H4=1,SUMIFS(tblEnlaces[Coste (peso)],tblEnlaces[Nodo Origen],$C4,tblEnlaces[Nodo Destino],H$3,tblEnlaces[Activo],1),0) -> 0 | I4: =IF(MatrizDeAdyacencia!I4=1,SUMIFS(tblEnlaces[Coste (peso)],tblEnlaces[Nodo Origen],$C4,tblEnlaces[Nodo Destino],I$3,tblEnlaces[Activo],1),0) -> 0 | J4: =IF(MatrizDeAdyacencia!J4=1,SUMIFS(tblEnlaces[Coste (peso)],tblEnlaces[Nodo Origen],$C4,tblEnlaces[Nodo Destino],J$3,tblEnlaces[Activo],1),0) -> 5 | K4: =IF(MatrizDeAdyacencia!K4=1,SUMIFS(tblEnlaces[Coste (peso)],tblEnlaces[Nodo Origen],$C4,tblEnlaces[Nodo Destino],K$3,tblEnlaces[Activo],1),0) -> 3 | ... V4: =IF(MatrizDeAdyacencia!V4=1,SUMIFS(tblEnlaces[Coste (peso)],tblEnlaces[Nodo Origen],$C4,tblEnlaces[Nodo Destino],V$3,tblEnlaces[Activo],1),0) -> 0 | Y4: Valor | Z4: Coste
B5: =VLOOKUP(tblMatrizPonderadaCostes[[#This Row],[NodoOrigen \ NodoDestino]],tblNodos[#All],2,FALSE) -> Contrabando / tráfico / comercio ilícito | C5: O2 | D5: =IF(MatrizDeAdyacencia!D5=1,SUMIFS(tblEnlaces[Coste (peso)],tblEnlaces[Nodo Origen],$C5,tblEnlaces[Nodo Destino],D$3,tblEnlaces[Activo],1),0) -> 0 | E5: =IF(MatrizDeAdyacencia!E5=1,SUMIFS(tblEnlaces[Coste (peso)],tblEnlaces[Nodo Origen],$C5,tblEnlaces[Nodo Destino],E$3,tblEnlaces[Activo],1),0) -> 0 | F5: =IF(MatrizDeAdyacencia!F5=1,SUMIFS(tblEnlaces[Coste (peso)],tblEnlaces[Nodo Origen],$C5,tblEnlaces[Nodo Destino],F$3,tblEnlaces[Activo],1),0) -> 0 | G5: =IF(MatrizDeAdyacencia!G5=1,SUMIFS(tblEnlaces[Coste (peso)],tblEnlaces[Nodo Origen],$C5,tblEnlaces[Nodo Destino],G$3,tblEnlaces[Activo],1),0) -> 0 | H5: =IF(MatrizDeAdyacencia!H5=1,SUMIFS(tblEnlaces[Coste (peso)],tblEnlaces[Nodo Origen],$C5,tblEnlaces[Nodo Destino],H$3,tblEnlaces[Activo],1),0) -> 0 | I5: =IF(MatrizDeAdyacencia!I5=1,SUMIFS(tblEnlaces[Coste (peso)],tblEnlaces[Nodo Origen],$C5,tblEnlaces[Nodo Destino],I$3,tblEnlaces[Activo],1),0) -> 0 | J5: =IF(MatrizDeAdyacencia!J5=1,SUMIFS(tblEnlaces[Coste (peso)],tblEnlaces[Nodo Origen],$C5,tblEnlaces[Nodo Destino],J$3,tblEnlaces[Activo],1),0) -> 5 | K5: =IF(MatrizDeAdyacencia!K5=1,SUMIFS(tblEnlaces[Coste (peso)],tblEnlaces[Nodo Origen],$C5,tblEnlaces[Nodo Destino],K$3,tblEnlaces[Activo],1),0) -> 3 | ... V5: =IF(MatrizDeAdyacencia!V5=1,SUMIFS(tblEnlaces[Coste (peso)],tblEnlaces[Nodo Origen],$C5,tblEnlaces[Nodo Destino],V$3,tblEnlaces[Activo],1),0) -> 0 | Y5: Bajo | Z5: 5
B6: =VLOOKUP(tblMatrizPonderadaCostes[[#This Row],[NodoOrigen \ NodoDestino]],tblNodos[#All],2,FALSE) -> Explotación de recursos naturales | C6: O3 | D6: =IF(MatrizDeAdyacencia!D6=1,SUMIFS(tblEnlaces[Coste (peso)],tblEnlaces[Nodo Origen],$C6,tblEnlaces[Nodo Destino],D$3,tblEnlaces[Activo],1),0) -> 0 | E6: =IF(MatrizDeAdyacencia!E6=1,SUMIFS(tblEnlaces[Coste (peso)],tblEnlaces[Nodo Origen],$C6,tblEnlaces[Nodo Destino],E$3,tblEnlaces[Activo],1),0) -> 0 | F6: =IF(MatrizDeAdyacencia!F6=1,SUMIFS(tblEnlaces[Coste (peso)],tblEnlaces[Nodo Origen],$C6,tblEnlaces[Nodo Destino],F$3,tblEnlaces[Activo],1),0) -> 0 | G6: =IF(MatrizDeAdyacencia!G6=1,SUMIFS(tblEnlaces[Coste (peso)],tblEnlaces[Nodo Origen],$C6,tblEnlaces[Nodo Destino],G$3,tblEnlaces[Activo],1),0) -> 0 | H6: =IF(MatrizDeAdyacencia!H6=1,SUMIFS(tblEnlaces[Coste (peso)],tblEnlaces[Nodo Origen],$C6,tblEnlaces[Nodo Destino],H$3,tblEnlaces[Activo],1),0) -> 0 | I6: =IF(MatrizDeAdyacencia!I6=1,SUMIFS(tblEnlaces[Coste (peso)],tblEnlaces[Nodo Origen],$C6,tblEnlaces[Nodo Destino],I$3,tblEnlaces[Activo],1),0) -> 0 | J6: =IF(MatrizDeAdyacencia!J6=1,SUMIFS(tblEnlaces[Coste (peso)],tblEnlaces[Nodo Origen],$C6,tblEnlaces[Nodo Destino],J$3,tblEnlaces[Activo],1),0) -> 5 | K6: =IF(MatrizDeAdyacencia!K6=1,SUMIFS(tblEnlaces[Coste (peso)],tblEnlaces[Nodo Origen],$C6,tblEnlaces[Nodo Destino],K$3,tblEnlaces[Activo],1),0) -> 3 | ... V6: =IF(MatrizDeAdyacencia!V6=1,SUMIFS(tblEnlaces[Coste (peso)],tblEnlaces[Nodo Origen],$C6,tblEnlaces[Nodo Destino],V$3,tblEnlaces[Activo],1),0) -> 0 | Y6: Bajo-Medio | Z6: 4
B7: =VLOOKUP(tblMatrizPonderadaCostes[[#This Row],[NodoOrigen \ NodoDestino]],tblNodos[#All],2,FALSE) -> Autofinanciación lícita / microfinanciación | C7: O4 | D7: =IF(MatrizDeAdyacencia!D7=1,SUMIFS(tblEnlaces[Coste (peso)],tblEnlaces[Nodo Origen],$C7,tblEnlaces[Nodo Destino],D$3,tblEnlaces[Activo],1),0) -> 0 | E7: =IF(MatrizDeAdyacencia!E7=1,SUMIFS(tblEnlaces[Coste (peso)],tblEnlaces[Nodo Origen],$C7,tblEnlaces[Nodo Destino],E$3,tblEnlaces[Activo],1),0) -> 0 | F7: =IF(MatrizDeAdyacencia!F7=1,SUMIFS(tblEnlaces[Coste (peso)],tblEnlaces[Nodo Origen],$C7,tblEnlaces[Nodo Destino],F$3,tblEnlaces[Activo],1),0) -> 0 | G7: =IF(MatrizDeAdyacencia!G7=1,SUMIFS(tblEnlaces[Coste (peso)],tblEnlaces[Nodo Origen],$C7,tblEnlaces[Nodo Destino],G$3,tblEnlaces[Activo],1),0) -> 0 | H7: =IF(MatrizDeAdyacencia!H7=1,SUMIFS(tblEnlaces[Coste (peso)],tblEnlaces[Nodo Origen],$C7,tblEnlaces[Nodo Destino],H$3,tblEnlaces[Activo],1),0) -> 0 | I7: =IF(MatrizDeAdyacencia!I7=1,SUMIFS(tblEnlaces[Coste (peso)],tblEnlaces[Nodo Origen],$C7,tblEnlaces[Nodo Destino],I$3,tblEnlaces[Activo],1),0) -> 0 | J7: =IF(MatrizDeAdyacencia!J7=1,SUMIFS(tblEnlaces[Coste (peso)],tblEnlaces[Nodo Origen],$C7,tblEnlaces[Nodo Destino],J$3,tblEnlaces[Activo],1),0) -> 0 | K7: =IF(MatrizDeAdyacencia!K7=1,SUMIFS(tblEnlaces[Coste (peso)],tblEnlaces[Nodo Origen],$C7,tblEnlaces[Nodo Destino],K$3,tblEnlaces[Activo],1),0) -> 0 | ... V7: =IF(MatrizDeAdyacencia!V7=1,SUMIFS(tblEnlaces[Coste (peso)],tblEnlaces[Nodo Origen],$C7,tblEnlaces[Nodo Destino],V$3,tblEnlaces[Activo],1),0) -> 0 | Y7: Medio | Z7: 3
B8: =VLOOKUP(tblMatrizPonderadaCostes[[#This Row],[NodoOrigen \ NodoDestino]],tblNodos[#All],2,FALSE) -> Actividades económicas formales / negocios | C8: O5 | D8: =IF(MatrizDeAdyacencia!D8=1,SUMIFS(tblEnlaces[Coste (peso)],tblEnlaces[Nodo Origen],$C8,tblEnlaces[Nodo Destino],D$3,tblEnlaces[Activo],1),0) -> 0 | E8: =IF(MatrizDeAdyacencia!E8=1,SUMIFS(tblEnlaces[Coste (peso)],tblEnlaces[Nodo Origen],$C8,tblEnlaces[Nodo Destino],E$3,tblEnlaces[Activo],1),0) -> 0 | F8: =IF(MatrizDeAdyacencia!F8=1,SUMIFS(tblEnlaces[Coste (peso)],tblEnlaces[Nodo Origen],$C8,tblEnlaces[Nodo Destino],F$3,tblEnlaces[Activo],1),0) -> 0 | G8: =IF(MatrizDeAdyacencia!G8=1,SUMIFS(tblEnlaces[Coste (peso)],tblEnlaces[Nodo Origen],$C8,tblEnlaces[Nodo Destino],G$3,tblEnlaces[Activo],1),0) -> 0 | H8: =IF(MatrizDeAdyacencia!H8=1,SUMIFS(tblEnlaces[Coste (peso)],tblEnlaces[Nodo Origen],$C8,tblEnlaces[Nodo Destino],H$3,tblEnlaces[Activo],1),0) -> 0 | I8: =IF(MatrizDeAdyacencia!I8=1,SUMIFS(tblEnlaces[Coste (peso)],tblEnlaces[Nodo Origen],$C8,tblEnlaces[Nodo Destino],I$3,tblEnlaces[Activo],1),0) -> 0 | J8: =IF(MatrizDeAdyacencia!J8=1,SUMIFS(tblEnlaces[Coste (peso)],tblEnlaces[Nodo Origen],$C8,tblEnlaces[Nodo Destino],J$3,tblEnlaces[Activo],1),0) -> 5 | K8: =IF(MatrizDeAdyacencia!K8=1,SUMIFS(tblEnlaces[Coste (peso)],tblEnlaces[Nodo Origen],$C8,tblEnlaces[Nodo Destino],K$3,tblEnlaces[Activo],1),0) -> 0 | ... V8: =IF(MatrizDeAdyacencia!V8=1,SUMIFS(tblEnlaces[Coste (peso)],tblEnlaces[Nodo Origen],$C8,tblEnlaces[Nodo Destino],V$3,tblEnlaces[Activo],1),0) -> 0 | Y8: Medio-Alto | Z8: 2
B9: =VLOOKUP(tblMatrizPonderadaCostes[[#This Row],[NodoOrigen \ NodoDestino]],tblNodos[#All],2,FALSE) -> Donaciones / crowdfunding / apoyo online | C9: O6 | D9: =IF(MatrizDeAdyacencia!D9=1,SUMIFS(tblEnlaces[Coste (peso)],tblEnlaces[Nodo Origen],$C9,tblEnlaces[Nodo Destino],D$3,tblEnlaces[Activo],1),0) -> 0 | E9: =IF(MatrizDeAdyacencia!E9=1,SUMIFS(tblEnlaces[Coste (peso)],tblEnlaces[Nodo Origen],$C9,tblEnlaces[Nodo Destino],E$3,tblEnlaces[Activo],1),0) -> 0 | F9: =IF(MatrizDeAdyacencia!F9=1,SUMIFS(tblEnlaces[Coste (peso)],tblEnlaces[Nodo Origen],$C9,tblEnlaces[Nodo Destino],F$3,tblEnlaces[Activo],1),0) -> 0 | G9: =IF(MatrizDeAdyacencia!G9=1,SUMIFS(tblEnlaces[Coste (peso)],tblEnlaces[Nodo Origen],$C9,tblEnlaces[Nodo Destino],G$3,tblEnlaces[Activo],1),0) -> 0 | H9: =IF(MatrizDeAdyacencia!H9=1,SUMIFS(tblEnlaces[Coste (peso)],tblEnlaces[Nodo Origen],$C9,tblEnlaces[Nodo Destino],H$3,tblEnlaces[Activo],1),0) -> 0 | I9: =IF(MatrizDeAdyacencia!I9=1,SUMIFS(tblEnlaces[Coste (peso)],tblEnlaces[Nodo Origen],$C9,tblEnlaces[Nodo Destino],I$3,tblEnlaces[Activo],1),0) -> 0 | J9: =IF(MatrizDeAdyacencia!J9=1,SUMIFS(tblEnlaces[Coste (peso)],tblEnlaces[Nodo Origen],$C9,tblEnlaces[Nodo Destino],J$3,tblEnlaces[Activo],1),0) -> 0 | K9: =IF(MatrizDeAdyacencia!K9=1,SUMIFS(tblEnlaces[Coste (peso)],tblEnlaces[Nodo Origen],$C9,tblEnlaces[Nodo Destino],K$3,tblEnlaces[Activo],1),0) -> 0 | ... V9: =IF(MatrizDeAdyacencia!V9=1,SUMIFS(tblEnlaces[Coste (peso)],tblEnlaces[Nodo Origen],$C9,tblEnlaces[Nodo Destino],V$3,tblEnlaces[Activo],1),0) -> 0 | Y9: Alto | Z9: 1
B10: =VLOOKUP(tblMatrizPonderadaCostes[[#This Row],[NodoOrigen \ NodoDestino]],tblNodos[#All],2,FALSE) -> Efectivo | C10: I1 | D10: =IF(MatrizDeAdyacencia!D10=1,SUMIFS(tblEnlaces[Coste (peso)],tblEnlaces[Nodo Origen],$C10,tblEnlaces[Nodo Destino],D$3,tblEnlaces[Activo],1),0) -> 0 | E10: =IF(MatrizDeAdyacencia!E10=1,SUMIFS(tblEnlaces[Coste (peso)],tblEnlaces[Nodo Origen],$C10,tblEnlaces[Nodo Destino],E$3,tblEnlaces[Activo],1),0) -> 0 | F10: =IF(MatrizDeAdyacencia!F10=1,SUMIFS(tblEnlaces[Coste (peso)],tblEnlaces[Nodo Origen],$C10,tblEnlaces[Nodo Destino],F$3,tblEnlaces[Activo],1),0) -> 0 | G10: =IF(MatrizDeAdyacencia!G10=1,SUMIFS(tblEnlaces[Coste (peso)],tblEnlaces[Nodo Origen],$C10,tblEnlaces[Nodo Destino],G$3,tblEnlaces[Activo],1),0) -> 0 | H10: =IF(MatrizDeAdyacencia!H10=1,SUMIFS(tblEnlaces[Coste (peso)],tblEnlaces[Nodo Origen],$C10,tblEnlaces[Nodo Destino],H$3,tblEnlaces[Activo],1),0) -> 0 | I10: =IF(MatrizDeAdyacencia!I10=1,SUMIFS(tblEnlaces[Coste (peso)],tblEnlaces[Nodo Origen],$C10,tblEnlaces[Nodo Destino],I$3,tblEnlaces[Activo],1),0) -> 0 | J10: =IF(MatrizDeAdyacencia!J10=1,SUMIFS(tblEnlaces[Coste (peso)],tblEnlaces[Nodo Origen],$C10,tblEnlaces[Nodo Destino],J$3,tblEnlaces[Activo],1),0) -> 0 | K10: =IF(MatrizDeAdyacencia!K10=1,SUMIFS(tblEnlaces[Coste (peso)],tblEnlaces[Nodo Origen],$C10,tblEnlaces[Nodo Destino],K$3,tblEnlaces[Activo],1),0) -> 3 | ... V10: =IF(MatrizDeAdyacencia!V10=1,SUMIFS(tblEnlaces[Coste (peso)],tblEnlaces[Nodo Origen],$C10,tblEnlaces[Nodo Destino],V$3,tblEnlaces[Activo],1),0) -> 5
B11: =VLOOKUP(tblMatrizPonderadaCostes[[#This Row],[NodoOrigen \ NodoDestino]],tblNodos[#All],2,FALSE) -> Hawala / HOSSP | C11: I2 | D11: =IF(MatrizDeAdyacencia!D11=1,SUMIFS(tblEnlaces[Coste (peso)],tblEnlaces[Nodo Origen],$C11,tblEnlaces[Nodo Destino],D$3,tblEnlaces[Activo],1),0) -> 0 | E11: =IF(MatrizDeAdyacencia!E11=1,SUMIFS(tblEnlaces[Coste (peso)],tblEnlaces[Nodo Origen],$C11,tblEnlaces[Nodo Destino],E$3,tblEnlaces[Activo],1),0) -> 0 | F11: =IF(MatrizDeAdyacencia!F11=1,SUMIFS(tblEnlaces[Coste (peso)],tblEnlaces[Nodo Origen],$C11,tblEnlaces[Nodo Destino],F$3,tblEnlaces[Activo],1),0) -> 0 | G11: =IF(MatrizDeAdyacencia!G11=1,SUMIFS(tblEnlaces[Coste (peso)],tblEnlaces[Nodo Origen],$C11,tblEnlaces[Nodo Destino],G$3,tblEnlaces[Activo],1),0) -> 0 | H11: =IF(MatrizDeAdyacencia!H11=1,SUMIFS(tblEnlaces[Coste (peso)],tblEnlaces[Nodo Origen],$C11,tblEnlaces[Nodo Destino],H$3,tblEnlaces[Activo],1),0) -> 0 | I11: =IF(MatrizDeAdyacencia!I11=1,SUMIFS(tblEnlaces[Coste (peso)],tblEnlaces[Nodo Origen],$C11,tblEnlaces[Nodo Destino],I$3,tblEnlaces[Activo],1),0) -> 0 | J11: =IF(MatrizDeAdyacencia!J11=1,SUMIFS(tblEnlaces[Coste (peso)],tblEnlaces[Nodo Origen],$C11,tblEnlaces[Nodo Destino],J$3,tblEnlaces[Activo],1),0) -> 0 | K11: =IF(MatrizDeAdyacencia!K11=1,SUMIFS(tblEnlaces[Coste (peso)],tblEnlaces[Nodo Origen],$C11,tblEnlaces[Nodo Destino],K$3,tblEnlaces[Activo],1),0) -> 0 | ... V11: =IF(MatrizDeAdyacencia!V11=1,SUMIFS(tblEnlaces[Coste (peso)],tblEnlaces[Nodo Origen],$C11,tblEnlaces[Nodo Destino],V$3,tblEnlaces[Activo],1),0) -> 3 | Y11: 🔎 Rango del valor de un Enlace (según tblPesos)
B12: =VLOOKUP(tblMatrizPonderadaCostes[[#This Row],[NodoOrigen \ NodoDestino]],tblNodos[#All],2,FALSE) -> MVTS / remesas | C12: I3 | D12: =IF(MatrizDeAdyacencia!D12=1,SUMIFS(tblEnlaces[Coste (peso)],tblEnlaces[Nodo Origen],$C12,tblEnlaces[Nodo Destino],D$3,tblEnlaces[Activo],1),0) -> 0 | E12: =IF(MatrizDeAdyacencia!E12=1,SUMIFS(tblEnlaces[Coste (peso)],tblEnlaces[Nodo Origen],$C12,tblEnlaces[Nodo Destino],E$3,tblEnlaces[Activo],1),0) -> 0 | F12: =IF(MatrizDeAdyacencia!F12=1,SUMIFS(tblEnlaces[Coste (peso)],tblEnlaces[Nodo Origen],$C12,tblEnlaces[Nodo Destino],F$3,tblEnlaces[Activo],1),0) -> 0 | G12: =IF(MatrizDeAdyacencia!G12=1,SUMIFS(tblEnlaces[Coste (peso)],tblEnlaces[Nodo Origen],$C12,tblEnlaces[Nodo Destino],G$3,tblEnlaces[Activo],1),0) -> 0 | H12: =IF(MatrizDeAdyacencia!H12=1,SUMIFS(tblEnlaces[Coste (peso)],tblEnlaces[Nodo Origen],$C12,tblEnlaces[Nodo Destino],H$3,tblEnlaces[Activo],1),0) -> 0 | I12: =IF(MatrizDeAdyacencia!I12=1,SUMIFS(tblEnlaces[Coste (peso)],tblEnlaces[Nodo Origen],$C12,tblEnlaces[Nodo Destino],I$3,tblEnlaces[Activo],1),0) -> 0 | J12: =IF(MatrizDeAdyacencia!J12=1,SUMIFS(tblEnlaces[Coste (peso)],tblEnlaces[Nodo Origen],$C12,tblEnlaces[Nodo Destino],J$3,tblEnlaces[Activo],1),0) -> 0 | K12: =IF(MatrizDeAdyacencia!K12=1,SUMIFS(tblEnlaces[Coste (peso)],tblEnlaces[Nodo Origen],$C12,tblEnlaces[Nodo Destino],K$3,tblEnlaces[Activo],1),0) -> 0 | ... V12: =IF(MatrizDeAdyacencia!V12=1,SUMIFS(tblEnlaces[Coste (peso)],tblEnlaces[Nodo Origen],$C12,tblEnlaces[Nodo Destino],V$3,tblEnlaces[Activo],1),0) -> 3 | Y12: Rango del Enlace | Z12: Coste
B13: =VLOOKUP(tblMatrizPonderadaCostes[[#This Row],[NodoOrigen \ NodoDestino]],tblNodos[#All],2,FALSE) -> Dinero móvil | C13: I4 | D13: =IF(MatrizDeAdyacencia!D13=1,SUMIFS(tblEnlaces[Coste (peso)],tblEnlaces[Nodo Origen],$C13,tblEnlaces[Nodo Destino],D$3,tblEnlaces[Activo],1),0) -> 0 | E13: =IF(MatrizDeAdyacencia!E13=1,SUMIFS(tblEnlaces[Coste (peso)],tblEnlaces[Nodo Origen],$C13,tblEnlaces[Nodo Destino],E$3,tblEnlaces[Activo],1),0) -> 0 | F13: =IF(MatrizDeAdyacencia!F13=1,SUMIFS(tblEnlaces[Coste (peso)],tblEnlaces[Nodo Origen],$C13,tblEnlaces[Nodo Destino],F$3,tblEnlaces[Activo],1),0) -> 0 | G13: =IF(MatrizDeAdyacencia!G13=1,SUMIFS(tblEnlaces[Coste (peso)],tblEnlaces[Nodo Origen],$C13,tblEnlaces[Nodo Destino],G$3,tblEnlaces[Activo],1),0) -> 0 | H13: =IF(MatrizDeAdyacencia!H13=1,SUMIFS(tblEnlaces[Coste (peso)],tblEnlaces[Nodo Origen],$C13,tblEnlaces[Nodo Destino],H$3,tblEnlaces[Activo],1),0) -> 0 | I13: =IF(MatrizDeAdyacencia!I13=1,SUMIFS(tblEnlaces[Coste (peso)],tblEnlaces[Nodo Origen],$C13,tblEnlaces[Nodo Destino],I$3,tblEnlaces[Activo],1),0) -> 0 | J13: =IF(MatrizDeAdyacencia!J13=1,SUMIFS(tblEnlaces[Coste (peso)],tblEnlaces[Nodo Origen],$C13,tblEnlaces[Nodo Destino],J$3,tblEnlaces[Activo],1),0) -> 0 | K13: =IF(MatrizDeAdyacencia!K13=1,SUMIFS(tblEnlaces[Coste (peso)],tblEnlaces[Nodo Origen],$C13,tblEnlaces[Nodo Destino],K$3,tblEnlaces[Activo],1),0) -> 0 | ... V13: =IF(MatrizDeAdyacencia!V13=1,SUMIFS(tblEnlaces[Coste (peso)],tblEnlaces[Nodo Origen],$C13,tblEnlaces[Nodo Destino],V$3,tblEnlaces[Activo],1),0) -> 0 | Y13: Mínimo posible | Z13: =MIN(tblPesosCoste[Coste]) -> 1
B14: =VLOOKUP(tblMatrizPonderadaCostes[[#This Row],[NodoOrigen \ NodoDestino]],tblNodos[#All],2,FALSE) -> Pagos online | C14: I5 | D14: =IF(MatrizDeAdyacencia!D14=1,SUMIFS(tblEnlaces[Coste (peso)],tblEnlaces[Nodo Origen],$C14,tblEnlaces[Nodo Destino],D$3,tblEnlaces[Activo],1),0) -> 0 | E14: =IF(MatrizDeAdyacencia!E14=1,SUMIFS(tblEnlaces[Coste (peso)],tblEnlaces[Nodo Origen],$C14,tblEnlaces[Nodo Destino],E$3,tblEnlaces[Activo],1),0) -> 0 | F14: =IF(MatrizDeAdyacencia!F14=1,SUMIFS(tblEnlaces[Coste (peso)],tblEnlaces[Nodo Origen],$C14,tblEnlaces[Nodo Destino],F$3,tblEnlaces[Activo],1),0) -> 0 | G14: =IF(MatrizDeAdyacencia!G14=1,SUMIFS(tblEnlaces[Coste (peso)],tblEnlaces[Nodo Origen],$C14,tblEnlaces[Nodo Destino],G$3,tblEnlaces[Activo],1),0) -> 0 | H14: =IF(MatrizDeAdyacencia!H14=1,SUMIFS(tblEnlaces[Coste (peso)],tblEnlaces[Nodo Origen],$C14,tblEnlaces[Nodo Destino],H$3,tblEnlaces[Activo],1),0) -> 0 | I14: =IF(MatrizDeAdyacencia!I14=1,SUMIFS(tblEnlaces[Coste (peso)],tblEnlaces[Nodo Origen],$C14,tblEnlaces[Nodo Destino],I$3,tblEnlaces[Activo],1),0) -> 0 | J14: =IF(MatrizDeAdyacencia!J14=1,SUMIFS(tblEnlaces[Coste (peso)],tblEnlaces[Nodo Origen],$C14,tblEnlaces[Nodo Destino],J$3,tblEnlaces[Activo],1),0) -> 0 | K14: =IF(MatrizDeAdyacencia!K14=1,SUMIFS(tblEnlaces[Coste (peso)],tblEnlaces[Nodo Origen],$C14,tblEnlaces[Nodo Destino],K$3,tblEnlaces[Activo],1),0) -> 0 | ... V14: =IF(MatrizDeAdyacencia!V14=1,SUMIFS(tblEnlaces[Coste (peso)],tblEnlaces[Nodo Origen],$C14,tblEnlaces[Nodo Destino],V$3,tblEnlaces[Activo],1),0) -> 0 | Y14: Máximo posible | Z14: =MAX(tblPesosCoste[Coste]) -> 5
B15: =VLOOKUP(tblMatrizPonderadaCostes[[#This Row],[NodoOrigen \ NodoDestino]],tblNodos[#All],2,FALSE) -> Servicios bancarios | C15: I6 | D15: =IF(MatrizDeAdyacencia!D15=1,SUMIFS(tblEnlaces[Coste (peso)],tblEnlaces[Nodo Origen],$C15,tblEnlaces[Nodo Destino],D$3,tblEnlaces[Activo],1),0) -> 0 | E15: =IF(MatrizDeAdyacencia!E15=1,SUMIFS(tblEnlaces[Coste (peso)],tblEnlaces[Nodo Origen],$C15,tblEnlaces[Nodo Destino],E$3,tblEnlaces[Activo],1),0) -> 0 | F15: =IF(MatrizDeAdyacencia!F15=1,SUMIFS(tblEnlaces[Coste (peso)],tblEnlaces[Nodo Origen],$C15,tblEnlaces[Nodo Destino],F$3,tblEnlaces[Activo],1),0) -> 0 | G15: =IF(MatrizDeAdyacencia!G15=1,SUMIFS(tblEnlaces[Coste (peso)],tblEnlaces[Nodo Origen],$C15,tblEnlaces[Nodo Destino],G$3,tblEnlaces[Activo],1),0) -> 0 | H15: =IF(MatrizDeAdyacencia!H15=1,SUMIFS(tblEnlaces[Coste (peso)],tblEnlaces[Nodo Origen],$C15,tblEnlaces[Nodo Destino],H$3,tblEnlaces[Activo],1),0) -> 0 | I15: =IF(MatrizDeAdyacencia!I15=1,SUMIFS(tblEnlaces[Coste (peso)],tblEnlaces[Nodo Origen],$C15,tblEnlaces[Nodo Destino],I$3,tblEnlaces[Activo],1),0) -> 0 | J15: =IF(MatrizDeAdyacencia!J15=1,SUMIFS(tblEnlaces[Coste (peso)],tblEnlaces[Nodo Origen],$C15,tblEnlaces[Nodo Destino],J$3,tblEnlaces[Activo],1),0) -> 0 | K15: =IF(MatrizDeAdyacencia!K15=1,SUMIFS(tblEnlaces[Coste (peso)],tblEnlaces[Nodo Origen],$C15,tblEnlaces[Nodo Destino],K$3,tblEnlaces[Activo],1),0) -> 0 | ... V15: =IF(MatrizDeAdyacencia!V15=1,SUMIFS(tblEnlaces[Coste (peso)],tblEnlaces[Nodo Origen],$C15,tblEnlaces[Nodo Destino],V$3,tblEnlaces[Activo],1),0) -> 0
B16: =VLOOKUP(tblMatrizPonderadaCostes[[#This Row],[NodoOrigen \ NodoDestino]],tblNodos[#All],2,FALSE) -> Tarjetas prepago / e-wallets | C16: I7 | D16: =IF(MatrizDeAdyacencia!D16=1,SUMIFS(tblEnlaces[Coste (peso)],tblEnlaces[Nodo Origen],$C16,tblEnlaces[Nodo Destino],D$3,tblEnlaces[Activo],1),0) -> 0 | E16: =IF(MatrizDeAdyacencia!E16=1,SUMIFS(tblEnlaces[Coste (peso)],tblEnlaces[Nodo Origen],$C16,tblEnlaces[Nodo Destino],E$3,tblEnlaces[Activo],1),0) -> 0 | F16: =IF(MatrizDeAdyacencia!F16=1,SUMIFS(tblEnlaces[Coste (peso)],tblEnlaces[Nodo Origen],$C16,tblEnlaces[Nodo Destino],F$3,tblEnlaces[Activo],1),0) -> 0 | G16: =IF(MatrizDeAdyacencia!G16=1,SUMIFS(tblEnlaces[Coste (peso)],tblEnlaces[Nodo Origen],$C16,tblEnlaces[Nodo Destino],G$3,tblEnlaces[Activo],1),0) -> 0 | H16: =IF(MatrizDeAdyacencia!H16=1,SUMIFS(tblEnlaces[Coste (peso)],tblEnlaces[Nodo Origen],$C16,tblEnlaces[Nodo Destino],H$3,tblEnlaces[Activo],1),0) -> 0 | I16: =IF(MatrizDeAdyacencia!I16=1,SUMIFS(tblEnlaces[Coste (peso)],tblEnlaces[Nodo Origen],$C16,tblEnlaces[Nodo Destino],I$3,tblEnlaces[Activo],1),0) -> 0 | J16: =IF(MatrizDeAdyacencia!J16=1,SUMIFS(tblEnlaces[Coste (peso)],tblEnlaces[Nodo Origen],$C16,tblEnlaces[Nodo Destino],J$3,tblEnlaces[Activo],1),0) -> 0 | K16: =IF(MatrizDeAdyacencia!K16=1,SUMIFS(tblEnlaces[Coste (peso)],tblEnlaces[Nodo Origen],$C16,tblEnlaces[Nodo Destino],K$3,tblEnlaces[Activo],1),0) -> 0 | ... V16: =IF(MatrizDeAdyacencia!V16=1,SUMIFS(tblEnlaces[Coste (peso)],tblEnlaces[Nodo Origen],$C16,tblEnlaces[Nodo Destino],V$3,tblEnlaces[Activo],1),0) -> 0
B17: =VLOOKUP(tblMatrizPonderadaCostes[[#This Row],[NodoOrigen \ NodoDestino]],tblNodos[#All],2,FALSE) -> Plataformas digitales | C17: I8 | D17: =IF(MatrizDeAdyacencia!D17=1,SUMIFS(tblEnlaces[Coste (peso)],tblEnlaces[Nodo Origen],$C17,tblEnlaces[Nodo Destino],D$3,tblEnlaces[Activo],1),0) -> 0 | E17: =IF(MatrizDeAdyacencia!E17=1,SUMIFS(tblEnlaces[Coste (peso)],tblEnlaces[Nodo Origen],$C17,tblEnlaces[Nodo Destino],E$3,tblEnlaces[Activo],1),0) -> 0 | F17: =IF(MatrizDeAdyacencia!F17=1,SUMIFS(tblEnlaces[Coste (peso)],tblEnlaces[Nodo Origen],$C17,tblEnlaces[Nodo Destino],F$3,tblEnlaces[Activo],1),0) -> 0 | G17: =IF(MatrizDeAdyacencia!G17=1,SUMIFS(tblEnlaces[Coste (peso)],tblEnlaces[Nodo Origen],$C17,tblEnlaces[Nodo Destino],G$3,tblEnlaces[Activo],1),0) -> 0 | H17: =IF(MatrizDeAdyacencia!H17=1,SUMIFS(tblEnlaces[Coste (peso)],tblEnlaces[Nodo Origen],$C17,tblEnlaces[Nodo Destino],H$3,tblEnlaces[Activo],1),0) -> 0 | I17: =IF(MatrizDeAdyacencia!I17=1,SUMIFS(tblEnlaces[Coste (peso)],tblEnlaces[Nodo Origen],$C17,tblEnlaces[Nodo Destino],I$3,tblEnlaces[Activo],1),0) -> 0 | J17: =IF(MatrizDeAdyacencia!J17=1,SUMIFS(tblEnlaces[Coste (peso)],tblEnlaces[Nodo Origen],$C17,tblEnlaces[Nodo Destino],J$3,tblEnlaces[Activo],1),0) -> 0 | K17: =IF(MatrizDeAdyacencia!K17=1,SUMIFS(tblEnlaces[Coste (peso)],tblEnlaces[Nodo Origen],$C17,tblEnlaces[Nodo Destino],K$3,tblEnlaces[Activo],1),0) -> 0 | ... V17: =IF(MatrizDeAdyacencia!V17=1,SUMIFS(tblEnlaces[Coste (peso)],tblEnlaces[Nodo Origen],$C17,tblEnlaces[Nodo Destino],V$3,tblEnlaces[Activo],1),0) -> 0
B18: =VLOOKUP(tblMatrizPonderadaCostes[[#This Row],[NodoOrigen \ NodoDestino]],tblNodos[#All],2,FALSE) -> Activos virtuales | C18: I9 | D18: =IF(MatrizDeAdyacencia!D18=1,SUMIFS(tblEnlaces[Coste (peso)],tblEnlaces[Nodo Origen],$C18,tblEnlaces[Nodo Destino],D$3,tblEnlaces[Activo],1),0) -> 0 | E18: =IF(MatrizDeAdyacencia!E18=1,SUMIFS(tblEnlaces[Coste (peso)],tblEnlaces[Nodo Origen],$C18,tblEnlaces[Nodo Destino],E$3,tblEnlaces[Activo],1),0) -> 0 | F18: =IF(MatrizDeAdyacencia!F18=1,SUMIFS(tblEnlaces[Coste (peso)],tblEnlaces[Nodo Origen],$C18,tblEnlaces[Nodo Destino],F$3,tblEnlaces[Activo],1),0) -> 0 | G18: =IF(MatrizDeAdyacencia!G18=1,SUMIFS(tblEnlaces[Coste (peso)],tblEnlaces[Nodo Origen],$C18,tblEnlaces[Nodo Destino],G$3,tblEnlaces[Activo],1),0) -> 0 | H18: =IF(MatrizDeAdyacencia!H18=1,SUMIFS(tblEnlaces[Coste (peso)],tblEnlaces[Nodo Origen],$C18,tblEnlaces[Nodo Destino],H$3,tblEnlaces[Activo],1),0) -> 0 | I18: =IF(MatrizDeAdyacencia!I18=1,SUMIFS(tblEnlaces[Coste (peso)],tblEnlaces[Nodo Origen],$C18,tblEnlaces[Nodo Destino],I$3,tblEnlaces[Activo],1),0) -> 0 | J18: =IF(MatrizDeAdyacencia!J18=1,SUMIFS(tblEnlaces[Coste (peso)],tblEnlaces[Nodo Origen],$C18,tblEnlaces[Nodo Destino],J$3,tblEnlaces[Activo],1),0) -> 0 | K18: =IF(MatrizDeAdyacencia!K18=1,SUMIFS(tblEnlaces[Coste (peso)],tblEnlaces[Nodo Origen],$C18,tblEnlaces[Nodo Destino],K$3,tblEnlaces[Activo],1),0) -> 0 | ... V18: =IF(MatrizDeAdyacencia!V18=1,SUMIFS(tblEnlaces[Coste (peso)],tblEnlaces[Nodo Origen],$C18,tblEnlaces[Nodo Destino],V$3,tblEnlaces[Activo],1),0) -> 0
B19: =VLOOKUP(tblMatrizPonderadaCostes[[#This Row],[NodoOrigen \ NodoDestino]],tblNodos[#All],2,FALSE) -> Tesorería central | C19: G1 | D19: =IF(MatrizDeAdyacencia!D19=1,SUMIFS(tblEnlaces[Coste (peso)],tblEnlaces[Nodo Origen],$C19,tblEnlaces[Nodo Destino],D$3,tblEnlaces[Activo],1),0) -> 0 | E19: =IF(MatrizDeAdyacencia!E19=1,SUMIFS(tblEnlaces[Coste (peso)],tblEnlaces[Nodo Origen],$C19,tblEnlaces[Nodo Destino],E$3,tblEnlaces[Activo],1),0) -> 0 | F19: =IF(MatrizDeAdyacencia!F19=1,SUMIFS(tblEnlaces[Coste (peso)],tblEnlaces[Nodo Origen],$C19,tblEnlaces[Nodo Destino],F$3,tblEnlaces[Activo],1),0) -> 0 | G19: =IF(MatrizDeAdyacencia!G19=1,SUMIFS(tblEnlaces[Coste (peso)],tblEnlaces[Nodo Origen],$C19,tblEnlaces[Nodo Destino],G$3,tblEnlaces[Activo],1),0) -> 0 | H19: =IF(MatrizDeAdyacencia!H19=1,SUMIFS(tblEnlaces[Coste (peso)],tblEnlaces[Nodo Origen],$C19,tblEnlaces[Nodo Destino],H$3,tblEnlaces[Activo],1),0) -> 0 | I19: =IF(MatrizDeAdyacencia!I19=1,SUMIFS(tblEnlaces[Coste (peso)],tblEnlaces[Nodo Origen],$C19,tblEnlaces[Nodo Destino],I$3,tblEnlaces[Activo],1),0) -> 0 | J19: =IF(MatrizDeAdyacencia!J19=1,SUMIFS(tblEnlaces[Coste (peso)],tblEnlaces[Nodo Origen],$C19,tblEnlaces[Nodo Destino],J$3,tblEnlaces[Activo],1),0) -> 3 | K19: =IF(MatrizDeAdyacencia!K19=1,SUMIFS(tblEnlaces[Coste (peso)],tblEnlaces[Nodo Origen],$C19,tblEnlaces[Nodo Destino],K$3,tblEnlaces[Activo],1),0) -> 0 | ... V19: =IF(MatrizDeAdyacencia!V19=1,SUMIFS(tblEnlaces[Coste (peso)],tblEnlaces[Nodo Origen],$C19,tblEnlaces[Nodo Destino],V$3,tblEnlaces[Activo],1),0) -> 5
B20: =VLOOKUP(tblMatrizPonderadaCostes[[#This Row],[NodoOrigen \ NodoDestino]],tblNodos[#All],2,FALSE) -> Centro financiero regional / célula | C20: G2 | D20: =IF(MatrizDeAdyacencia!D20=1,SUMIFS(tblEnlaces[Coste (peso)],tblEnlaces[Nodo Origen],$C20,tblEnlaces[Nodo Destino],D$3,tblEnlaces[Activo],1),0) -> 0 | E20: =IF(MatrizDeAdyacencia!E20=1,SUMIFS(tblEnlaces[Coste (peso)],tblEnlaces[Nodo Origen],$C20,tblEnlaces[Nodo Destino],E$3,tblEnlaces[Activo],1),0) -> 0 | F20: =IF(MatrizDeAdyacencia!F20=1,SUMIFS(tblEnlaces[Coste (peso)],tblEnlaces[Nodo Origen],$C20,tblEnlaces[Nodo Destino],F$3,tblEnlaces[Activo],1),0) -> 0 | G20: =IF(MatrizDeAdyacencia!G20=1,SUMIFS(tblEnlaces[Coste (peso)],tblEnlaces[Nodo Origen],$C20,tblEnlaces[Nodo Destino],G$3,tblEnlaces[Activo],1),0) -> 0 | H20: =IF(MatrizDeAdyacencia!H20=1,SUMIFS(tblEnlaces[Coste (peso)],tblEnlaces[Nodo Origen],$C20,tblEnlaces[Nodo Destino],H$3,tblEnlaces[Activo],1),0) -> 0 | I20: =IF(MatrizDeAdyacencia!I20=1,SUMIFS(tblEnlaces[Coste (peso)],tblEnlaces[Nodo Origen],$C20,tblEnlaces[Nodo Destino],I$3,tblEnlaces[Activo],1),0) -> 0 | J20: =IF(MatrizDeAdyacencia!J20=1,SUMIFS(tblEnlaces[Coste (peso)],tblEnlaces[Nodo Origen],$C20,tblEnlaces[Nodo Destino],J$3,tblEnlaces[Activo],1),0) -> 5 | K20: =IF(MatrizDeAdyacencia!K20=1,SUMIFS(tblEnlaces[Coste (peso)],tblEnlaces[Nodo Origen],$C20,tblEnlaces[Nodo Destino],K$3,tblEnlaces[Activo],1),0) -> 3 | ... V20: =IF(MatrizDeAdyacencia!V20=1,SUMIFS(tblEnlaces[Coste (peso)],tblEnlaces[Nodo Origen],$C20,tblEnlaces[Nodo Destino],V$3,tblEnlaces[Activo],1),0) -> 5
B21: =VLOOKUP(tblMatrizPonderadaCostes[[#This Row],[NodoOrigen \ NodoDestino]],tblNodos[#All],2,FALSE) -> Facilitador externo / entidad instrumental | C21: G3 | D21: =IF(MatrizDeAdyacencia!D21=1,SUMIFS(tblEnlaces[Coste (peso)],tblEnlaces[Nodo Origen],$C21,tblEnlaces[Nodo Destino],D$3,tblEnlaces[Activo],1),0) -> 0 | E21: =IF(MatrizDeAdyacencia!E21=1,SUMIFS(tblEnlaces[Coste (peso)],tblEnlaces[Nodo Origen],$C21,tblEnlaces[Nodo Destino],E$3,tblEnlaces[Activo],1),0) -> 0 | F21: =IF(MatrizDeAdyacencia!F21=1,SUMIFS(tblEnlaces[Coste (peso)],tblEnlaces[Nodo Origen],$C21,tblEnlaces[Nodo Destino],F$3,tblEnlaces[Activo],1),0) -> 0 | G21: =IF(MatrizDeAdyacencia!G21=1,SUMIFS(tblEnlaces[Coste (peso)],tblEnlaces[Nodo Origen],$C21,tblEnlaces[Nodo Destino],G$3,tblEnlaces[Activo],1),0) -> 0 | H21: =IF(MatrizDeAdyacencia!H21=1,SUMIFS(tblEnlaces[Coste (peso)],tblEnlaces[Nodo Origen],$C21,tblEnlaces[Nodo Destino],H$3,tblEnlaces[Activo],1),0) -> 0 | I21: =IF(MatrizDeAdyacencia!I21=1,SUMIFS(tblEnlaces[Coste (peso)],tblEnlaces[Nodo Origen],$C21,tblEnlaces[Nodo Destino],I$3,tblEnlaces[Activo],1),0) -> 0 | J21: =IF(MatrizDeAdyacencia!J21=1,SUMIFS(tblEnlaces[Coste (peso)],tblEnlaces[Nodo Origen],$C21,tblEnlaces[Nodo Destino],J$3,tblEnlaces[Activo],1),0) -> 0 | K21: =IF(MatrizDeAdyacencia!K21=1,SUMIFS(tblEnlaces[Coste (peso)],tblEnlaces[Nodo Origen],$C21,tblEnlaces[Nodo Destino],K$3,tblEnlaces[Activo],1),0) -> 0 | ... V21: =IF(MatrizDeAdyacencia!V21=1,SUMIFS(tblEnlaces[Coste (peso)],tblEnlaces[Nodo Origen],$C21,tblEnlaces[Nodo Destino],V$3,tblEnlaces[Activo],1),0) -> 5
B22: =VLOOKUP(tblMatrizPonderadaCostes[[#This Row],[NodoOrigen \ NodoDestino]],tblNodos[#All],2,FALSE) -> Destino operativo | C22: D | D22: =IF(MatrizDeAdyacencia!D22=1,SUMIFS(tblEnlaces[Coste (peso)],tblEnlaces[Nodo Origen],$C22,tblEnlaces[Nodo Destino],D$3,tblEnlaces[Activo],1),0) -> 0 | E22: =IF(MatrizDeAdyacencia!E22=1,SUMIFS(tblEnlaces[Coste (peso)],tblEnlaces[Nodo Origen],$C22,tblEnlaces[Nodo Destino],E$3,tblEnlaces[Activo],1),0) -> 0 | F22: =IF(MatrizDeAdyacencia!F22=1,SUMIFS(tblEnlaces[Coste (peso)],tblEnlaces[Nodo Origen],$C22,tblEnlaces[Nodo Destino],F$3,tblEnlaces[Activo],1),0) -> 0 | G22: =IF(MatrizDeAdyacencia!G22=1,SUMIFS(tblEnlaces[Coste (peso)],tblEnlaces[Nodo Origen],$C22,tblEnlaces[Nodo Destino],G$3,tblEnlaces[Activo],1),0) -> 0 | H22: =IF(MatrizDeAdyacencia!H22=1,SUMIFS(tblEnlaces[Coste (peso)],tblEnlaces[Nodo Origen],$C22,tblEnlaces[Nodo Destino],H$3,tblEnlaces[Activo],1),0) -> 0 | I22: =IF(MatrizDeAdyacencia!I22=1,SUMIFS(tblEnlaces[Coste (peso)],tblEnlaces[Nodo Origen],$C22,tblEnlaces[Nodo Destino],I$3,tblEnlaces[Activo],1),0) -> 0 | J22: =IF(MatrizDeAdyacencia!J22=1,SUMIFS(tblEnlaces[Coste (peso)],tblEnlaces[Nodo Origen],$C22,tblEnlaces[Nodo Destino],J$3,tblEnlaces[Activo],1),0) -> 0 | K22: =IF(MatrizDeAdyacencia!K22=1,SUMIFS(tblEnlaces[Coste (peso)],tblEnlaces[Nodo Origen],$C22,tblEnlaces[Nodo Destino],K$3,tblEnlaces[Activo],1),0) -> 0 | ... V22: =IF(MatrizDeAdyacencia!V22=1,SUMIFS(tblEnlaces[Coste (peso)],tblEnlaces[Nodo Origen],$C22,tblEnlaces[Nodo Destino],V$3,tblEnlaces[Activo],1),0) -> 0

Sheet MatrizPonderadaValorOperativo
B2: Matriz Ponderada de Valor Operativo | D2: =VLOOKUP(tblMatrizPonderadaValorOperativo[[#Headers],[O1]],tblNodos[#All],2,FALSE) -> Coerción y cobros forzosos | E2: =VLOOKUP(tblMatrizPonderadaValorOperativo[[#Headers],[O2]],tblNodos[#All],2,FALSE) -> Contrabando / tráfico / comercio ilícito | F2: =VLOOKUP(tblMatrizPonderadaValorOperativo[[#Headers],[O3]],tblNodos[#All],2,FALSE) -> Explotación de recursos naturales | G2: =VLOOKUP(tblMatrizPonderadaValorOperativo[[#Headers],[O4]],tblNodos[#All],2,FALSE) -> Autofinanciación lícita / microfinanciación | H2: =VLOOKUP(tblMatrizPonderadaValorOperativo[[#Headers],[O5]],tblNodos[#All],2,FALSE) -> Actividades económicas formales / negocios | I2: =VLOOKUP(tblMatrizPonderadaValorOperativo[[#Headers],[O6]],tblNodos[#All],2,FALSE) -> Donaciones / crowdfunding / apoyo online | J2: =VLOOKUP(tblMatrizPonderadaValorOperativo[[#Headers],[I1]],tblNodos[#All],2,FALSE) -> Efectivo | K2: =VLOOKUP(tblMatrizPonderadaValorOperativo[[#Headers],[I2]],tblNodos[#All],2,FALSE) -> Hawala / HOSSP | L2: =VLOOKUP(tblMatrizPonderadaValorOperativo[[#Headers],[I3]],tblNodos[#All],2,FALSE) -> MVTS / remesas | M2: =VLOOKUP(tblMatrizPonderadaValorOperativo[[#Headers],[I4]],tblNodos[#All],2,FALSE) -> Dinero móvil | N2: =VLOOKUP(tblMatrizPonderadaValorOperativo[[#Headers],[I5]],tblNodos[#All],2,FALSE) -> Pagos online | O2: =VLOOKUP(tblMatrizPonderadaValorOperativo[[#Headers],[I6]],tblNodos[#All],2,FALSE) -> Servicios bancarios | P2: =VLOOKUP(tblMatrizPonderadaValorOperativo[[#Headers],[I7]],tblNodos[#All],2,FALSE) -> Tarjetas prepago / e-wallets | Q2: =VLOOKUP(tblMatrizPonderadaValorOperativo[[#Headers],[I8]],tblNodos[#All],2,FALSE) -> Plataformas digitales | R2: =VLOOKUP(tblMatrizPonderadaValorOperativo[[#Headers],[I9]],tblNodos[#All],2,FALSE) -> Activos virtuales | S2: =VLOOKUP(tblMatrizPonderadaValorOperativo[[#Headers],[G1]],tblNodos[#All],2,FALSE) -> Tesorería central | T2: =VLOOKUP(tblMatrizPonderadaValorOperativo[[#Headers],[G2]],tblNodos[#All],2,FALSE) -> Centro financiero regional / célula | U2: =VLOOKUP(tblMatrizPonderadaValorOperativo[[#Headers],[G3]],tblNodos[#All],2,FALSE) -> Facilitador externo / entidad instrumental | V2: =VLOOKUP(tblMatrizPonderadaValorOperativo[[#Headers],[D]],tblNodos[#All],2,FALSE) -> Destino operativo
B3: Nombre Nodo | C3: NodoOrigen \ NodoDestino | D3: O1 | E3: O2 | F3: O3 | G3: O4 | H3: O5 | I3: O6 | J3: I1 | K3: I2 | L3: I3 | M3: I4 | N3: I5 | O3: I6 | P3: I7 | Q3: I8 | R3: I9 | S3: G1 | T3: G2 | U3: G3 | V3: D | Y3: Pesos por Propiedad del Enlace
B4: =VLOOKUP(tblMatrizPonderadaValorOperativo[[#This Row],[NodoOrigen \ NodoDestino]],tblNodos[#All],2,FALSE) -> Coerción y cobros forzosos | C4: O1 | D4: =IF(MatrizDeAdyacencia!D4=1, SUMIFS(tblEnlaces[ValorOperativo (peso)], tblEnlaces[Nodo Origen], $C4, tblEnlaces[Nodo Destino], D$3, tblEnlaces[Activo], 1), 0) -> 0 | E4: =IF(MatrizDeAdyacencia!E4=1, SUMIFS(tblEnlaces[ValorOperativo (peso)], tblEnlaces[Nodo Origen], $C4, tblEnlaces[Nodo Destino], E$3, tblEnlaces[Activo], 1), 0) -> 0 | F4: =IF(MatrizDeAdyacencia!F4=1, SUMIFS(tblEnlaces[ValorOperativo (peso)], tblEnlaces[Nodo Origen], $C4, tblEnlaces[Nodo Destino], F$3, tblEnlaces[Activo], 1), 0) -> 0 | G4: =IF(MatrizDeAdyacencia!G4=1, SUMIFS(tblEnlaces[ValorOperativo (peso)], tblEnlaces[Nodo Origen], $C4, tblEnlaces[Nodo Destino], G$3, tblEnlaces[Activo], 1), 0) -> 0 | H4: =IF(MatrizDeAdyacencia!H4=1, SUMIFS(tblEnlaces[ValorOperativo (peso)], tblEnlaces[Nodo Origen], $C4, tblEnlaces[Nodo Destino], H$3, tblEnlaces[Activo], 1), 0) -> 0 | I4: =IF(MatrizDeAdyacencia!I4=1, SUMIFS(tblEnlaces[ValorOperativo (peso)], tblEnlaces[Nodo Origen], $C4, tblEnlaces[Nodo Destino], I$3, tblEnlaces[Activo], 1), 0) -> 0 | J4: =IF(MatrizDeAdyacencia!J4=1, SUMIFS(tblEnlaces[ValorOperativo (peso)], tblEnlaces[Nodo Origen], $C4, tblEnlaces[Nodo Destino], J$3, tblEnlaces[Activo], 1), 0) -> 18 | K4: =IF(MatrizDeAdyacencia!K4=1, SUMIFS(tblEnlaces[ValorOperativo (peso)], tblEnlaces[Nodo Origen], $C4, tblEnlaces[Nodo Destino], K$3, tblEnlaces[Activo], 1), 0) -> 18 | ... V4: =IF(MatrizDeAdyacencia!V4=1, SUMIFS(tblEnlaces[ValorOperativo (peso)], tblEnlaces[Nodo Origen], $C4, tblEnlaces[Nodo Destino], V$3, tblEnlaces[Activo], 1), 0) -> 0 | Y4: Valor | Z4: Eficiencia | AA4: Exposición | AB4: Capacidad | AC4: Resiliencia
B5: =VLOOKUP(tblMatrizPonderadaValorOperativo[[#This Row],[NodoOrigen \ NodoDestino]],tblNodos[#All],2,FALSE) -> Contrabando / tráfico / comercio ilícito | C5: O2 | D5: =IF(MatrizDeAdyacencia!D5=1, SUMIFS(tblEnlaces[ValorOperativo (peso)], tblEnlaces[Nodo Origen], $C5, tblEnlaces[Nodo Destino], D$3, tblEnlaces[Activo], 1), 0) -> 0 | E5: =IF(MatrizDeAdyacencia!E5=1, SUMIFS(tblEnlaces[ValorOperativo (peso)], tblEnlaces[Nodo Origen], $C5, tblEnlaces[Nodo Destino], E$3, tblEnlaces[Activo], 1), 0) -> 0 | F5: =IF(MatrizDeAdyacencia!F5=1, SUMIFS(tblEnlaces[ValorOperativo (peso)], tblEnlaces[Nodo Origen], $C5, tblEnlaces[Nodo Destino], F$3, tblEnlaces[Activo], 1), 0) -> 0 | G5: =IF(MatrizDeAdyacencia!G5=1, SUMIFS(tblEnlaces[ValorOperativo (peso)], tblEnlaces[Nodo Origen], $C5, tblEnlaces[Nodo Destino], G$3, tblEnlaces[Activo], 1), 0) -> 0 | H5: =IF(MatrizDeAdyacencia!H5=1, SUMIFS(tblEnlaces[ValorOperativo (peso)], tblEnlaces[Nodo Origen], $C5, tblEnlaces[Nodo Destino], H$3, tblEnlaces[Activo], 1), 0) -> 0 | I5: =IF(MatrizDeAdyacencia!I5=1, SUMIFS(tblEnlaces[ValorOperativo (peso)], tblEnlaces[Nodo Origen], $C5, tblEnlaces[Nodo Destino], I$3, tblEnlaces[Activo], 1), 0) -> 0 | J5: =IF(MatrizDeAdyacencia!J5=1, SUMIFS(tblEnlaces[ValorOperativo (peso)], tblEnlaces[Nodo Origen], $C5, tblEnlaces[Nodo Destino], J$3, tblEnlaces[Activo], 1), 0) -> 17 | K5: =IF(MatrizDeAdyacencia!K5=1, SUMIFS(tblEnlaces[ValorOperativo (peso)], tblEnlaces[Nodo Origen], $C5, tblEnlaces[Nodo Destino], K$3, tblEnlaces[Activo], 1), 0) -> 19 | ... V5: =IF(MatrizDeAdyacencia!V5=1, SUMIFS(tblEnlaces[ValorOperativo (peso)], tblEnlaces[Nodo Origen], $C5, tblEnlaces[Nodo Destino], V$3, tblEnlaces[Activo], 1), 0) -> 0 | Y5: Bajo | Z5: 1 | AA5: 5 | AB5: 1 | AC5: 1
B6: =VLOOKUP(tblMatrizPonderadaValorOperativo[[#This Row],[NodoOrigen \ NodoDestino]],tblNodos[#All],2,FALSE) -> Explotación de recursos naturales | C6: O3 | D6: =IF(MatrizDeAdyacencia!D6=1, SUMIFS(tblEnlaces[ValorOperativo (peso)], tblEnlaces[Nodo Origen], $C6, tblEnlaces[Nodo Destino], D$3, tblEnlaces[Activo], 1), 0) -> 0 | E6: =IF(MatrizDeAdyacencia!E6=1, SUMIFS(tblEnlaces[ValorOperativo (peso)], tblEnlaces[Nodo Origen], $C6, tblEnlaces[Nodo Destino], E$3, tblEnlaces[Activo], 1), 0) -> 0 | F6: =IF(MatrizDeAdyacencia!F6=1, SUMIFS(tblEnlaces[ValorOperativo (peso)], tblEnlaces[Nodo Origen], $C6, tblEnlaces[Nodo Destino], F$3, tblEnlaces[Activo], 1), 0) -> 0 | G6: =IF(MatrizDeAdyacencia!G6=1, SUMIFS(tblEnlaces[ValorOperativo (peso)], tblEnlaces[Nodo Origen], $C6, tblEnlaces[Nodo Destino], G$3, tblEnlaces[Activo], 1), 0) -> 0 | H6: =IF(MatrizDeAdyacencia!H6=1, SUMIFS(tblEnlaces[ValorOperativo (peso)], tblEnlaces[Nodo Origen], $C6, tblEnlaces[Nodo Destino], H$3, tblEnlaces[Activo], 1), 0) -> 0 | I6: =IF(MatrizDeAdyacencia!I6=1, SUMIFS(tblEnlaces[ValorOperativo (peso)], tblEnlaces[Nodo Origen], $C6, tblEnlaces[Nodo Destino], I$3, tblEnlaces[Activo], 1), 0) -> 0 | J6: =IF(MatrizDeAdyacencia!J6=1, SUMIFS(tblEnlaces[ValorOperativo (peso)], tblEnlaces[Nodo Origen], $C6, tblEnlaces[Nodo Destino], J$3, tblEnlaces[Activo], 1), 0) -> 17 | K6: =IF(MatrizDeAdyacencia!K6=1, SUMIFS(tblEnlaces[ValorOperativo (peso)], tblEnlaces[Nodo Origen], $C6, tblEnlaces[Nodo Destino], K$3, tblEnlaces[Activo], 1), 0) -> 19 | ... V6: =IF(MatrizDeAdyacencia!V6=1, SUMIFS(tblEnlaces[ValorOperativo (peso)], tblEnlaces[Nodo Origen], $C6, tblEnlaces[Nodo Destino], V$3, tblEnlaces[Activo], 1), 0) -> 0 | Y6: Bajo-Medio | Z6: 2 | AA6: 4 | AB6: 2 | AC6: 2
B7: =VLOOKUP(tblMatrizPonderadaValorOperativo[[#This Row],[NodoOrigen \ NodoDestino]],tblNodos[#All],2,FALSE) -> Autofinanciación lícita / microfinanciación | C7: O4 | D7: =IF(MatrizDeAdyacencia!D7=1, SUMIFS(tblEnlaces[ValorOperativo (peso)], tblEnlaces[Nodo Origen], $C7, tblEnlaces[Nodo Destino], D$3, tblEnlaces[Activo], 1), 0) -> 0 | E7: =IF(MatrizDeAdyacencia!E7=1, SUMIFS(tblEnlaces[ValorOperativo (peso)], tblEnlaces[Nodo Origen], $C7, tblEnlaces[Nodo Destino], E$3, tblEnlaces[Activo], 1), 0) -> 0 | F7: =IF(MatrizDeAdyacencia!F7=1, SUMIFS(tblEnlaces[ValorOperativo (peso)], tblEnlaces[Nodo Origen], $C7, tblEnlaces[Nodo Destino], F$3, tblEnlaces[Activo], 1), 0) -> 0 | G7: =IF(MatrizDeAdyacencia!G7=1, SUMIFS(tblEnlaces[ValorOperativo (peso)], tblEnlaces[Nodo Origen], $C7, tblEnlaces[Nodo Destino], G$3, tblEnlaces[Activo], 1), 0) -> 0 | H7: =IF(MatrizDeAdyacencia!H7=1, SUMIFS(tblEnlaces[ValorOperativo (peso)], tblEnlaces[Nodo Origen], $C7, tblEnlaces[Nodo Destino], H$3, tblEnlaces[Activo], 1), 0) -> 0 | I7: =IF(MatrizDeAdyacencia!I7=1, SUMIFS(tblEnlaces[ValorOperativo (peso)], tblEnlaces[Nodo Origen], $C7, tblEnlaces[Nodo Destino], I$3, tblEnlaces[Activo], 1), 0) -> 0 | J7: =IF(MatrizDeAdyacencia!J7=1, SUMIFS(tblEnlaces[ValorOperativo (peso)], tblEnlaces[Nodo Origen], $C7, tblEnlaces[Nodo Destino], J$3, tblEnlaces[Activo], 1), 0) -> 0 | K7: =IF(MatrizDeAdyacencia!K7=1, SUMIFS(tblEnlaces[ValorOperativo (peso)], tblEnlaces[Nodo Origen], $C7, tblEnlaces[Nodo Destino], K$3, tblEnlaces[Activo], 1), 0) -> 0 | ... V7: =IF(MatrizDeAdyacencia!V7=1, SUMIFS(tblEnlaces[ValorOperativo (peso)], tblEnlaces[Nodo Origen], $C7, tblEnlaces[Nodo Destino], V$3, tblEnlaces[Activo], 1), 0) -> 0 | Y7: Medio | Z7: 3 | AA7: 3 | AB7: 3 | AC7: 3
B8: =VLOOKUP(tblMatrizPonderadaValorOperativo[[#This Row],[NodoOrigen \ NodoDestino]],tblNodos[#All],2,FALSE) -> Actividades económicas formales / negocios | C8: O5 | D8: =IF(MatrizDeAdyacencia!D8=1, SUMIFS(tblEnlaces[ValorOperativo (peso)], tblEnlaces[Nodo Origen], $C8, tblEnlaces[Nodo Destino], D$3, tblEnlaces[Activo], 1), 0) -> 0 | E8: =IF(MatrizDeAdyacencia!E8=1, SUMIFS(tblEnlaces[ValorOperativo (peso)], tblEnlaces[Nodo Origen], $C8, tblEnlaces[Nodo Destino], E$3, tblEnlaces[Activo], 1), 0) -> 0 | F8: =IF(MatrizDeAdyacencia!F8=1, SUMIFS(tblEnlaces[ValorOperativo (peso)], tblEnlaces[Nodo Origen], $C8, tblEnlaces[Nodo Destino], F$3, tblEnlaces[Activo], 1), 0) -> 0 | G8: =IF(MatrizDeAdyacencia!G8=1, SUMIFS(tblEnlaces[ValorOperativo (peso)], tblEnlaces[Nodo Origen], $C8, tblEnlaces[Nodo Destino], G$3, tblEnlaces[Activo], 1), 0) -> 0 | H8: =IF(MatrizDeAdyacencia!H8=1, SUMIFS(tblEnlaces[ValorOperativo (peso)], tblEnlaces[Nodo Origen], $C8, tblEnlaces[Nodo Destino], H$3, tblEnlaces[Activo], 1), 0) -> 0 | I8: =IF(MatrizDeAdyacencia!I8=1, SUMIFS(tblEnlaces[ValorOperativo (peso)], tblEnlaces[Nodo Origen], $C8, tblEnlaces[Nodo Destino], I$3, tblEnlaces[Activo], 1), 0) -> 0 | J8: =IF(MatrizDeAdyacencia!J8=1, SUMIFS(tblEnlaces[ValorOperativo (peso)], tblEnlaces[Nodo Origen], $C8, tblEnlaces[Nodo Destino], J$3, tblEnlaces[Activo], 1), 0) -> 16 | K8: =IF(MatrizDeAdyacencia!K8=1, SUMIFS(tblEnlaces[ValorOperativo (peso)], tblEnlaces[Nodo Origen], $C8, tblEnlaces[Nodo Destino], K$3, tblEnlaces[Activo], 1), 0) -> 0 | ... V8: =IF(MatrizDeAdyacencia!V8=1, SUMIFS(tblEnlaces[ValorOperativo (peso)], tblEnlaces[Nodo Origen], $C8, tblEnlaces[Nodo Destino], V$3, tblEnlaces[Activo], 1), 0) -> 0 | Y8: Medio-Alto | Z8: 4 | AA8: 2 | AB8: 4 | AC8: 4
B9: =VLOOKUP(tblMatrizPonderadaValorOperativo[[#This Row],[NodoOrigen \ NodoDestino]],tblNodos[#All],2,FALSE) -> Donaciones / crowdfunding / apoyo online | C9: O6 | D9: =IF(MatrizDeAdyacencia!D9=1, SUMIFS(tblEnlaces[ValorOperativo (peso)], tblEnlaces[Nodo Origen], $C9, tblEnlaces[Nodo Destino], D$3, tblEnlaces[Activo], 1), 0) -> 0 | E9: =IF(MatrizDeAdyacencia!E9=1, SUMIFS(tblEnlaces[ValorOperativo (peso)], tblEnlaces[Nodo Origen], $C9, tblEnlaces[Nodo Destino], E$3, tblEnlaces[Activo], 1), 0) -> 0 | F9: =IF(MatrizDeAdyacencia!F9=1, SUMIFS(tblEnlaces[ValorOperativo (peso)], tblEnlaces[Nodo Origen], $C9, tblEnlaces[Nodo Destino], F$3, tblEnlaces[Activo], 1), 0) -> 0 | G9: =IF(MatrizDeAdyacencia!G9=1, SUMIFS(tblEnlaces[ValorOperativo (peso)], tblEnlaces[Nodo Origen], $C9, tblEnlaces[Nodo Destino], G$3, tblEnlaces[Activo], 1), 0) -> 0 | H9: =IF(MatrizDeAdyacencia!H9=1, SUMIFS(tblEnlaces[ValorOperativo (peso)], tblEnlaces[Nodo Origen], $C9, tblEnlaces[Nodo Destino], H$3, tblEnlaces[Activo], 1), 0) -> 0 | I9: =IF(MatrizDeAdyacencia!I9=1, SUMIFS(tblEnlaces[ValorOperativo (peso)], tblEnlaces[Nodo Origen], $C9, tblEnlaces[Nodo Destino], I$3, tblEnlaces[Activo], 1), 0) -> 0 | J9: =IF(MatrizDeAdyacencia!J9=1, SUMIFS(tblEnlaces[ValorOperativo (peso)], tblEnlaces[Nodo Origen], $C9, tblEnlaces[Nodo Destino], J$3, tblEnlaces[Activo], 1), 0) -> 0 | K9: =IF(MatrizDeAdyacencia!K9=1, SUMIFS(tblEnlaces[ValorOperativo (peso)], tblEnlaces[Nodo Origen], $C9, tblEnlaces[Nodo Destino], K$3, tblEnlaces[Activo], 1), 0) -> 0 | ... V9: =IF(MatrizDeAdyacencia!V9=1, SUMIFS(tblEnlaces[ValorOperativo (peso)], tblEnlaces[Nodo Origen], $C9, tblEnlaces[Nodo Destino], V$3, tblEnlaces[Activo], 1), 0) -> 0 | Y9: Alto | Z9: 5 | AA9: 1 | AB9: 5 | AC9: 5
B10: =VLOOKUP(tblMatrizPonderadaValorOperativo[[#This Row],[NodoOrigen \ NodoDestino]],tblNodos[#All],2,FALSE) -> Efectivo | C10: I1 | D10: =IF(MatrizDeAdyacencia!D10=1, SUMIFS(tblEnlaces[ValorOperativo (peso)], tblEnlaces[Nodo Origen], $C10, tblEnlaces[Nodo Destino], D$3, tblEnlaces[Activo], 1), 0) -> 0 | E10: =IF(MatrizDeAdyacencia!E10=1, SUMIFS(tblEnlaces[ValorOperativo (peso)], tblEnlaces[Nodo Origen], $C10, tblEnlaces[Nodo Destino], E$3, tblEnlaces[Activo], 1), 0) -> 0 | F10: =IF(MatrizDeAdyacencia!F10=1, SUMIFS(tblEnlaces[ValorOperativo (peso)], tblEnlaces[Nodo Origen], $C10, tblEnlaces[Nodo Destino], F$3, tblEnlaces[Activo], 1), 0) -> 0 | G10: =IF(MatrizDeAdyacencia!G10=1, SUMIFS(tblEnlaces[ValorOperativo (peso)], tblEnlaces[Nodo Origen], $C10, tblEnlaces[Nodo Destino], G$3, tblEnlaces[Activo], 1), 0) -> 0 | H10: =IF(MatrizDeAdyacencia!H10=1, SUMIFS(tblEnlaces[ValorOperativo (peso)], tblEnlaces[Nodo Origen], $C10, tblEnlaces[Nodo Destino], H$3, tblEnlaces[Activo], 1), 0) -> 0 | I10: =IF(MatrizDeAdyacencia!I10=1, SUMIFS(tblEnlaces[ValorOperativo (peso)], tblEnlaces[Nodo Origen], $C10, tblEnlaces[Nodo Destino], I$3, tblEnlaces[Activo], 1), 0) -> 0 | J10: =IF(MatrizDeAdyacencia!J10=1, SUMIFS(tblEnlaces[ValorOperativo (peso)], tblEnlaces[Nodo Origen], $C10, tblEnlaces[Nodo Destino], J$3, tblEnlaces[Activo], 1), 0) -> 0 | K10: =IF(MatrizDeAdyacencia!K10=1, SUMIFS(tblEnlaces[ValorOperativo (peso)], tblEnlaces[Nodo Origen], $C10, tblEnlaces[Nodo Destino], K$3, tblEnlaces[Activo], 1), 0) -> 18 | ... V10: =IF(MatrizDeAdyacencia!V10=1, SUMIFS(tblEnlaces[ValorOperativo (peso)], tblEnlaces[Nodo Origen], $C10, tblEnlaces[Nodo Destino], V$3, tblEnlaces[Activo], 1), 0) -> 15
B11: =VLOOKUP(tblMatrizPonderadaValorOperativo[[#This Row],[NodoOrigen \ NodoDestino]],tblNodos[#All],2,FALSE) -> Hawala / HOSSP | C11: I2 | D11: =IF(MatrizDeAdyacencia!D11=1, SUMIFS(tblEnlaces[ValorOperativo (peso)], tblEnlaces[Nodo Origen], $C11, tblEnlaces[Nodo Destino], D$3, tblEnlaces[Activo], 1), 0) -> 0 | E11: =IF(MatrizDeAdyacencia!E11=1, SUMIFS(tblEnlaces[ValorOperativo (peso)], tblEnlaces[Nodo Origen], $C11, tblEnlaces[Nodo Destino], E$3, tblEnlaces[Activo], 1), 0) -> 0 | F11: =IF(MatrizDeAdyacencia!F11=1, SUMIFS(tblEnlaces[ValorOperativo (peso)], tblEnlaces[Nodo Origen], $C11, tblEnlaces[Nodo Destino], F$3, tblEnlaces[Activo], 1), 0) -> 0 | G11: =IF(MatrizDeAdyacencia!G11=1, SUMIFS(tblEnlaces[ValorOperativo (peso)], tblEnlaces[Nodo Origen], $C11, tblEnlaces[Nodo Destino], G$3, tblEnlaces[Activo], 1), 0) -> 0 | H11: =IF(MatrizDeAdyacencia!H11=1, SUMIFS(tblEnlaces[ValorOperativo (peso)], tblEnlaces[Nodo Origen], $C11, tblEnlaces[Nodo Destino], H$3, tblEnlaces[Activo], 1), 0) -> 0 | I11: =IF(MatrizDeAdyacencia!I11=1, SUMIFS(tblEnlaces[ValorOperativo (peso)], tblEnlaces[Nodo Origen], $C11, tblEnlaces[Nodo Destino], I$3, tblEnlaces[Activo], 1), 0) -> 0 | J11: =IF(MatrizDeAdyacencia!J11=1, SUMIFS(tblEnlaces[ValorOperativo (peso)], tblEnlaces[Nodo Origen], $C11, tblEnlaces[Nodo Destino], J$3, tblEnlaces[Activo], 1), 0) -> 0 | K11: =IF(MatrizDeAdyacencia!K11=1, SUMIFS(tblEnlaces[ValorOperativo (peso)], tblEnlaces[Nodo Origen], $C11, tblEnlaces[Nodo Destino], K$3, tblEnlaces[Activo], 1), 0) -> 0 | ... V11: =IF(MatrizDeAdyacencia!V11=1, SUMIFS(tblEnlaces[ValorOperativo (peso)], tblEnlaces[Nodo Origen], $C11, tblEnlaces[Nodo Destino], V$3, tblEnlaces[Activo], 1), 0) -> 17
B12: =VLOOKUP(tblMatrizPonderadaValorOperativo[[#This Row],[NodoOrigen \ NodoDestino]],tblNodos[#All],2,FALSE) -> MVTS / remesas | C12: I3 | D12: =IF(MatrizDeAdyacencia!D12=1, SUMIFS(tblEnlaces[ValorOperativo (peso)], tblEnlaces[Nodo Origen], $C12, tblEnlaces[Nodo Destino], D$3, tblEnlaces[Activo], 1), 0) -> 0 | E12: =IF(MatrizDeAdyacencia!E12=1, SUMIFS(tblEnlaces[ValorOperativo (peso)], tblEnlaces[Nodo Origen], $C12, tblEnlaces[Nodo Destino], E$3, tblEnlaces[Activo], 1), 0) -> 0 | F12: =IF(MatrizDeAdyacencia!F12=1, SUMIFS(tblEnlaces[ValorOperativo (peso)], tblEnlaces[Nodo Origen], $C12, tblEnlaces[Nodo Destino], F$3, tblEnlaces[Activo], 1), 0) -> 0 | G12: =IF(MatrizDeAdyacencia!G12=1, SUMIFS(tblEnlaces[ValorOperativo (peso)], tblEnlaces[Nodo Origen], $C12, tblEnlaces[Nodo Destino], G$3, tblEnlaces[Activo], 1), 0) -> 0 | H12: =IF(MatrizDeAdyacencia!H12=1, SUMIFS(tblEnlaces[ValorOperativo (peso)], tblEnlaces[Nodo Origen], $C12, tblEnlaces[Nodo Destino], H$3, tblEnlaces[Activo], 1), 0) -> 0 | I12: =IF(MatrizDeAdyacencia!I12=1, SUMIFS(tblEnlaces[ValorOperativo (peso)], tblEnlaces[Nodo Origen], $C12, tblEnlaces[Nodo Destino], I$3, tblEnlaces[Activo], 1), 0) -> 0 | J12: =IF(MatrizDeAdyacencia!J12=1, SUMIFS(tblEnlaces[ValorOperativo (peso)], tblEnlaces[Nodo Origen], $C12, tblEnlaces[Nodo Destino], J$3, tblEnlaces[Activo], 1), 0) -> 0 | K12: =IF(MatrizDeAdyacencia!K12=1, SUMIFS(tblEnlaces[ValorOperativo (peso)], tblEnlaces[Nodo Origen], $C12, tblEnlaces[Nodo Destino], K$3, tblEnlaces[Activo], 1), 0) -> 0 | ... V12: =IF(MatrizDeAdyacencia!V12=1, SUMIFS(tblEnlaces[ValorOperativo (peso)], tblEnlaces[Nodo Origen], $C12, tblEnlaces[Nodo Destino], V$3, tblEnlaces[Activo], 1), 0) -> 14 | Y12: Rango del Enlace | Z12: Eficiencia | AA12: Exposición | AB12: Capacidad | AC12: Resiliencia | AD12: Total
B13: =VLOOKUP(tblMatrizPonderadaValorOperativo[[#This Row],[NodoOrigen \ NodoDestino]],tblNodos[#All],2,FALSE) -> Dinero móvil | C13: I4 | D13: =IF(MatrizDeAdyacencia!D13=1, SUMIFS(tblEnlaces[ValorOperativo (peso)], tblEnlaces[Nodo Origen], $C13, tblEnlaces[Nodo Destino], D$3, tblEnlaces[Activo], 1), 0) -> 0 | E13: =IF(MatrizDeAdyacencia!E13=1, SUMIFS(tblEnlaces[ValorOperativo (peso)], tblEnlaces[Nodo Origen], $C13, tblEnlaces[Nodo Destino], E$3, tblEnlaces[Activo], 1), 0) -> 0 | F13: =IF(MatrizDeAdyacencia!F13=1, SUMIFS(tblEnlaces[ValorOperativo (peso)], tblEnlaces[Nodo Origen], $C13, tblEnlaces[Nodo Destino], F$3, tblEnlaces[Activo], 1), 0) -> 0 | G13: =IF(MatrizDeAdyacencia!G13=1, SUMIFS(tblEnlaces[ValorOperativo (peso)], tblEnlaces[Nodo Origen], $C13, tblEnlaces[Nodo Destino], G$3, tblEnlaces[Activo], 1), 0) -> 0 | H13: =IF(MatrizDeAdyacencia!H13=1, SUMIFS(tblEnlaces[ValorOperativo (peso)], tblEnlaces[Nodo Origen], $C13, tblEnlaces[Nodo Destino], H$3, tblEnlaces[Activo], 1), 0) -> 0 | I13: =IF(MatrizDeAdyacencia!I13=1, SUMIFS(tblEnlaces[ValorOperativo (peso)], tblEnlaces[Nodo Origen], $C13, tblEnlaces[Nodo Destino], I$3, tblEnlaces[Activo], 1), 0) -> 0 | J13: =IF(MatrizDeAdyacencia!J13=1, SUMIFS(tblEnlaces[ValorOperativo (peso)], tblEnlaces[Nodo Origen], $C13, tblEnlaces[Nodo Destino], J$3, tblEnlaces[Activo], 1), 0) -> 0 | K13: =IF(MatrizDeAdyacencia!K13=1, SUMIFS(tblEnlaces[ValorOperativo (peso)], tblEnlaces[Nodo Origen], $C13, tblEnlaces[Nodo Destino], K$3, tblEnlaces[Activo], 1), 0) -> 0 | ... V13: =IF(MatrizDeAdyacencia!V13=1, SUMIFS(tblEnlaces[ValorOperativo (peso)], tblEnlaces[Nodo Origen], $C13, tblEnlaces[Nodo Destino], V$3, tblEnlaces[Activo], 1), 0) -> 0 | Y13: Mínimo posible | Z13: 1 | AA13: 1 | AB13: 1 | AC13: 1 | AD13: 4
B14: =VLOOKUP(tblMatrizPonderadaValorOperativo[[#This Row],[NodoOrigen \ NodoDestino]],tblNodos[#All],2,FALSE) -> Pagos online | C14: I5 | D14: =IF(MatrizDeAdyacencia!D14=1, SUMIFS(tblEnlaces[ValorOperativo (peso)], tblEnlaces[Nodo Origen], $C14, tblEnlaces[Nodo Destino], D$3, tblEnlaces[Activo], 1), 0) -> 0 | E14: =IF(MatrizDeAdyacencia!E14=1, SUMIFS(tblEnlaces[ValorOperativo (peso)], tblEnlaces[Nodo Origen], $C14, tblEnlaces[Nodo Destino], E$3, tblEnlaces[Activo], 1), 0) -> 0 | F14: =IF(MatrizDeAdyacencia!F14=1, SUMIFS(tblEnlaces[ValorOperativo (peso)], tblEnlaces[Nodo Origen], $C14, tblEnlaces[Nodo Destino], F$3, tblEnlaces[Activo], 1), 0) -> 0 | G14: =IF(MatrizDeAdyacencia!G14=1, SUMIFS(tblEnlaces[ValorOperativo (peso)], tblEnlaces[Nodo Origen], $C14, tblEnlaces[Nodo Destino], G$3, tblEnlaces[Activo], 1), 0) -> 0 | H14: =IF(MatrizDeAdyacencia!H14=1, SUMIFS(tblEnlaces[ValorOperativo (peso)], tblEnlaces[Nodo Origen], $C14, tblEnlaces[Nodo Destino], H$3, tblEnlaces[Activo], 1), 0) -> 0 | I14: =IF(MatrizDeAdyacencia!I14=1, SUMIFS(tblEnlaces[ValorOperativo (peso)], tblEnlaces[Nodo Origen], $C14, tblEnlaces[Nodo Destino], I$3, tblEnlaces[Activo], 1), 0) -> 0 | J14: =IF(MatrizDeAdyacencia!J14=1, SUMIFS(tblEnlaces[ValorOperativo (peso)], tblEnlaces[Nodo Origen], $C14, tblEnlaces[Nodo Destino], J$3, tblEnlaces[Activo], 1), 0) -> 0 | K14: =IF(MatrizDeAdyacencia!K14=1, SUMIFS(tblEnlaces[ValorOperativo (peso)], tblEnlaces[Nodo Origen], $C14, tblEnlaces[Nodo Destino], K$3, tblEnlaces[Activo], 1), 0) -> 0 | ... V14: =IF(MatrizDeAdyacencia!V14=1, SUMIFS(tblEnlaces[ValorOperativo (peso)], tblEnlaces[Nodo Origen], $C14, tblEnlaces[Nodo Destino], V$3, tblEnlaces[Activo], 1), 0) -> 0 | Y14: Máximo posible | Z14: 5 | AA14: 5 | AB14: 5 | AC14: 5 | AD14: 20
B15: =VLOOKUP(tblMatrizPonderadaValorOperativo[[#This Row],[NodoOrigen \ NodoDestino]],tblNodos[#All],2,FALSE) -> Servicios bancarios | C15: I6 | D15: =IF(MatrizDeAdyacencia!D15=1, SUMIFS(tblEnlaces[ValorOperativo (peso)], tblEnlaces[Nodo Origen], $C15, tblEnlaces[Nodo Destino], D$3, tblEnlaces[Activo], 1), 0) -> 0 | E15: =IF(MatrizDeAdyacencia!E15=1, SUMIFS(tblEnlaces[ValorOperativo (peso)], tblEnlaces[Nodo Origen], $C15, tblEnlaces[Nodo Destino], E$3, tblEnlaces[Activo], 1), 0) -> 0 | F15: =IF(MatrizDeAdyacencia!F15=1, SUMIFS(tblEnlaces[ValorOperativo (peso)], tblEnlaces[Nodo Origen], $C15, tblEnlaces[Nodo Destino], F$3, tblEnlaces[Activo], 1), 0) -> 0 | G15: =IF(MatrizDeAdyacencia!G15=1, SUMIFS(tblEnlaces[ValorOperativo (peso)], tblEnlaces[Nodo Origen], $C15, tblEnlaces[Nodo Destino], G$3, tblEnlaces[Activo], 1), 0) -> 0 | H15: =IF(MatrizDeAdyacencia!H15=1, SUMIFS(tblEnlaces[ValorOperativo (peso)], tblEnlaces[Nodo Origen], $C15, tblEnlaces[Nodo Destino], H$3, tblEnlaces[Activo], 1), 0) -> 0 | I15: =IF(MatrizDeAdyacencia!I15=1, SUMIFS(tblEnlaces[ValorOperativo (peso)], tblEnlaces[Nodo Origen], $C15, tblEnlaces[Nodo Destino], I$3, tblEnlaces[Activo], 1), 0) -> 0 | J15: =IF(MatrizDeAdyacencia!J15=1, SUMIFS(tblEnlaces[ValorOperativo (peso)], tblEnlaces[Nodo Origen], $C15, tblEnlaces[Nodo Destino], J$3, tblEnlaces[Activo], 1), 0) -> 0 | K15: =IF(MatrizDeAdyacencia!K15=1, SUMIFS(tblEnlaces[ValorOperativo (peso)], tblEnlaces[Nodo Origen], $C15, tblEnlaces[Nodo Destino], K$3, tblEnlaces[Activo], 1), 0) -> 0 | ... V15: =IF(MatrizDeAdyacencia!V15=1, SUMIFS(tblEnlaces[ValorOperativo (peso)], tblEnlaces[Nodo Origen], $C15, tblEnlaces[Nodo Destino], V$3, tblEnlaces[Activo], 1), 0) -> 0
B16: =VLOOKUP(tblMatrizPonderadaValorOperativo[[#This Row],[NodoOrigen \ NodoDestino]],tblNodos[#All],2,FALSE) -> Tarjetas prepago / e-wallets | C16: I7 | D16: =IF(MatrizDeAdyacencia!D16=1, SUMIFS(tblEnlaces[ValorOperativo (peso)], tblEnlaces[Nodo Origen], $C16, tblEnlaces[Nodo Destino], D$3, tblEnlaces[Activo], 1), 0) -> 0 | E16: =IF(MatrizDeAdyacencia!E16=1, SUMIFS(tblEnlaces[ValorOperativo (peso)], tblEnlaces[Nodo Origen], $C16, tblEnlaces[Nodo Destino], E$3, tblEnlaces[Activo], 1), 0) -> 0 | F16: =IF(MatrizDeAdyacencia!F16=1, SUMIFS(tblEnlaces[ValorOperativo (peso)], tblEnlaces[Nodo Origen], $C16, tblEnlaces[Nodo Destino], F$3, tblEnlaces[Activo], 1), 0) -> 0 | G16: =IF(MatrizDeAdyacencia!G16=1, SUMIFS(tblEnlaces[ValorOperativo (peso)], tblEnlaces[Nodo Origen], $C16, tblEnlaces[Nodo Destino], G$3, tblEnlaces[Activo], 1), 0) -> 0 | H16: =IF(MatrizDeAdyacencia!H16=1, SUMIFS(tblEnlaces[ValorOperativo (peso)], tblEnlaces[Nodo Origen], $C16, tblEnlaces[Nodo Destino], H$3, tblEnlaces[Activo], 1), 0) -> 0 | I16: =IF(MatrizDeAdyacencia!I16=1, SUMIFS(tblEnlaces[ValorOperativo (peso)], tblEnlaces[Nodo Origen], $C16, tblEnlaces[Nodo Destino], I$3, tblEnlaces[Activo], 1), 0) -> 0 | J16: =IF(MatrizDeAdyacencia!J16=1, SUMIFS(tblEnlaces[ValorOperativo (peso)], tblEnlaces[Nodo Origen], $C16, tblEnlaces[Nodo Destino], J$3, tblEnlaces[Activo], 1), 0) -> 0 | K16: =IF(MatrizDeAdyacencia!K16=1, SUMIFS(tblEnlaces[ValorOperativo (peso)], tblEnlaces[Nodo Origen], $C16, tblEnlaces[Nodo Destino], K$3, tblEnlaces[Activo], 1), 0) -> 0 | ... V16: =IF(MatrizDeAdyacencia!V16=1, SUMIFS(tblEnlaces[ValorOperativo (peso)], tblEnlaces[Nodo Origen], $C16, tblEnlaces[Nodo Destino], V$3, tblEnlaces[Activo], 1), 0) -> 0
B17: =VLOOKUP(tblMatrizPonderadaValorOperativo[[#This Row],[NodoOrigen \ NodoDestino]],tblNodos[#All],2,FALSE) -> Plataformas digitales | C17: I8 | D17: =IF(MatrizDeAdyacencia!D17=1, SUMIFS(tblEnlaces[ValorOperativo (peso)], tblEnlaces[Nodo Origen], $C17, tblEnlaces[Nodo Destino], D$3, tblEnlaces[Activo], 1), 0) -> 0 | E17: =IF(MatrizDeAdyacencia!E17=1, SUMIFS(tblEnlaces[ValorOperativo (peso)], tblEnlaces[Nodo Origen], $C17, tblEnlaces[Nodo Destino], E$3, tblEnlaces[Activo], 1), 0) -> 0 | F17: =IF(MatrizDeAdyacencia!F17=1, SUMIFS(tblEnlaces[ValorOperativo (peso)], tblEnlaces[Nodo Origen], $C17, tblEnlaces[Nodo Destino], F$3, tblEnlaces[Activo], 1), 0) -> 0 | G17: =IF(MatrizDeAdyacencia!G17=1, SUMIFS(tblEnlaces[ValorOperativo (peso)], tblEnlaces[Nodo Origen], $C17, tblEnlaces[Nodo Destino], G$3, tblEnlaces[Activo], 1), 0) -> 0 | H17: =IF(MatrizDeAdyacencia!H17=1, SUMIFS(tblEnlaces[ValorOperativo (peso)], tblEnlaces[Nodo Origen], $C17, tblEnlaces[Nodo Destino], H$3, tblEnlaces[Activo], 1), 0) -> 0 | I17: =IF(MatrizDeAdyacencia!I17=1, SUMIFS(tblEnlaces[ValorOperativo (peso)], tblEnlaces[Nodo Origen], $C17, tblEnlaces[Nodo Destino], I$3, tblEnlaces[Activo], 1), 0) -> 0 | J17: =IF(MatrizDeAdyacencia!J17=1, SUMIFS(tblEnlaces[ValorOperativo (peso)], tblEnlaces[Nodo Origen], $C17, tblEnlaces[Nodo Destino], J$3, tblEnlaces[Activo], 1), 0) -> 0 | K17: =IF(MatrizDeAdyacencia!K17=1, SUMIFS(tblEnlaces[ValorOperativo (peso)], tblEnlaces[Nodo Origen], $C17, tblEnlaces[Nodo Destino], K$3, tblEnlaces[Activo], 1), 0) -> 0 | ... V17: =IF(MatrizDeAdyacencia!V17=1, SUMIFS(tblEnlaces[ValorOperativo (peso)], tblEnlaces[Nodo Origen], $C17, tblEnlaces[Nodo Destino], V$3, tblEnlaces[Activo], 1), 0) -> 0
B18: =VLOOKUP(tblMatrizPonderadaValorOperativo[[#This Row],[NodoOrigen \ NodoDestino]],tblNodos[#All],2,FALSE) -> Activos virtuales | C18: I9 | D18: =IF(MatrizDeAdyacencia!D18=1, SUMIFS(tblEnlaces[ValorOperativo (peso)], tblEnlaces[Nodo Origen], $C18, tblEnlaces[Nodo Destino], D$3, tblEnlaces[Activo], 1), 0) -> 0 | E18: =IF(MatrizDeAdyacencia!E18=1, SUMIFS(tblEnlaces[ValorOperativo (peso)], tblEnlaces[Nodo Origen], $C18, tblEnlaces[Nodo Destino], E$3, tblEnlaces[Activo], 1), 0) -> 0 | F18: =IF(MatrizDeAdyacencia!F18=1, SUMIFS(tblEnlaces[ValorOperativo (peso)], tblEnlaces[Nodo Origen], $C18, tblEnlaces[Nodo Destino], F$3, tblEnlaces[Activo], 1), 0) -> 0 | G18: =IF(MatrizDeAdyacencia!G18=1, SUMIFS(tblEnlaces[ValorOperativo (peso)], tblEnlaces[Nodo Origen], $C18, tblEnlaces[Nodo Destino], G$3, tblEnlaces[Activo], 1), 0) -> 0 | H18: =IF(MatrizDeAdyacencia!H18=1, SUMIFS(tblEnlaces[ValorOperativo (peso)], tblEnlaces[Nodo Origen], $C18, tblEnlaces[Nodo Destino], H$3, tblEnlaces[Activo], 1), 0) -> 0 | I18: =IF(MatrizDeAdyacencia!I18=1, SUMIFS(tblEnlaces[ValorOperativo (peso)], tblEnlaces[Nodo Origen], $C18, tblEnlaces[Nodo Destino], I$3, tblEnlaces[Activo], 1), 0) -> 0 | J18: =IF(MatrizDeAdyacencia!J18=1, SUMIFS(tblEnlaces[ValorOperativo (peso)], tblEnlaces[Nodo Origen], $C18, tblEnlaces[Nodo Destino], J$3, tblEnlaces[Activo], 1), 0) -> 0 | K18: =IF(MatrizDeAdyacencia!K18=1, SUMIFS(tblEnlaces[ValorOperativo (peso)], tblEnlaces[Nodo Origen], $C18, tblEnlaces[Nodo Destino], K$3, tblEnlaces[Activo], 1), 0) -> 0 | ... V18: =IF(MatrizDeAdyacencia!V18=1, SUMIFS(tblEnlaces[ValorOperativo (peso)], tblEnlaces[Nodo Origen], $C18, tblEnlaces[Nodo Destino], V$3, tblEnlaces[Activo], 1), 0) -> 0
B19: =VLOOKUP(tblMatrizPonderadaValorOperativo[[#This Row],[NodoOrigen \ NodoDestino]],tblNodos[#All],2,FALSE) -> Tesorería central | C19: G1 | D19: =IF(MatrizDeAdyacencia!D19=1, SUMIFS(tblEnlaces[ValorOperativo (peso)], tblEnlaces[Nodo Origen], $C19, tblEnlaces[Nodo Destino], D$3, tblEnlaces[Activo], 1), 0) -> 0 | E19: =IF(MatrizDeAdyacencia!E19=1, SUMIFS(tblEnlaces[ValorOperativo (peso)], tblEnlaces[Nodo Origen], $C19, tblEnlaces[Nodo Destino], E$3, tblEnlaces[Activo], 1), 0) -> 0 | F19: =IF(MatrizDeAdyacencia!F19=1, SUMIFS(tblEnlaces[ValorOperativo (peso)], tblEnlaces[Nodo Origen], $C19, tblEnlaces[Nodo Destino], F$3, tblEnlaces[Activo], 1), 0) -> 0 | G19: =IF(MatrizDeAdyacencia!G19=1, SUMIFS(tblEnlaces[ValorOperativo (peso)], tblEnlaces[Nodo Origen], $C19, tblEnlaces[Nodo Destino], G$3, tblEnlaces[Activo], 1), 0) -> 0 | H19: =IF(MatrizDeAdyacencia!H19=1, SUMIFS(tblEnlaces[ValorOperativo (peso)], tblEnlaces[Nodo Origen], $C19, tblEnlaces[Nodo Destino], H$3, tblEnlaces[Activo], 1), 0) -> 0 | I19: =IF(MatrizDeAdyacencia!I19=1, SUMIFS(tblEnlaces[ValorOperativo (peso)], tblEnlaces[Nodo Origen], $C19, tblEnlaces[Nodo Destino], I$3, tblEnlaces[Activo], 1), 0) -> 0 | J19: =IF(MatrizDeAdyacencia!J19=1, SUMIFS(tblEnlaces[ValorOperativo (peso)], tblEnlaces[Nodo Origen], $C19, tblEnlaces[Nodo Destino], J$3, tblEnlaces[Activo], 1), 0) -> 17 | K19: =IF(MatrizDeAdyacencia!K19=1, SUMIFS(tblEnlaces[ValorOperativo (peso)], tblEnlaces[Nodo Origen], $C19, tblEnlaces[Nodo Destino], K$3, tblEnlaces[Activo], 1), 0) -> 0 | ... V19: =IF(MatrizDeAdyacencia!V19=1, SUMIFS(tblEnlaces[ValorOperativo (peso)], tblEnlaces[Nodo Origen], $C19, tblEnlaces[Nodo Destino], V$3, tblEnlaces[Activo], 1), 0) -> 16
B20: =VLOOKUP(tblMatrizPonderadaValorOperativo[[#This Row],[NodoOrigen \ NodoDestino]],tblNodos[#All],2,FALSE) -> Centro financiero regional / célula | C20: G2 | D20: =IF(MatrizDeAdyacencia!D20=1, SUMIFS(tblEnlaces[ValorOperativo (peso)], tblEnlaces[Nodo Origen], $C20, tblEnlaces[Nodo Destino], D$3, tblEnlaces[Activo], 1), 0) -> 0 | E20: =IF(MatrizDeAdyacencia!E20=1, SUMIFS(tblEnlaces[ValorOperativo (peso)], tblEnlaces[Nodo Origen], $C20, tblEnlaces[Nodo Destino], E$3, tblEnlaces[Activo], 1), 0) -> 0 | F20: =IF(MatrizDeAdyacencia!F20=1, SUMIFS(tblEnlaces[ValorOperativo (peso)], tblEnlaces[Nodo Origen], $C20, tblEnlaces[Nodo Destino], F$3, tblEnlaces[Activo], 1), 0) -> 0 | G20: =IF(MatrizDeAdyacencia!G20=1, SUMIFS(tblEnlaces[ValorOperativo (peso)], tblEnlaces[Nodo Origen], $C20, tblEnlaces[Nodo Destino], G$3, tblEnlaces[Activo], 1), 0) -> 0 | H20: =IF(MatrizDeAdyacencia!H20=1, SUMIFS(tblEnlaces[ValorOperativo (peso)], tblEnlaces[Nodo Origen], $C20, tblEnlaces[Nodo Destino], H$3, tblEnlaces[Activo], 1), 0) -> 0 | I20: =IF(MatrizDeAdyacencia!I20=1, SUMIFS(tblEnlaces[ValorOperativo (peso)], tblEnlaces[Nodo Origen], $C20, tblEnlaces[Nodo Destino], I$3, tblEnlaces[Activo], 1), 0) -> 0 | J20: =IF(MatrizDeAdyacencia!J20=1, SUMIFS(tblEnlaces[ValorOperativo (peso)], tblEnlaces[Nodo Origen], $C20, tblEnlaces[Nodo Destino], J$3, tblEnlaces[Activo], 1), 0) -> 16 | K20: =IF(MatrizDeAdyacencia!K20=1, SUMIFS(tblEnlaces[ValorOperativo (peso)], tblEnlaces[Nodo Origen], $C20, tblEnlaces[Nodo Destino], K$3, tblEnlaces[Activo], 1), 0) -> 18 | ... V20: =IF(MatrizDeAdyacencia!V20=1, SUMIFS(tblEnlaces[ValorOperativo (peso)], tblEnlaces[Nodo Origen], $C20, tblEnlaces[Nodo Destino], V$3, tblEnlaces[Activo], 1), 0) -> 14
B21: =VLOOKUP(tblMatrizPonderadaValorOperativo[[#This Row],[NodoOrigen \ NodoDestino]],tblNodos[#All],2,FALSE) -> Facilitador externo / entidad instrumental | C21: G3 | D21: =IF(MatrizDeAdyacencia!D21=1, SUMIFS(tblEnlaces[ValorOperativo (peso)], tblEnlaces[Nodo Origen], $C21, tblEnlaces[Nodo Destino], D$3, tblEnlaces[Activo], 1), 0) -> 0 | E21: =IF(MatrizDeAdyacencia!E21=1, SUMIFS(tblEnlaces[ValorOperativo (peso)], tblEnlaces[Nodo Origen], $C21, tblEnlaces[Nodo Destino], E$3, tblEnlaces[Activo], 1), 0) -> 0 | F21: =IF(MatrizDeAdyacencia!F21=1, SUMIFS(tblEnlaces[ValorOperativo (peso)], tblEnlaces[Nodo Origen], $C21, tblEnlaces[Nodo Destino], F$3, tblEnlaces[Activo], 1), 0) -> 0 | G21: =IF(MatrizDeAdyacencia!G21=1, SUMIFS(tblEnlaces[ValorOperativo (peso)], tblEnlaces[Nodo Origen], $C21, tblEnlaces[Nodo Destino], G$3, tblEnlaces[Activo], 1), 0) -> 0 | H21: =IF(MatrizDeAdyacencia!H21=1, SUMIFS(tblEnlaces[ValorOperativo (peso)], tblEnlaces[Nodo Origen], $C21, tblEnlaces[Nodo Destino], H$3, tblEnlaces[Activo], 1), 0) -> 0 | I21: =IF(MatrizDeAdyacencia!I21=1, SUMIFS(tblEnlaces[ValorOperativo (peso)], tblEnlaces[Nodo Origen], $C21, tblEnlaces[Nodo Destino], I$3, tblEnlaces[Activo], 1), 0) -> 0 | J21: =IF(MatrizDeAdyacencia!J21=1, SUMIFS(tblEnlaces[ValorOperativo (peso)], tblEnlaces[Nodo Origen], $C21, tblEnlaces[Nodo Destino], J$3, tblEnlaces[Activo], 1), 0) -> 0 | K21: =IF(MatrizDeAdyacencia!K21=1, SUMIFS(tblEnlaces[ValorOperativo (peso)], tblEnlaces[Nodo Origen], $C21, tblEnlaces[Nodo Destino], K$3, tblEnlaces[Activo], 1), 0) -> 0 | ... V21: =IF(MatrizDeAdyacencia!V21=1, SUMIFS(tblEnlaces[ValorOperativo (peso)], tblEnlaces[Nodo Origen], $C21, tblEnlaces[Nodo Destino], V$3, tblEnlaces[Activo], 1), 0) -> 14
B22: =VLOOKUP(tblMatrizPonderadaValorOperativo[[#This Row],[NodoOrigen \ NodoDestino]],tblNodos[#All],2,FALSE) -> Destino operativo | C22: D | D22: =IF(MatrizDeAdyacencia!D22=1, SUMIFS(tblEnlaces[ValorOperativo (peso)], tblEnlaces[Nodo Origen], $C22, tblEnlaces[Nodo Destino], D$3, tblEnlaces[Activo], 1), 0) -> 0 | E22: =IF(MatrizDeAdyacencia!E22=1, SUMIFS(tblEnlaces[ValorOperativo (peso)], tblEnlaces[Nodo Origen], $C22, tblEnlaces[Nodo Destino], E$3, tblEnlaces[Activo], 1), 0) -> 0 | F22: =IF(MatrizDeAdyacencia!F22=1, SUMIFS(tblEnlaces[ValorOperativo (peso)], tblEnlaces[Nodo Origen], $C22, tblEnlaces[Nodo Destino], F$3, tblEnlaces[Activo], 1), 0) -> 0 | G22: =IF(MatrizDeAdyacencia!G22=1, SUMIFS(tblEnlaces[ValorOperativo (peso)], tblEnlaces[Nodo Origen], $C22, tblEnlaces[Nodo Destino], G$3, tblEnlaces[Activo], 1), 0) -> 0 | H22: =IF(MatrizDeAdyacencia!H22=1, SUMIFS(tblEnlaces[ValorOperativo (peso)], tblEnlaces[Nodo Origen], $C22, tblEnlaces[Nodo Destino], H$3, tblEnlaces[Activo], 1), 0) -> 0 | I22: =IF(MatrizDeAdyacencia!I22=1, SUMIFS(tblEnlaces[ValorOperativo (peso)], tblEnlaces[Nodo Origen], $C22, tblEnlaces[Nodo Destino], I$3, tblEnlaces[Activo], 1), 0) -> 0 | J22: =IF(MatrizDeAdyacencia!J22=1, SUMIFS(tblEnlaces[ValorOperativo (peso)], tblEnlaces[Nodo Origen], $C22, tblEnlaces[Nodo Destino], J$3, tblEnlaces[Activo], 1), 0) -> 0 | K22: =IF(MatrizDeAdyacencia!K22=1, SUMIFS(tblEnlaces[ValorOperativo (peso)], tblEnlaces[Nodo Origen], $C22, tblEnlaces[Nodo Destino], K$3, tblEnlaces[Activo], 1), 0) -> 0 | ... V22: =IF(MatrizDeAdyacencia!V22=1, SUMIFS(tblEnlaces[ValorOperativo (peso)], tblEnlaces[Nodo Origen], $C22, tblEnlaces[Nodo Destino], V$3, tblEnlaces[Activo], 1), 0) -> 0

Sheet MatrizTradeOff Valor Op-Coste
B2: Matriz TRADE-OFF Valor Operativo-Coste | D2: =VLOOKUP(tblMatrizTradeOff[[#Headers],[O1]],tblNodos[#All],2,FALSE) -> Coerción y cobros forzosos | E2: =VLOOKUP(tblMatrizTradeOff[[#Headers],[O2]],tblNodos[#All],2,FALSE) -> Contrabando / tráfico / comercio ilícito | F2: =VLOOKUP(tblMatrizTradeOff[[#Headers],[O3]],tblNodos[#All],2,FALSE) -> Explotación de recursos naturales | G2: =VLOOKUP(tblMatrizTradeOff[[#Headers],[O4]],tblNodos[#All],2,FALSE) -> Autofinanciación lícita / microfinanciación | H2: =VLOOKUP(tblMatrizTradeOff[[#Headers],[O5]],tblNodos[#All],2,FALSE) -> Actividades económicas formales / negocios | I2: =VLOOKUP(tblMatrizTradeOff[[#Headers],[O6]],tblNodos[#All],2,FALSE) -> Donaciones / crowdfunding / apoyo online | J2: =VLOOKUP(tblMatrizTradeOff[[#Headers],[I1]],tblNodos[#All],2,FALSE) -> Efectivo | K2: =VLOOKUP(tblMatrizTradeOff[[#Headers],[I2]],tblNodos[#All],2,FALSE) -> Hawala / HOSSP | L2: =VLOOKUP(tblMatrizTradeOff[[#Headers],[I3]],tblNodos[#All],2,FALSE) -> MVTS / remesas | M2: =VLOOKUP(tblMatrizTradeOff[[#Headers],[I4]],tblNodos[#All],2,FALSE) -> Dinero móvil | N2: =VLOOKUP(tblMatrizTradeOff[[#Headers],[I5]],tblNodos[#All],2,FALSE) -> Pagos online | O2: =VLOOKUP(tblMatrizTradeOff[[#Headers],[I6]],tblNodos[#All],2,FALSE) -> Servicios bancarios | P2: =VLOOKUP(tblMatrizTradeOff[[#Headers],[I7]],tblNodos[#All],2,FALSE) -> Tarjetas prepago / e-wallets | Q2: =VLOOKUP(tblMatrizTradeOff[[#Headers],[I8]],tblNodos[#All],2,FALSE) -> Plataformas digitales | R2: =VLOOKUP(tblMatrizTradeOff[[#Headers],[I9]],tblNodos[#All],2,FALSE) -> Activos virtuales | S2: =VLOOKUP(tblMatrizTradeOff[[#Headers],[G1]],tblNodos[#All],2,FALSE) -> Tesorería central | T2: =VLOOKUP(tblMatrizTradeOff[[#Headers],[G2]],tblNodos[#All],2,FALSE) -> Centro financiero regional / célula | U2: =VLOOKUP(tblMatrizTradeOff[[#Headers],[G3]],tblNodos[#All],2,FALSE) -> Facilitador externo / entidad instrumental | V2: =VLOOKUP(tblMatrizTradeOff[[#Headers],[D]],tblNodos[#All],2,FALSE) -> Destino operativo | X2: Matriz de Distancias | Z2: =VLOOKUP(tblMatrizDistancias[[#Headers],[O1]],tblNodos[#All],2,FALSE) -> Coerción y cobros forzosos | AA2: =VLOOKUP(tblMatrizDistancias[[#Headers],[O2]],tblNodos[#All],2,FALSE) -> Contrabando / tráfico / comercio ilícito | AB2: =VLOOKUP(tblMatrizDistancias[[#Headers],[O3]],tblNodos[#All],2,FALSE) -> Explotación de recursos naturales | AC2: =VLOOKUP(tblMatrizDistancias[[#Headers],[O4]],tblNodos[#All],2,FALSE) -> Autofinanciación lícita / microfinanciación | AD2: =VLOOKUP(tblMatrizDistancias[[#Headers],[O5]],tblNodos[#All],2,FALSE) -> Actividades económicas formales / negocios | AE2: =VLOOKUP(tblMatrizDistancias[[#Headers],[O6]],tblNodos[#All],2,FALSE) -> Donaciones / crowdfunding / apoyo online | AF2: =VLOOKUP(tblMatrizDistancias[[#Headers],[I1]],tblNodos[#All],2,FALSE) -> Efectivo | AG2: =VLOOKUP(tblMatrizDistancias[[#Headers],[I2]],tblNodos[#All],2,FALSE) -> Hawala / HOSSP | AH2: =VLOOKUP(tblMatrizDistancias[[#Headers],[I3]],tblNodos[#All],2,FALSE) -> MVTS / remesas | AI2: =VLOOKUP(tblMatrizDistancias[[#Headers],[I4]],tblNodos[#All],2,FALSE) -> Dinero móvil | AJ2: =VLOOKUP(tblMatrizDistancias[[#Headers],[I5]],tblNodos[#All],2,FALSE) -> Pagos online | AK2: =VLOOKUP(tblMatrizDistancias[[#Headers],[I6]],tblNodos[#All],2,FALSE) -> Servicios bancarios | AL2: =VLOOKUP(tblMatrizDistancias[[#Headers],[I7]],tblNodos[#All],2,FALSE) -> Tarjetas prepago / e-wallets | AM2: =VLOOKUP(tblMatrizDistancias[[#Headers],[I8]],tblNodos[#All],2,FALSE) -> Plataformas digitales | AN2: =VLOOKUP(tblMatrizDistancias[[#Headers],[I9]],tblNodos[#All],2,FALSE) -> Activos virtuales | AO2: =VLOOKUP(tblMatrizDistancias[[#Headers],[G1]],tblNodos[#All],2,FALSE) -> Tesorería central | AP2: =VLOOKUP(tblMatrizDistancias[[#Headers],[G2]],tblNodos[#All],2,FALSE) -> Centro financiero regional / célula | AQ2: =VLOOKUP(tblMatrizDistancias[[#Headers],[G3]],tblNodos[#All],2,FALSE) -> Facilitador externo / entidad instrumental | AR2: =VLOOKUP(tblMatrizDistancias[[#Headers],[D]],tblNodos[#All],2,FALSE) -> Destino operativo
B3: Nombre Nodo | C3: NodoOrigen \ NodoDestino | D3: O1 | E3: O2 | F3: O3 | G3: O4 | H3: O5 | I3: O6 | J3: I1 | K3: I2 | L3: I3 | M3: I4 | N3: I5 | O3: I6 | P3: I7 | Q3: I8 | R3: I9 | S3: G1 | T3: G2 | U3: G3 | V3: D | X3: Nombre Nodo | Y3: NodoOrigen \ NodoDestino | Z3: O1 | AA3: O2 | AB3: O3 | AC3: O4 | AD3: O5 | AE3: O6 | AF3: I1 | AG3: I2 | AH3: I3 | AI3: I4 | AJ3: I5 | AK3: I6 | AL3: I7 | AM3: I8 | AN3: I9 | AO3: G1 | AP3: G2 | AQ3: G3 | AR3: D
B4: =VLOOKUP(tblMatrizTradeOff[[#This Row],[NodoOrigen \ NodoDestino]],tblNodos[#All],2,FALSE) -> Coerción y cobros forzosos | C4: O1 | D4: =IF(OR(MatrizPonderadaCostes!D4=0,MatrizPonderadaValorOperativo!D4=0),0,MatrizPonderadaValorOperativo!D4/MatrizPonderadaCostes!D4) -> 0 | E4: =IF(OR(MatrizPonderadaCostes!E4=0,MatrizPonderadaValorOperativo!E4=0),0,MatrizPonderadaValorOperativo!E4/MatrizPonderadaCostes!E4) -> 0 | F4: =IF(OR(MatrizPonderadaCostes!F4=0,MatrizPonderadaValorOperativo!F4=0),0,MatrizPonderadaValorOperativo!F4/MatrizPonderadaCostes!F4) -> 0 | G4: =IF(OR(MatrizPonderadaCostes!G4=0,MatrizPonderadaValorOperativo!G4=0),0,MatrizPonderadaValorOperativo!G4/MatrizPonderadaCostes!G4) -> 0 | H4: =IF(OR(MatrizPonderadaCostes!H4=0,MatrizPonderadaValorOperativo!H4=0),0,MatrizPonderadaValorOperativo!H4/MatrizPonderadaCostes!H4) -> 0 | I4: =IF(OR(MatrizPonderadaCostes!I4=0,MatrizPonderadaValorOperativo!I4=0),0,MatrizPonderadaValorOperativo!I4/MatrizPonderadaCostes!I4) -> 0 | J4: =IF(OR(MatrizPonderadaCostes!J4=0,MatrizPonderadaValorOperativo!J4=0),0,MatrizPonderadaValorOperativo!J4/MatrizPonderadaCostes!J4) -> 3.6 | K4: =IF(OR(MatrizPonderadaCostes!K4=0,MatrizPonderadaValorOperativo!K4=0),0,MatrizPonderadaValorOperativo!K4/MatrizPonderadaCostes!K4) -> 6 | ... V4: =IF(OR(MatrizPonderadaCostes!V4=0,MatrizPonderadaValorOperativo!V4=0),0,MatrizPonderadaValorOperativo!V4/MatrizPonderadaCostes!V4) -> 0 | X4: =VLOOKUP(tblMatrizDistancias[[#This Row],[NodoOrigen \ NodoDestino]],tblNodos[#All],2,FALSE) -> Coerción y cobros forzosos | Y4: O1 | Z4: =IF(tblMatrizDistancias[[#This Row],[NodoOrigen \ NodoDestino]]="O1",0,IF(tblMatrizTradeOff[[#This Row],[O1]]=0,9999,1/tblMatrizTradeOff[[#This Row],[O1]])) -> 0 | AA4: =IF(tblMatrizDistancias[[#This Row],[NodoOrigen \ NodoDestino]]="O2",0,IF(tblMatrizTradeOff[[#This Row],[O2]]=0,9999,1/tblMatrizTradeOff[[#This Row],[O2]])) -> 9999 | AB4: =IF(tblMatrizDistancias[[#This Row],[NodoOrigen \ NodoDestino]]="O3",0,IF(tblMatrizTradeOff[[#This Row],[O3]]=0,9999,1/tblMatrizTradeOff[[#This Row],[O3]])) -> 9999 | AC4: =IF(tblMatrizDistancias[[#This Row],[NodoOrigen \ NodoDestino]]="O4",0,IF(tblMatrizTradeOff[[#This Row],[O4]]=0,9999,1/tblMatrizTradeOff[[#This Row],[O4]])) -> 9999 | AD4: =IF(tblMatrizDistancias[[#This Row],[NodoOrigen \ NodoDestino]]="O5",0,IF(tblMatrizTradeOff[[#This Row],[O5]]=0,9999,1/tblMatrizTradeOff[[#This Row],[O5]])) -> 9999 | AE4: =IF(tblMatrizDistancias[[#This Row],[NodoOrigen \ NodoDestino]]="O6",0,IF(tblMatrizTradeOff[[#This Row],[O6]]=0,9999,1/tblMatrizTradeOff[[#This Row],[O6]])) -> 9999 | AF4: =IF(tblMatrizDistancias[[#This Row],[NodoOrigen \ NodoDestino]]="I1",0,IF(tblMatrizTradeOff[[#This Row],[I1]]=0,9999,1/tblMatrizTradeOff[[#This Row],[I1]])) -> 0.27777778 | AG4: =IF(tblMatrizDistancias[[#This Row],[NodoOrigen \ NodoDestino]]="I2",0,IF(tblMatrizTradeOff[[#This Row],[I2]]=0,9999,1/tblMatrizTradeOff[[#This Row],[I2]])) -> 0.16666667 | AH4: =IF(tblMatrizDistancias[[#This Row],[NodoOrigen \ NodoDestino]]="I3",0,IF(tblMatrizTradeOff[[#This Row],[I3]]=0,9999,1/tblMatrizTradeOff[[#This Row],[I3]])) -> 0.21428571 | AI4: =IF(tblMatrizDistancias[[#This Row],[NodoOrigen \ NodoDestino]]="I4",0,IF(tblMatrizTradeOff[[#This Row],[I4]]=0,9999,1/tblMatrizTradeOff[[#This Row],[I4]])) -> 0.28571429 | AJ4: =IF(tblMatrizDistancias[[#This Row],[NodoOrigen \ NodoDestino]]="I5",0,IF(tblMatrizTradeOff[[#This Row],[I5]]=0,9999,1/tblMatrizTradeOff[[#This Row],[I5]])) -> 9999 | AK4: =IF(tblMatrizDistancias[[#This Row],[NodoOrigen \ NodoDestino]]="I6",0,IF(tblMatrizTradeOff[[#This Row],[I6]]=0,9999,1/tblMatrizTradeOff[[#This Row],[I6]])) -> 9999 | AL4: =IF(tblMatrizDistancias[[#This Row],[NodoOrigen \ NodoDestino]]="I7",0,IF(tblMatrizTradeOff[[#This Row],[I7]]=0,9999,1/tblMatrizTradeOff[[#This Row],[I7]])) -> 9999 | AM4: =IF(tblMatrizDistancias[[#This Row],[NodoOrigen \ NodoDestino]]="I8",0,IF(tblMatrizTradeOff[[#This Row],[I8]]=0,9999,1/tblMatrizTradeOff[[#This Row],[I8]])) -> 9999 | AN4: =IF(tblMatrizDistancias[[#This Row],[NodoOrigen \ NodoDestino]]="I9",0,IF(tblMatrizTradeOff[[#This Row],[I9]]=0,9999,1/tblMatrizTradeOff[[#This Row],[I9]])) -> 0.25 | AO4: =IF(tblMatrizDistancias[[#This Row],[NodoOrigen \ NodoDestino]]="G1",0,IF(tblMatrizTradeOff[[#This Row],[G1]]=0,9999,1/tblMatrizTradeOff[[#This Row],[G1]])) -> 9999 | AP4: =IF(tblMatrizDistancias[[#This Row],[NodoOrigen \ NodoDestino]]="G2",0,IF(tblMatrizTradeOff[[#This Row],[G2]]=0,9999,1/tblMatrizTradeOff[[#This Row],[G2]])) -> 9999 | AQ4: =IF(tblMatrizDistancias[[#This Row],[NodoOrigen \ NodoDestino]]="G3",0,IF(tblMatrizTradeOff[[#This Row],[G3]]=0,9999,1/tblMatrizTradeOff[[#This Row],[G3]])) -> 9999 | AR4: =IF(tblMatrizDistancias[[#This Row],[NodoOrigen \ NodoDestino]]="D",0,IF(tblMatrizTradeOff[[#This Row],[D]]=0,9999,1/tblMatrizTradeOff[[#This Row],[D]])) -> 9999
B5: =VLOOKUP(tblMatrizTradeOff[[#This Row],[NodoOrigen \ NodoDestino]],tblNodos[#All],2,FALSE) -> Contrabando / tráfico / comercio ilícito | C5: O2 | D5: =IF(OR(MatrizPonderadaCostes!D5=0,MatrizPonderadaValorOperativo!D5=0),0,MatrizPonderadaValorOperativo!D5/MatrizPonderadaCostes!D5) -> 0 | E5: =IF(OR(MatrizPonderadaCostes!E5=0,MatrizPonderadaValorOperativo!E5=0),0,MatrizPonderadaValorOperativo!E5/MatrizPonderadaCostes!E5) -> 0 | F5: =IF(OR(MatrizPonderadaCostes!F5=0,MatrizPonderadaValorOperativo!F5=0),0,MatrizPonderadaValorOperativo!F5/MatrizPonderadaCostes!F5) -> 0 | G5: =IF(OR(MatrizPonderadaCostes!G5=0,MatrizPonderadaValorOperativo!G5=0),0,MatrizPonderadaValorOperativo!G5/MatrizPonderadaCostes!G5) -> 0 | H5: =IF(OR(MatrizPonderadaCostes!H5=0,MatrizPonderadaValorOperativo!H5=0),0,MatrizPonderadaValorOperativo!H5/MatrizPonderadaCostes!H5) -> 0 | I5: =IF(OR(MatrizPonderadaCostes!I5=0,MatrizPonderadaValorOperativo!I5=0),0,MatrizPonderadaValorOperativo!I5/MatrizPonderadaCostes!I5) -> 0 | J5: =IF(OR(MatrizPonderadaCostes!J5=0,MatrizPonderadaValorOperativo!J5=0),0,MatrizPonderadaValorOperativo!J5/MatrizPonderadaCostes!J5) -> 3.4 | K5: =IF(OR(MatrizPonderadaCostes!K5=0,MatrizPonderadaValorOperativo!K5=0),0,MatrizPonderadaValorOperativo!K5/MatrizPonderadaCostes!K5) -> 6.3333333 | ... V5: =IF(OR(MatrizPonderadaCostes!V5=0,MatrizPonderadaValorOperativo!V5=0),0,MatrizPonderadaValorOperativo!V5/MatrizPonderadaCostes!V5) -> 0 | X5: =VLOOKUP(tblMatrizDistancias[[#This Row],[NodoOrigen \ NodoDestino]],tblNodos[#All],2,FALSE) -> Contrabando / tráfico / comercio ilícito | Y5: O2 | Z5: =IF(tblMatrizDistancias[[#This Row],[NodoOrigen \ NodoDestino]]="O1",0,IF(tblMatrizTradeOff[[#This Row],[O1]]=0,9999,1/tblMatrizTradeOff[[#This Row],[O1]])) -> 9999 | AA5: =IF(tblMatrizDistancias[[#This Row],[NodoOrigen \ NodoDestino]]="O2",0,IF(tblMatrizTradeOff[[#This Row],[O2]]=0,9999,1/tblMatrizTradeOff[[#This Row],[O2]])) -> 0 | AB5: =IF(tblMatrizDistancias[[#This Row],[NodoOrigen \ NodoDestino]]="O3",0,IF(tblMatrizTradeOff[[#This Row],[O3]]=0,9999,1/tblMatrizTradeOff[[#This Row],[O3]])) -> 9999 | AC5: =IF(tblMatrizDistancias[[#This Row],[NodoOrigen \ NodoDestino]]="O4",0,IF(tblMatrizTradeOff[[#This Row],[O4]]=0,9999,1/tblMatrizTradeOff[[#This Row],[O4]])) -> 9999 | AD5: =IF(tblMatrizDistancias[[#This Row],[NodoOrigen \ NodoDestino]]="O5",0,IF(tblMatrizTradeOff[[#This Row],[O5]]=0,9999,1/tblMatrizTradeOff[[#This Row],[O5]])) -> 9999 | AE5: =IF(tblMatrizDistancias[[#This Row],[NodoOrigen \ NodoDestino]]="O6",0,IF(tblMatrizTradeOff[[#This Row],[O6]]=0,9999,1/tblMatrizTradeOff[[#This Row],[O6]])) -> 9999 | AF5: =IF(tblMatrizDistancias[[#This Row],[NodoOrigen \ NodoDestino]]="I1",0,IF(tblMatrizTradeOff[[#This Row],[I1]]=0,9999,1/tblMatrizTradeOff[[#This Row],[I1]])) -> 0.29411765 | AG5: =IF(tblMatrizDistancias[[#This Row],[NodoOrigen \ NodoDestino]]="I2",0,IF(tblMatrizTradeOff[[#This Row],[I2]]=0,9999,1/tblMatrizTradeOff[[#This Row],[I2]])) -> 0.15789474 | AH5: =IF(tblMatrizDistancias[[#This Row],[NodoOrigen \ NodoDestino]]="I3",0,IF(tblMatrizTradeOff[[#This Row],[I3]]=0,9999,1/tblMatrizTradeOff[[#This Row],[I3]])) -> 0.21428571 | AI5: =IF(tblMatrizDistancias[[#This Row],[NodoOrigen \ NodoDestino]]="I4",0,IF(tblMatrizTradeOff[[#This Row],[I4]]=0,9999,1/tblMatrizTradeOff[[#This Row],[I4]])) -> 9999 | AJ5: =IF(tblMatrizDistancias[[#This Row],[NodoOrigen \ NodoDestino]]="I5",0,IF(tblMatrizTradeOff[[#This Row],[I5]]=0,9999,1/tblMatrizTradeOff[[#This Row],[I5]])) -> 9999 | AK5: =IF(tblMatrizDistancias[[#This Row],[NodoOrigen \ NodoDestino]]="I6",0,IF(tblMatrizTradeOff[[#This Row],[I6]]=0,9999,1/tblMatrizTradeOff[[#This Row],[I6]])) -> 9999 | AL5: =IF(tblMatrizDistancias[[#This Row],[NodoOrigen \ NodoDestino]]="I7",0,IF(tblMatrizTradeOff[[#This Row],[I7]]=0,9999,1/tblMatrizTradeOff[[#This Row],[I7]])) -> 9999 | AM5: =IF(tblMatrizDistancias[[#This Row],[NodoOrigen \ NodoDestino]]="I8",0,IF(tblMatrizTradeOff[[#This Row],[I8]]=0,9999,1/tblMatrizTradeOff[[#This Row],[I8]])) -> 9999 | AN5: =IF(tblMatrizDistancias[[#This Row],[NodoOrigen \ NodoDestino]]="I9",0,IF(tblMatrizTradeOff[[#This Row],[I9]]=0,9999,1/tblMatrizTradeOff[[#This Row],[I9]])) -> 9999 | AO5: =IF(tblMatrizDistancias[[#This Row],[NodoOrigen \ NodoDestino]]="G1",0,IF(tblMatrizTradeOff[[#This Row],[G1]]=0,9999,1/tblMatrizTradeOff[[#This Row],[G1]])) -> 9999 | AP5: =IF(tblMatrizDistancias[[#This Row],[NodoOrigen \ NodoDestino]]="G2",0,IF(tblMatrizTradeOff[[#This Row],[G2]]=0,9999,1/tblMatrizTradeOff[[#This Row],[G2]])) -> 9999 | AQ5: =IF(tblMatrizDistancias[[#This Row],[NodoOrigen \ NodoDestino]]="G3",0,IF(tblMatrizTradeOff[[#This Row],[G3]]=0,9999,1/tblMatrizTradeOff[[#This Row],[G3]])) -> 9999 | AR5: =IF(tblMatrizDistancias[[#This Row],[NodoOrigen \ NodoDestino]]="D",0,IF(tblMatrizTradeOff[[#This Row],[D]]=0,9999,1/tblMatrizTradeOff[[#This Row],[D]])) -> 9999
B6: =VLOOKUP(tblMatrizTradeOff[[#This Row],[NodoOrigen \ NodoDestino]],tblNodos[#All],2,FALSE) -> Explotación de recursos naturales | C6: O3 | D6: =IF(OR(MatrizPonderadaCostes!D6=0,MatrizPonderadaValorOperativo!D6=0),0,MatrizPonderadaValorOperativo!D6/MatrizPonderadaCostes!D6) -> 0 | E6: =IF(OR(MatrizPonderadaCostes!E6=0,MatrizPonderadaValorOperativo!E6=0),0,MatrizPonderadaValorOperativo!E6/MatrizPonderadaCostes!E6) -> 0 | F6: =IF(OR(MatrizPonderadaCostes!F6=0,MatrizPonderadaValorOperativo!F6=0),0,MatrizPonderadaValorOperativo!F6/MatrizPonderadaCostes!F6) -> 0 | G6: =IF(OR(MatrizPonderadaCostes!G6=0,MatrizPonderadaValorOperativo!G6=0),0,MatrizPonderadaValorOperativo!G6/MatrizPonderadaCostes!G6) -> 0 | H6: =IF(OR(MatrizPonderadaCostes!H6=0,MatrizPonderadaValorOperativo!H6=0),0,MatrizPonderadaValorOperativo!H6/MatrizPonderadaCostes!H6) -> 0 | I6: =IF(OR(MatrizPonderadaCostes!I6=0,MatrizPonderadaValorOperativo!I6=0),0,MatrizPonderadaValorOperativo!I6/MatrizPonderadaCostes!I6) -> 0 | J6: =IF(OR(MatrizPonderadaCostes!J6=0,MatrizPonderadaValorOperativo!J6=0),0,MatrizPonderadaValorOperativo!J6/MatrizPonderadaCostes!J6) -> 3.4 | K6: =IF(OR(MatrizPonderadaCostes!K6=0,MatrizPonderadaValorOperativo!K6=0),0,MatrizPonderadaValorOperativo!K6/MatrizPonderadaCostes!K6) -> 6.3333333 | ... V6: =IF(OR(MatrizPonderadaCostes!V6=0,MatrizPonderadaValorOperativo!V6=0),0,MatrizPonderadaValorOperativo!V6/MatrizPonderadaCostes!V6) -> 0 | X6: =VLOOKUP(tblMatrizDistancias[[#This Row],[NodoOrigen \ NodoDestino]],tblNodos[#All],2,FALSE) -> Explotación de recursos naturales | Y6: O3 | Z6: =IF(tblMatrizDistancias[[#This Row],[NodoOrigen \ NodoDestino]]="O1",0,IF(tblMatrizTradeOff[[#This Row],[O1]]=0,9999,1/tblMatrizTradeOff[[#This Row],[O1]])) -> 9999 | AA6: =IF(tblMatrizDistancias[[#This Row],[NodoOrigen \ NodoDestino]]="O2",0,IF(tblMatrizTradeOff[[#This Row],[O2]]=0,9999,1/tblMatrizTradeOff[[#This Row],[O2]])) -> 9999 | AB6: =IF(tblMatrizDistancias[[#This Row],[NodoOrigen \ NodoDestino]]="O3",0,IF(tblMatrizTradeOff[[#This Row],[O3]]=0,9999,1/tblMatrizTradeOff[[#This Row],[O3]])) -> 0 | AC6: =IF(tblMatrizDistancias[[#This Row],[NodoOrigen \ NodoDestino]]="O4",0,IF(tblMatrizTradeOff[[#This Row],[O4]]=0,9999,1/tblMatrizTradeOff[[#This Row],[O4]])) -> 9999 | AD6: =IF(tblMatrizDistancias[[#This Row],[NodoOrigen \ NodoDestino]]="O5",0,IF(tblMatrizTradeOff[[#This Row],[O5]]=0,9999,1/tblMatrizTradeOff[[#This Row],[O5]])) -> 9999 | AE6: =IF(tblMatrizDistancias[[#This Row],[NodoOrigen \ NodoDestino]]="O6",0,IF(tblMatrizTradeOff[[#This Row],[O6]]=0,9999,1/tblMatrizTradeOff[[#This Row],[O6]])) -> 9999 | AF6: =IF(tblMatrizDistancias[[#This Row],[NodoOrigen \ NodoDestino]]="I1",0,IF(tblMatrizTradeOff[[#This Row],[I1]]=0,9999,1/tblMatrizTradeOff[[#This Row],[I1]])) -> 0.29411765 | AG6: =IF(tblMatrizDistancias[[#This Row],[NodoOrigen \ NodoDestino]]="I2",0,IF(tblMatrizTradeOff[[#This Row],[I2]]=0,9999,1/tblMatrizTradeOff[[#This Row],[I2]])) -> 0.15789474 | AH6: =IF(tblMatrizDistancias[[#This Row],[NodoOrigen \ NodoDestino]]="I3",0,IF(tblMatrizTradeOff[[#This Row],[I3]]=0,9999,1/tblMatrizTradeOff[[#This Row],[I3]])) -> 0.2 | AI6: =IF(tblMatrizDistancias[[#This Row],[NodoOrigen \ NodoDestino]]="I4",0,IF(tblMatrizTradeOff[[#This Row],[I4]]=0,9999,1/tblMatrizTradeOff[[#This Row],[I4]])) -> 9999 | AJ6: =IF(tblMatrizDistancias[[#This Row],[NodoOrigen \ NodoDestino]]="I5",0,IF(tblMatrizTradeOff[[#This Row],[I5]]=0,9999,1/tblMatrizTradeOff[[#This Row],[I5]])) -> 9999 | AK6: =IF(tblMatrizDistancias[[#This Row],[NodoOrigen \ NodoDestino]]="I6",0,IF(tblMatrizTradeOff[[#This Row],[I6]]=0,9999,1/tblMatrizTradeOff[[#This Row],[I6]])) -> 9999 | AL6: =IF(tblMatrizDistancias[[#This Row],[NodoOrigen \ NodoDestino]]="I7",0,IF(tblMatrizTradeOff[[#This Row],[I7]]=0,9999,1/tblMatrizTradeOff[[#This Row],[I7]])) -> 9999 | AM6: =IF(tblMatrizDistancias[[#This Row],[NodoOrigen \ NodoDestino]]="I8",0,IF(tblMatrizTradeOff[[#This Row],[I8]]=0,9999,1/tblMatrizTradeOff[[#This Row],[I8]])) -> 9999 | AN6: =IF(tblMatrizDistancias[[#This Row],[NodoOrigen \ NodoDestino]]="I9",0,IF(tblMatrizTradeOff[[#This Row],[I9]]=0,9999,1/tblMatrizTradeOff[[#This Row],[I9]])) -> 9999 | AO6: =IF(tblMatrizDistancias[[#This Row],[NodoOrigen \ NodoDestino]]="G1",0,IF(tblMatrizTradeOff[[#This Row],[G1]]=0,9999,1/tblMatrizTradeOff[[#This Row],[G1]])) -> 9999 | AP6: =IF(tblMatrizDistancias[[#This Row],[NodoOrigen \ NodoDestino]]="G2",0,IF(tblMatrizTradeOff[[#This Row],[G2]]=0,9999,1/tblMatrizTradeOff[[#This Row],[G2]])) -> 9999 | AQ6: =IF(tblMatrizDistancias[[#This Row],[NodoOrigen \ NodoDestino]]="G3",0,IF(tblMatrizTradeOff[[#This Row],[G3]]=0,9999,1/tblMatrizTradeOff[[#This Row],[G3]])) -> 9999 | AR6: =IF(tblMatrizDistancias[[#This Row],[NodoOrigen \ NodoDestino]]="D",0,IF(tblMatrizTradeOff[[#This Row],[D]]=0,9999,1/tblMatrizTradeOff[[#This Row],[D]])) -> 9999
B7: =VLOOKUP(tblMatrizTradeOff[[#This Row],[NodoOrigen \ NodoDestino]],tblNodos[#All],2,FALSE) -> Autofinanciación lícita / microfinanciación | C7: O4 | D7: =IF(OR(MatrizPonderadaCostes!D7=0,MatrizPonderadaValorOperativo!D7=0),0,MatrizPonderadaValorOperativo!D7/MatrizPonderadaCostes!D7) -> 0 | E7: =IF(OR(MatrizPonderadaCostes!E7=0,MatrizPonderadaValorOperativo!E7=0),0,MatrizPonderadaValorOperativo!E7/MatrizPonderadaCostes!E7) -> 0 | F7: =IF(OR(MatrizPonderadaCostes!F7=0,MatrizPonderadaValorOperativo!F7=0),0,MatrizPonderadaValorOperativo!F7/MatrizPonderadaCostes!F7) -> 0 | G7: =IF(OR(MatrizPonderadaCostes!G7=0,MatrizPonderadaValorOperativo!G7=0),0,MatrizPonderadaValorOperativo!G7/MatrizPonderadaCostes!G7) -> 0 | H7: =IF(OR(MatrizPonderadaCostes!H7=0,MatrizPonderadaValorOperativo!H7=0),0,MatrizPonderadaValorOperativo!H7/MatrizPonderadaCostes!H7) -> 0 | I7: =IF(OR(MatrizPonderadaCostes!I7=0,MatrizPonderadaValorOperativo!I7=0),0,MatrizPonderadaValorOperativo!I7/MatrizPonderadaCostes!I7) -> 0 | J7: =IF(OR(MatrizPonderadaCostes!J7=0,MatrizPonderadaValorOperativo!J7=0),0,MatrizPonderadaValorOperativo!J7/MatrizPonderadaCostes!J7) -> 0 | K7: =IF(OR(MatrizPonderadaCostes!K7=0,MatrizPonderadaValorOperativo!K7=0),0,MatrizPonderadaValorOperativo!K7/MatrizPonderadaCostes!K7) -> 0 | ... V7: =IF(OR(MatrizPonderadaCostes!V7=0,MatrizPonderadaValorOperativo!V7=0),0,MatrizPonderadaValorOperativo!V7/MatrizPonderadaCostes!V7) -> 0 | X7: =VLOOKUP(tblMatrizDistancias[[#This Row],[NodoOrigen \ NodoDestino]],tblNodos[#All],2,FALSE) -> Autofinanciación lícita / microfinanciación | Y7: O4 | Z7: =IF(tblMatrizDistancias[[#This Row],[NodoOrigen \ NodoDestino]]="O1",0,IF(tblMatrizTradeOff[[#This Row],[O1]]=0,9999,1/tblMatrizTradeOff[[#This Row],[O1]])) -> 9999 | AA7: =IF(tblMatrizDistancias[[#This Row],[NodoOrigen \ NodoDestino]]="O2",0,IF(tblMatrizTradeOff[[#This Row],[O2]]=0,9999,1/tblMatrizTradeOff[[#This Row],[O2]])) -> 9999 | AB7: =IF(tblMatrizDistancias[[#This Row],[NodoOrigen \ NodoDestino]]="O3",0,IF(tblMatrizTradeOff[[#This Row],[O3]]=0,9999,1/tblMatrizTradeOff[[#This Row],[O3]])) -> 9999 | AC7: =IF(tblMatrizDistancias[[#This Row],[NodoOrigen \ NodoDestino]]="O4",0,IF(tblMatrizTradeOff[[#This Row],[O4]]=0,9999,1/tblMatrizTradeOff[[#This Row],[O4]])) -> 0 | AD7: =IF(tblMatrizDistancias[[#This Row],[NodoOrigen \ NodoDestino]]="O5",0,IF(tblMatrizTradeOff[[#This Row],[O5]]=0,9999,1/tblMatrizTradeOff[[#This Row],[O5]])) -> 9999 | AE7: =IF(tblMatrizDistancias[[#This Row],[NodoOrigen \ NodoDestino]]="O6",0,IF(tblMatrizTradeOff[[#This Row],[O6]]=0,9999,1/tblMatrizTradeOff[[#This Row],[O6]])) -> 9999 | AF7: =IF(tblMatrizDistancias[[#This Row],[NodoOrigen \ NodoDestino]]="I1",0,IF(tblMatrizTradeOff[[#This Row],[I1]]=0,9999,1/tblMatrizTradeOff[[#This Row],[I1]])) -> 9999 | AG7: =IF(tblMatrizDistancias[[#This Row],[NodoOrigen \ NodoDestino]]="I2",0,IF(tblMatrizTradeOff[[#This Row],[I2]]=0,9999,1/tblMatrizTradeOff[[#This Row],[I2]])) -> 9999 | AH7: =IF(tblMatrizDistancias[[#This Row],[NodoOrigen \ NodoDestino]]="I3",0,IF(tblMatrizTradeOff[[#This Row],[I3]]=0,9999,1/tblMatrizTradeOff[[#This Row],[I3]])) -> 9999 | AI7: =IF(tblMatrizDistancias[[#This Row],[NodoOrigen \ NodoDestino]]="I4",0,IF(tblMatrizTradeOff[[#This Row],[I4]]=0,9999,1/tblMatrizTradeOff[[#This Row],[I4]])) -> 0.35714286 | AJ7: =IF(tblMatrizDistancias[[#This Row],[NodoOrigen \ NodoDestino]]="I5",0,IF(tblMatrizTradeOff[[#This Row],[I5]]=0,9999,1/tblMatrizTradeOff[[#This Row],[I5]])) -> 0.30769231 | AK7: =IF(tblMatrizDistancias[[#This Row],[NodoOrigen \ NodoDestino]]="I6",0,IF(tblMatrizTradeOff[[#This Row],[I6]]=0,9999,1/tblMatrizTradeOff[[#This Row],[I6]])) -> 0.25 | AL7: =IF(tblMatrizDistancias[[#This Row],[NodoOrigen \ NodoDestino]]="I7",0,IF(tblMatrizTradeOff[[#This Row],[I7]]=0,9999,1/tblMatrizTradeOff[[#This Row],[I7]])) -> 0.3 | AM7: =IF(tblMatrizDistancias[[#This Row],[NodoOrigen \ NodoDestino]]="I8",0,IF(tblMatrizTradeOff[[#This Row],[I8]]=0,9999,1/tblMatrizTradeOff[[#This Row],[I8]])) -> 9999 | AN7: =IF(tblMatrizDistancias[[#This Row],[NodoOrigen \ NodoDestino]]="I9",0,IF(tblMatrizTradeOff[[#This Row],[I9]]=0,9999,1/tblMatrizTradeOff[[#This Row],[I9]])) -> 9999 | AO7: =IF(tblMatrizDistancias[[#This Row],[NodoOrigen \ NodoDestino]]="G1",0,IF(tblMatrizTradeOff[[#This Row],[G1]]=0,9999,1/tblMatrizTradeOff[[#This Row],[G1]])) -> 9999 | AP7: =IF(tblMatrizDistancias[[#This Row],[NodoOrigen \ NodoDestino]]="G2",0,IF(tblMatrizTradeOff[[#This Row],[G2]]=0,9999,1/tblMatrizTradeOff[[#This Row],[G2]])) -> 9999 | AQ7: =IF(tblMatrizDistancias[[#This Row],[NodoOrigen \ NodoDestino]]="G3",0,IF(tblMatrizTradeOff[[#This Row],[G3]]=0,9999,1/tblMatrizTradeOff[[#This Row],[G3]])) -> 9999 | AR7: =IF(tblMatrizDistancias[[#This Row],[NodoOrigen \ NodoDestino]]="D",0,IF(tblMatrizTradeOff[[#This Row],[D]]=0,9999,1/tblMatrizTradeOff[[#This Row],[D]])) -> 9999
B8: =VLOOKUP(tblMatrizTradeOff[[#This Row],[NodoOrigen \ NodoDestino]],tblNodos[#All],2,FALSE) -> Actividades económicas formales / negocios | C8: O5 | D8: =IF(OR(MatrizPonderadaCostes!D8=0,MatrizPonderadaValorOperativo!D8=0),0,MatrizPonderadaValorOperativo!D8/MatrizPonderadaCostes!D8) -> 0 | E8: =IF(OR(MatrizPonderadaCostes!E8=0,MatrizPonderadaValorOperativo!E8=0),0,MatrizPonderadaValorOperativo!E8/MatrizPonderadaCostes!E8) -> 0 | F8: =IF(OR(MatrizPonderadaCostes!F8=0,MatrizPonderadaValorOperativo!F8=0),0,MatrizPonderadaValorOperativo!F8/MatrizPonderadaCostes!F8) -> 0 | G8: =IF(OR(MatrizPonderadaCostes!G8=0,MatrizPonderadaValorOperativo!G8=0),0,MatrizPonderadaValorOperativo!G8/MatrizPonderadaCostes!G8) -> 0 | H8: =IF(OR(MatrizPonderadaCostes!H8=0,MatrizPonderadaValorOperativo!H8=0),0,MatrizPonderadaValorOperativo!H8/MatrizPonderadaCostes!H8) -> 0 | I8: =IF(OR(MatrizPonderadaCostes!I8=0,MatrizPonderadaValorOperativo!I8=0),0,MatrizPonderadaValorOperativo!I8/MatrizPonderadaCostes!I8) -> 0 | J8: =IF(OR(MatrizPonderadaCostes!J8=0,MatrizPonderadaValorOperativo!J8=0),0,MatrizPonderadaValorOperativo!J8/MatrizPonderadaCostes!J8) -> 3.2 | K8: =IF(OR(MatrizPonderadaCostes!K8=0,MatrizPonderadaValorOperativo!K8=0),0,MatrizPonderadaValorOperativo!K8/MatrizPonderadaCostes!K8) -> 0 | ... V8: =IF(OR(MatrizPonderadaCostes!V8=0,MatrizPonderadaValorOperativo!V8=0),0,MatrizPonderadaValorOperativo!V8/MatrizPonderadaCostes!V8) -> 0 | X8: =VLOOKUP(tblMatrizDistancias[[#This Row],[NodoOrigen \ NodoDestino]],tblNodos[#All],2,FALSE) -> Actividades económicas formales / negocios | Y8: O5 | Z8: =IF(tblMatrizDistancias[[#This Row],[NodoOrigen \ NodoDestino]]="O1",0,IF(tblMatrizTradeOff[[#This Row],[O1]]=0,9999,1/tblMatrizTradeOff[[#This Row],[O1]])) -> 9999 | AA8: =IF(tblMatrizDistancias[[#This Row],[NodoOrigen \ NodoDestino]]="O2",0,IF(tblMatrizTradeOff[[#This Row],[O2]]=0,9999,1/tblMatrizTradeOff[[#This Row],[O2]])) -> 9999 | AB8: =IF(tblMatrizDistancias[[#This Row],[NodoOrigen \ NodoDestino]]="O3",0,IF(tblMatrizTradeOff[[#This Row],[O3]]=0,9999,1/tblMatrizTradeOff[[#This Row],[O3]])) -> 9999 | AC8: =IF(tblMatrizDistancias[[#This Row],[NodoOrigen \ NodoDestino]]="O4",0,IF(tblMatrizTradeOff[[#This Row],[O4]]=0,9999,1/tblMatrizTradeOff[[#This Row],[O4]])) -> 9999 | AD8: =IF(tblMatrizDistancias[[#This Row],[NodoOrigen \ NodoDestino]]="O5",0,IF(tblMatrizTradeOff[[#This Row],[O5]]=0,9999,1/tblMatrizTradeOff[[#This Row],[O5]])) -> 0 | AE8: =IF(tblMatrizDistancias[[#This Row],[NodoOrigen \ NodoDestino]]="O6",0,IF(tblMatrizTradeOff[[#This Row],[O6]]=0,9999,1/tblMatrizTradeOff[[#This Row],[O6]])) -> 9999 | AF8: =IF(tblMatrizDistancias[[#This Row],[NodoOrigen \ NodoDestino]]="I1",0,IF(tblMatrizTradeOff[[#This Row],[I1]]=0,9999,1/tblMatrizTradeOff[[#This Row],[I1]])) -> 0.3125 | AG8: =IF(tblMatrizDistancias[[#This Row],[NodoOrigen \ NodoDestino]]="I2",0,IF(tblMatrizTradeOff[[#This Row],[I2]]=0,9999,1/tblMatrizTradeOff[[#This Row],[I2]])) -> 9999 | AH8: =IF(tblMatrizDistancias[[#This Row],[NodoOrigen \ NodoDestino]]="I3",0,IF(tblMatrizTradeOff[[#This Row],[I3]]=0,9999,1/tblMatrizTradeOff[[#This Row],[I3]])) -> 9999 | AI8: =IF(tblMatrizDistancias[[#This Row],[NodoOrigen \ NodoDestino]]="I4",0,IF(tblMatrizTradeOff[[#This Row],[I4]]=0,9999,1/tblMatrizTradeOff[[#This Row],[I4]])) -> 9999 | AJ8: =IF(tblMatrizDistancias[[#This Row],[NodoOrigen \ NodoDestino]]="I5",0,IF(tblMatrizTradeOff[[#This Row],[I5]]=0,9999,1/tblMatrizTradeOff[[#This Row],[I5]])) -> 0.30769231 | AK8: =IF(tblMatrizDistancias[[#This Row],[NodoOrigen \ NodoDestino]]="I6",0,IF(tblMatrizTradeOff[[#This Row],[I6]]=0,9999,1/tblMatrizTradeOff[[#This Row],[I6]])) -> 0.21428571 | AL8: =IF(tblMatrizDistancias[[#This Row],[NodoOrigen \ NodoDestino]]="I7",0,IF(tblMatrizTradeOff[[#This Row],[I7]]=0,9999,1/tblMatrizTradeOff[[#This Row],[I7]])) -> 9999 | AM8: =IF(tblMatrizDistancias[[#This Row],[NodoOrigen \ NodoDestino]]="I8",0,IF(tblMatrizTradeOff[[#This Row],[I8]]=0,9999,1/tblMatrizTradeOff[[#This Row],[I8]])) -> 9999 | AN8: =IF(tblMatrizDistancias[[#This Row],[NodoOrigen \ NodoDestino]]="I9",0,IF(tblMatrizTradeOff[[#This Row],[I9]]=0,9999,1/tblMatrizTradeOff[[#This Row],[I9]])) -> 9999 | AO8: =IF(tblMatrizDistancias[[#This Row],[NodoOrigen \ NodoDestino]]="G1",0,IF(tblMatrizTradeOff[[#This Row],[G1]]=0,9999,1/tblMatrizTradeOff[[#This Row],[G1]])) -> 9999 | AP8: =IF(tblMatrizDistancias[[#This Row],[NodoOrigen \ NodoDestino]]="G2",0,IF(tblMatrizTradeOff[[#This Row],[G2]]=0,9999,1/tblMatrizTradeOff[[#This Row],[G2]])) -> 9999 | AQ8: =IF(tblMatrizDistancias[[#This Row],[NodoOrigen \ NodoDestino]]="G3",0,IF(tblMatrizTradeOff[[#This Row],[G3]]=0,9999,1/tblMatrizTradeOff[[#This Row],[G3]])) -> 9999 | AR8: =IF(tblMatrizDistancias[[#This Row],[NodoOrigen \ NodoDestino]]="D",0,IF(tblMatrizTradeOff[[#This Row],[D]]=0,9999,1/tblMatrizTradeOff[[#This Row],[D]])) -> 9999
B9: =VLOOKUP(tblMatrizTradeOff[[#This Row],[NodoOrigen \ NodoDestino]],tblNodos[#All],2,FALSE) -> Donaciones / crowdfunding / apoyo online | C9: O6 | D9: =IF(OR(MatrizPonderadaCostes!D9=0,MatrizPonderadaValorOperativo!D9=0),0,MatrizPonderadaValorOperativo!D9/MatrizPonderadaCostes!D9) -> 0 | E9: =IF(OR(MatrizPonderadaCostes!E9=0,MatrizPonderadaValorOperativo!E9=0),0,MatrizPonderadaValorOperativo!E9/MatrizPonderadaCostes!E9) -> 0 | F9: =IF(OR(MatrizPonderadaCostes!F9=0,MatrizPonderadaValorOperativo!F9=0),0,MatrizPonderadaValorOperativo!F9/MatrizPonderadaCostes!F9) -> 0 | G9: =IF(OR(MatrizPonderadaCostes!G9=0,MatrizPonderadaValorOperativo!G9=0),0,MatrizPonderadaValorOperativo!G9/MatrizPonderadaCostes!G9) -> 0 | H9: =IF(OR(MatrizPonderadaCostes!H9=0,MatrizPonderadaValorOperativo!H9=0),0,MatrizPonderadaValorOperativo!H9/MatrizPonderadaCostes!H9) -> 0 | I9: =IF(OR(MatrizPonderadaCostes!I9=0,MatrizPonderadaValorOperativo!I9=0),0,MatrizPonderadaValorOperativo!I9/MatrizPonderadaCostes!I9) -> 0 | J9: =IF(OR(MatrizPonderadaCostes!J9=0,MatrizPonderadaValorOperativo!J9=0),0,MatrizPonderadaValorOperativo!J9/MatrizPonderadaCostes!J9) -> 0 | K9: =IF(OR(MatrizPonderadaCostes!K9=0,MatrizPonderadaValorOperativo!K9=0),0,MatrizPonderadaValorOperativo!K9/MatrizPonderadaCostes!K9) -> 0 | ... V9: =IF(OR(MatrizPonderadaCostes!V9=0,MatrizPonderadaValorOperativo!V9=0),0,MatrizPonderadaValorOperativo!V9/MatrizPonderadaCostes!V9) -> 0 | X9: =VLOOKUP(tblMatrizDistancias[[#This Row],[NodoOrigen \ NodoDestino]],tblNodos[#All],2,FALSE) -> Donaciones / crowdfunding / apoyo online | Y9: O6 | Z9: =IF(tblMatrizDistancias[[#This Row],[NodoOrigen \ NodoDestino]]="O1",0,IF(tblMatrizTradeOff[[#This Row],[O1]]=0,9999,1/tblMatrizTradeOff[[#This Row],[O1]])) -> 9999 | AA9: =IF(tblMatrizDistancias[[#This Row],[NodoOrigen \ NodoDestino]]="O2",0,IF(tblMatrizTradeOff[[#This Row],[O2]]=0,9999,1/tblMatrizTradeOff[[#This Row],[O2]])) -> 9999 | AB9: =IF(tblMatrizDistancias[[#This Row],[NodoOrigen \ NodoDestino]]="O3",0,IF(tblMatrizTradeOff[[#This Row],[O3]]=0,9999,1/tblMatrizTradeOff[[#This Row],[O3]])) -> 9999 | AC9: =IF(tblMatrizDistancias[[#This Row],[NodoOrigen \ NodoDestino]]="O4",0,IF(tblMatrizTradeOff[[#This Row],[O4]]=0,9999,1/tblMatrizTradeOff[[#This Row],[O4]])) -> 9999 | AD9: =IF(tblMatrizDistancias[[#This Row],[NodoOrigen \ NodoDestino]]="O5",0,IF(tblMatrizTradeOff[[#This Row],[O5]]=0,9999,1/tblMatrizTradeOff[[#This Row],[O5]])) -> 9999 | AE9: =IF(tblMatrizDistancias[[#This Row],[NodoOrigen \ NodoDestino]]="O6",0,IF(tblMatrizTradeOff[[#This Row],[O6]]=0,9999,1/tblMatrizTradeOff[[#This Row],[O6]])) -> 0 | AF9: =IF(tblMatrizDistancias[[#This Row],[NodoOrigen \ NodoDestino]]="I1",0,IF(tblMatrizTradeOff[[#This Row],[I1]]=0,9999,1/tblMatrizTradeOff[[#This Row],[I1]])) -> 9999 | AG9: =IF(tblMatrizDistancias[[#This Row],[NodoOrigen \ NodoDestino]]="I2",0,IF(tblMatrizTradeOff[[#This Row],[I2]]=0,9999,1/tblMatrizTradeOff[[#This Row],[I2]])) -> 9999 | AH9: =IF(tblMatrizDistancias[[#This Row],[NodoOrigen \ NodoDestino]]="I3",0,IF(tblMatrizTradeOff[[#This Row],[I3]]=0,9999,1/tblMatrizTradeOff[[#This Row],[I3]])) -> 0.21428571 | AI9: =IF(tblMatrizDistancias[[#This Row],[NodoOrigen \ NodoDestino]]="I4",0,IF(tblMatrizTradeOff[[#This Row],[I4]]=0,9999,1/tblMatrizTradeOff[[#This Row],[I4]])) -> 9999 | AJ9: =IF(tblMatrizDistancias[[#This Row],[NodoOrigen \ NodoDestino]]="I5",0,IF(tblMatrizTradeOff[[#This Row],[I5]]=0,9999,1/tblMatrizTradeOff[[#This Row],[I5]])) -> 0.30769231 | AK9: =IF(tblMatrizDistancias[[#This Row],[NodoOrigen \ NodoDestino]]="I6",0,IF(tblMatrizTradeOff[[#This Row],[I6]]=0,9999,1/tblMatrizTradeOff[[#This Row],[I6]])) -> 9999 | AL9: =IF(tblMatrizDistancias[[#This Row],[NodoOrigen \ NodoDestino]]="I7",0,IF(tblMatrizTradeOff[[#This Row],[I7]]=0,9999,1/tblMatrizTradeOff[[#This Row],[I7]])) -> 9999 | AM9: =IF(tblMatrizDistancias[[#This Row],[NodoOrigen \ NodoDestino]]="I8",0,IF(tblMatrizTradeOff[[#This Row],[I8]]=0,9999,1/tblMatrizTradeOff[[#This Row],[I8]])) -> 0.45454545 | AN9: =IF(tblMatrizDistancias[[#This Row],[NodoOrigen \ NodoDestino]]="I9",0,IF(tblMatrizTradeOff[[#This Row],[I9]]=0,9999,1/tblMatrizTradeOff[[#This Row],[I9]])) -> 0.25 | AO9: =IF(tblMatrizDistancias[[#This Row],[NodoOrigen \ NodoDestino]]="G1",0,IF(tblMatrizTradeOff[[#This Row],[G1]]=0,9999,1/tblMatrizTradeOff[[#This Row],[G1]])) -> 9999 | AP9: =IF(tblMatrizDistancias[[#This Row],[NodoOrigen \ NodoDestino]]="G2",0,IF(tblMatrizTradeOff[[#This Row],[G2]]=0,9999,1/tblMatrizTradeOff[[#This Row],[G2]])) -> 9999 | AQ9: =IF(tblMatrizDistancias[[#This Row],[NodoOrigen \ NodoDestino]]="G3",0,IF(tblMatrizTradeOff[[#This Row],[G3]]=0,9999,1/tblMatrizTradeOff[[#This Row],[G3]])) -> 9999 | AR9: =IF(tblMatrizDistancias[[#This Row],[NodoOrigen \ NodoDestino]]="D",0,IF(tblMatrizTradeOff[[#This Row],[D]]=0,9999,1/tblMatrizTradeOff[[#This Row],[D]])) -> 9999
B10: =VLOOKUP(tblMatrizTradeOff[[#This Row],[NodoOrigen \ NodoDestino]],tblNodos[#All],2,FALSE) -> Efectivo | C10: I1 | D10: =IF(OR(MatrizPonderadaCostes!D10=0,MatrizPonderadaValorOperativo!D10=0),0,MatrizPonderadaValorOperativo!D10/MatrizPonderadaCostes!D10) -> 0 | E10: =IF(OR(MatrizPonderadaCostes!E10=0,MatrizPonderadaValorOperativo!E10=0),0,MatrizPonderadaValorOperativo!E10/MatrizPonderadaCostes!E10) -> 0 | F10: =IF(OR(MatrizPonderadaCostes!F10=0,MatrizPonderadaValorOperativo!F10=0),0,MatrizPonderadaValorOperativo!F10/MatrizPonderadaCostes!F10) -> 0 | G10: =IF(OR(MatrizPonderadaCostes!G10=0,MatrizPonderadaValorOperativo!G10=0),0,MatrizPonderadaValorOperativo!G10/MatrizPonderadaCostes!G10) -> 0 | H10: =IF(OR(MatrizPonderadaCostes!H10=0,MatrizPonderadaValorOperativo!H10=0),0,MatrizPonderadaValorOperativo!H10/MatrizPonderadaCostes!H10) -> 0 | I10: =IF(OR(MatrizPonderadaCostes!I10=0,MatrizPonderadaValorOperativo!I10=0),0,MatrizPonderadaValorOperativo!I10/MatrizPonderadaCostes!I10) -> 0 | J10: =IF(OR(MatrizPonderadaCostes!J10=0,MatrizPonderadaValorOperativo!J10=0),0,MatrizPonderadaValorOperativo!J10/MatrizPonderadaCostes!J10) -> 0 | K10: =IF(OR(MatrizPonderadaCostes!K10=0,MatrizPonderadaValorOperativo!K10=0),0,MatrizPonderadaValorOperativo!K10/MatrizPonderadaCostes!K10) -> 6 | ... V10: =IF(OR(MatrizPonderadaCostes!V10=0,MatrizPonderadaValorOperativo!V10=0),0,MatrizPonderadaValorOperativo!V10/MatrizPonderadaCostes!V10) -> 3 | X10: =VLOOKUP(tblMatrizDistancias[[#This Row],[NodoOrigen \ NodoDestino]],tblNodos[#All],2,FALSE) -> Efectivo | Y10: I1 | Z10: =IF(tblMatrizDistancias[[#This Row],[NodoOrigen \ NodoDestino]]="O1",0,IF(tblMatrizTradeOff[[#This Row],[O1]]=0,9999,1/tblMatrizTradeOff[[#This Row],[O1]])) -> 9999 | AA10: =IF(tblMatrizDistancias[[#This Row],[NodoOrigen \ NodoDestino]]="O2",0,IF(tblMatrizTradeOff[[#This Row],[O2]]=0,9999,1/tblMatrizTradeOff[[#This Row],[O2]])) -> 9999 | AB10: =IF(tblMatrizDistancias[[#This Row],[NodoOrigen \ NodoDestino]]="O3",0,IF(tblMatrizTradeOff[[#This Row],[O3]]=0,9999,1/tblMatrizTradeOff[[#This Row],[O3]])) -> 9999 | AC10: =IF(tblMatrizDistancias[[#This Row],[NodoOrigen \ NodoDestino]]="O4",0,IF(tblMatrizTradeOff[[#This Row],[O4]]=0,9999,1/tblMatrizTradeOff[[#This Row],[O4]])) -> 9999 | AD10: =IF(tblMatrizDistancias[[#This Row],[NodoOrigen \ NodoDestino]]="O5",0,IF(tblMatrizTradeOff[[#This Row],[O5]]=0,9999,1/tblMatrizTradeOff[[#This Row],[O5]])) -> 9999 | AE10: =IF(tblMatrizDistancias[[#This Row],[NodoOrigen \ NodoDestino]]="O6",0,IF(tblMatrizTradeOff[[#This Row],[O6]]=0,9999,1/tblMatrizTradeOff[[#This Row],[O6]])) -> 9999 | AF10: =IF(tblMatrizDistancias[[#This Row],[NodoOrigen \ NodoDestino]]="I1",0,IF(tblMatrizTradeOff[[#This Row],[I1]]=0,9999,1/tblMatrizTradeOff[[#This Row],[I1]])) -> 0 | AG10: =IF(tblMatrizDistancias[[#This Row],[NodoOrigen \ NodoDestino]]="I2",0,IF(tblMatrizTradeOff[[#This Row],[I2]]=0,9999,1/tblMatrizTradeOff[[#This Row],[I2]])) -> 0.16666667 | AH10: =IF(tblMatrizDistancias[[#This Row],[NodoOrigen \ NodoDestino]]="I3",0,IF(tblMatrizTradeOff[[#This Row],[I3]]=0,9999,1/tblMatrizTradeOff[[#This Row],[I3]])) -> 9999 | AI10: =IF(tblMatrizDistancias[[#This Row],[NodoOrigen \ NodoDestino]]="I4",0,IF(tblMatrizTradeOff[[#This Row],[I4]]=0,9999,1/tblMatrizTradeOff[[#This Row],[I4]])) -> 0.23076923 | AJ10: =IF(tblMatrizDistancias[[#This Row],[NodoOrigen \ NodoDestino]]="I5",0,IF(tblMatrizTradeOff[[#This Row],[I5]]=0,9999,1/tblMatrizTradeOff[[#This Row],[I5]])) -> 9999 | AK10: =IF(tblMatrizDistancias[[#This Row],[NodoOrigen \ NodoDestino]]="I6",0,IF(tblMatrizTradeOff[[#This Row],[I6]]=0,9999,1/tblMatrizTradeOff[[#This Row],[I6]])) -> 9999 | AL10: =IF(tblMatrizDistancias[[#This Row],[NodoOrigen \ NodoDestino]]="I7",0,IF(tblMatrizTradeOff[[#This Row],[I7]]=0,9999,1/tblMatrizTradeOff[[#This Row],[I7]])) -> 9999 | AM10: =IF(tblMatrizDistancias[[#This Row],[NodoOrigen \ NodoDestino]]="I8",0,IF(tblMatrizTradeOff[[#This Row],[I8]]=0,9999,1/tblMatrizTradeOff[[#This Row],[I8]])) -> 9999 | AN10: =IF(tblMatrizDistancias[[#This Row],[NodoOrigen \ NodoDestino]]="I9",0,IF(tblMatrizTradeOff[[#This Row],[I9]]=0,9999,1/tblMatrizTradeOff[[#This Row],[I9]])) -> 0.16666667 | AO10: =IF(tblMatrizDistancias[[#This Row],[NodoOrigen \ NodoDestino]]="G1",0,IF(tblMatrizTradeOff[[#This Row],[G1]]=0,9999,1/tblMatrizTradeOff[[#This Row],[G1]])) -> 9999 | AP10: =IF(tblMatrizDistancias[[#This Row],[NodoOrigen \ NodoDestino]]="G2",0,IF(tblMatrizTradeOff[[#This Row],[G2]]=0,9999,1/tblMatrizTradeOff[[#This Row],[G2]])) -> 9999 | AQ10: =IF(tblMatrizDistancias[[#This Row],[NodoOrigen \ NodoDestino]]="G3",0,IF(tblMatrizTradeOff[[#This Row],[G3]]=0,9999,1/tblMatrizTradeOff[[#This Row],[G3]])) -> 9999 | AR10: =IF(tblMatrizDistancias[[#This Row],[NodoOrigen \ NodoDestino]]="D",0,IF(tblMatrizTradeOff[[#This Row],[D]]=0,9999,1/tblMatrizTradeOff[[#This Row],[D]])) -> 0.33333333
B11: =VLOOKUP(tblMatrizTradeOff[[#This Row],[NodoOrigen \ NodoDestino]],tblNodos[#All],2,FALSE) -> Hawala / HOSSP | C11: I2 | D11: =IF(OR(MatrizPonderadaCostes!D11=0,MatrizPonderadaValorOperativo!D11=0),0,MatrizPonderadaValorOperativo!D11/MatrizPonderadaCostes!D11) -> 0 | E11: =IF(OR(MatrizPonderadaCostes!E11=0,MatrizPonderadaValorOperativo!E11=0),0,MatrizPonderadaValorOperativo!E11/MatrizPonderadaCostes!E11) -> 0 | F11: =IF(OR(MatrizPonderadaCostes!F11=0,MatrizPonderadaValorOperativo!F11=0),0,MatrizPonderadaValorOperativo!F11/MatrizPonderadaCostes!F11) -> 0 | G11: =IF(OR(MatrizPonderadaCostes!G11=0,MatrizPonderadaValorOperativo!G11=0),0,MatrizPonderadaValorOperativo!G11/MatrizPonderadaCostes!G11) -> 0 | H11: =IF(OR(MatrizPonderadaCostes!H11=0,MatrizPonderadaValorOperativo!H11=0),0,MatrizPonderadaValorOperativo!H11/MatrizPonderadaCostes!H11) -> 0 | I11: =IF(OR(MatrizPonderadaCostes!I11=0,MatrizPonderadaValorOperativo!I11=0),0,MatrizPonderadaValorOperativo!I11/MatrizPonderadaCostes!I11) -> 0 | J11: =IF(OR(MatrizPonderadaCostes!J11=0,MatrizPonderadaValorOperativo!J11=0),0,MatrizPonderadaValorOperativo!J11/MatrizPonderadaCostes!J11) -> 0 | K11: =IF(OR(MatrizPonderadaCostes!K11=0,MatrizPonderadaValorOperativo!K11=0),0,MatrizPonderadaValorOperativo!K11/MatrizPonderadaCostes!K11) -> 0 | ... V11: =IF(OR(MatrizPonderadaCostes!V11=0,MatrizPonderadaValorOperativo!V11=0),0,MatrizPonderadaValorOperativo!V11/MatrizPonderadaCostes!V11) -> 5.6666667 | X11: =VLOOKUP(tblMatrizDistancias[[#This Row],[NodoOrigen \ NodoDestino]],tblNodos[#All],2,FALSE) -> Hawala / HOSSP | Y11: I2 | Z11: =IF(tblMatrizDistancias[[#This Row],[NodoOrigen \ NodoDestino]]="O1",0,IF(tblMatrizTradeOff[[#This Row],[O1]]=0,9999,1/tblMatrizTradeOff[[#This Row],[O1]])) -> 9999 | AA11: =IF(tblMatrizDistancias[[#This Row],[NodoOrigen \ NodoDestino]]="O2",0,IF(tblMatrizTradeOff[[#This Row],[O2]]=0,9999,1/tblMatrizTradeOff[[#This Row],[O2]])) -> 9999 | AB11: =IF(tblMatrizDistancias[[#This Row],[NodoOrigen \ NodoDestino]]="O3",0,IF(tblMatrizTradeOff[[#This Row],[O3]]=0,9999,1/tblMatrizTradeOff[[#This Row],[O3]])) -> 9999 | AC11: =IF(tblMatrizDistancias[[#This Row],[NodoOrigen \ NodoDestino]]="O4",0,IF(tblMatrizTradeOff[[#This Row],[O4]]=0,9999,1/tblMatrizTradeOff[[#This Row],[O4]])) -> 9999 | AD11: =IF(tblMatrizDistancias[[#This Row],[NodoOrigen \ NodoDestino]]="O5",0,IF(tblMatrizTradeOff[[#This Row],[O5]]=0,9999,1/tblMatrizTradeOff[[#This Row],[O5]])) -> 9999 | AE11: =IF(tblMatrizDistancias[[#This Row],[NodoOrigen \ NodoDestino]]="O6",0,IF(tblMatrizTradeOff[[#This Row],[O6]]=0,9999,1/tblMatrizTradeOff[[#This Row],[O6]])) -> 9999 | AF11: =IF(tblMatrizDistancias[[#This Row],[NodoOrigen \ NodoDestino]]="I1",0,IF(tblMatrizTradeOff[[#This Row],[I1]]=0,9999,1/tblMatrizTradeOff[[#This Row],[I1]])) -> 9999 | AG11: =IF(tblMatrizDistancias[[#This Row],[NodoOrigen \ NodoDestino]]="I2",0,IF(tblMatrizTradeOff[[#This Row],[I2]]=0,9999,1/tblMatrizTradeOff[[#This Row],[I2]])) -> 0 | AH11: =IF(tblMatrizDistancias[[#This Row],[NodoOrigen \ NodoDestino]]="I3",0,IF(tblMatrizTradeOff[[#This Row],[I3]]=0,9999,1/tblMatrizTradeOff[[#This Row],[I3]])) -> 9999 | AI11: =IF(tblMatrizDistancias[[#This Row],[NodoOrigen \ NodoDestino]]="I4",0,IF(tblMatrizTradeOff[[#This Row],[I4]]=0,9999,1/tblMatrizTradeOff[[#This Row],[I4]])) -> 9999 | AJ11: =IF(tblMatrizDistancias[[#This Row],[NodoOrigen \ NodoDestino]]="I5",0,IF(tblMatrizTradeOff[[#This Row],[I5]]=0,9999,1/tblMatrizTradeOff[[#This Row],[I5]])) -> 9999 | AK11: =IF(tblMatrizDistancias[[#This Row],[NodoOrigen \ NodoDestino]]="I6",0,IF(tblMatrizTradeOff[[#This Row],[I6]]=0,9999,1/tblMatrizTradeOff[[#This Row],[I6]])) -> 9999 | AL11: =IF(tblMatrizDistancias[[#This Row],[NodoOrigen \ NodoDestino]]="I7",0,IF(tblMatrizTradeOff[[#This Row],[I7]]=0,9999,1/tblMatrizTradeOff[[#This Row],[I7]])) -> 9999 | AM11: =IF(tblMatrizDistancias[[#This Row],[NodoOrigen \ NodoDestino]]="I8",0,IF(tblMatrizTradeOff[[#This Row],[I8]]=0,9999,1/tblMatrizTradeOff[[#This Row],[I8]])) -> 9999 | AN11: =IF(tblMatrizDistancias[[#This Row],[NodoOrigen \ NodoDestino]]="I9",0,IF(tblMatrizTradeOff[[#This Row],[I9]]=0,9999,1/tblMatrizTradeOff[[#This Row],[I9]])) -> 9999 | AO11: =IF(tblMatrizDistancias[[#This Row],[NodoOrigen \ NodoDestino]]="G1",0,IF(tblMatrizTradeOff[[#This Row],[G1]]=0,9999,1/tblMatrizTradeOff[[#This Row],[G1]])) -> 0.2 | AP11: =IF(tblMatrizDistancias[[#This Row],[NodoOrigen \ NodoDestino]]="G2",0,IF(tblMatrizTradeOff[[#This Row],[G2]]=0,9999,1/tblMatrizTradeOff[[#This Row],[G2]])) -> 0.15789474 | AQ11: =IF(tblMatrizDistancias[[#This Row],[NodoOrigen \ NodoDestino]]="G3",0,IF(tblMatrizTradeOff[[#This Row],[G3]]=0,9999,1/tblMatrizTradeOff[[#This Row],[G3]])) -> 9999 | AR11: =IF(tblMatrizDistancias[[#This Row],[NodoOrigen \ NodoDestino]]="D",0,IF(tblMatrizTradeOff[[#This Row],[D]]=0,9999,1/tblMatrizTradeOff[[#This Row],[D]])) -> 0.17647059
B12: =VLOOKUP(tblMatrizTradeOff[[#This Row],[NodoOrigen \ NodoDestino]],tblNodos[#All],2,FALSE) -> MVTS / remesas | C12: I3 | D12: =IF(OR(MatrizPonderadaCostes!D12=0,MatrizPonderadaValorOperativo!D12=0),0,MatrizPonderadaValorOperativo!D12/MatrizPonderadaCostes!D12) -> 0 | E12: =IF(OR(MatrizPonderadaCostes!E12=0,MatrizPonderadaValorOperativo!E12=0),0,MatrizPonderadaValorOperativo!E12/MatrizPonderadaCostes!E12) -> 0 | F12: =IF(OR(MatrizPonderadaCostes!F12=0,MatrizPonderadaValorOperativo!F12=0),0,MatrizPonderadaValorOperativo!F12/MatrizPonderadaCostes!F12) -> 0 | G12: =IF(OR(MatrizPonderadaCostes!G12=0,MatrizPonderadaValorOperativo!G12=0),0,MatrizPonderadaValorOperativo!G12/MatrizPonderadaCostes!G12) -> 0 | H12: =IF(OR(MatrizPonderadaCostes!H12=0,MatrizPonderadaValorOperativo!H12=0),0,MatrizPonderadaValorOperativo!H12/MatrizPonderadaCostes!H12) -> 0 | I12: =IF(OR(MatrizPonderadaCostes!I12=0,MatrizPonderadaValorOperativo!I12=0),0,MatrizPonderadaValorOperativo!I12/MatrizPonderadaCostes!I12) -> 0 | J12: =IF(OR(MatrizPonderadaCostes!J12=0,MatrizPonderadaValorOperativo!J12=0),0,MatrizPonderadaValorOperativo!J12/MatrizPonderadaCostes!J12) -> 0 | K12: =IF(OR(MatrizPonderadaCostes!K12=0,MatrizPonderadaValorOperativo!K12=0),0,MatrizPonderadaValorOperativo!K12/MatrizPonderadaCostes!K12) -> 0 | ... V12: =IF(OR(MatrizPonderadaCostes!V12=0,MatrizPonderadaValorOperativo!V12=0),0,MatrizPonderadaValorOperativo!V12/MatrizPonderadaCostes!V12) -> 4.6666667 | X12: =VLOOKUP(tblMatrizDistancias[[#This Row],[NodoOrigen \ NodoDestino]],tblNodos[#All],2,FALSE) -> MVTS / remesas | Y12: I3 | Z12: =IF(tblMatrizDistancias[[#This Row],[NodoOrigen \ NodoDestino]]="O1",0,IF(tblMatrizTradeOff[[#This Row],[O1]]=0,9999,1/tblMatrizTradeOff[[#This Row],[O1]])) -> 9999 | AA12: =IF(tblMatrizDistancias[[#This Row],[NodoOrigen \ NodoDestino]]="O2",0,IF(tblMatrizTradeOff[[#This Row],[O2]]=0,9999,1/tblMatrizTradeOff[[#This Row],[O2]])) -> 9999 | AB12: =IF(tblMatrizDistancias[[#This Row],[NodoOrigen \ NodoDestino]]="O3",0,IF(tblMatrizTradeOff[[#This Row],[O3]]=0,9999,1/tblMatrizTradeOff[[#This Row],[O3]])) -> 9999 | AC12: =IF(tblMatrizDistancias[[#This Row],[NodoOrigen \ NodoDestino]]="O4",0,IF(tblMatrizTradeOff[[#This Row],[O4]]=0,9999,1/tblMatrizTradeOff[[#This Row],[O4]])) -> 9999 | AD12: =IF(tblMatrizDistancias[[#This Row],[NodoOrigen \ NodoDestino]]="O5",0,IF(tblMatrizTradeOff[[#This Row],[O5]]=0,9999,1/tblMatrizTradeOff[[#This Row],[O5]])) -> 9999 | AE12: =IF(tblMatrizDistancias[[#This Row],[NodoOrigen \ NodoDestino]]="O6",0,IF(tblMatrizTradeOff[[#This Row],[O6]]=0,9999,1/tblMatrizTradeOff[[#This Row],[O6]])) -> 9999 | AF12: =IF(tblMatrizDistancias[[#This Row],[NodoOrigen \ NodoDestino]]="I1",0,IF(tblMatrizTradeOff[[#This Row],[I1]]=0,9999,1/tblMatrizTradeOff[[#This Row],[I1]])) -> 9999 | AG12: =IF(tblMatrizDistancias[[#This Row],[NodoOrigen \ NodoDestino]]="I2",0,IF(tblMatrizTradeOff[[#This Row],[I2]]=0,9999,1/tblMatrizTradeOff[[#This Row],[I2]])) -> 9999 | AH12: =IF(tblMatrizDistancias[[#This Row],[NodoOrigen \ NodoDestino]]="I3",0,IF(tblMatrizTradeOff[[#This Row],[I3]]=0,9999,1/tblMatrizTradeOff[[#This Row],[I3]])) -> 0 | AI12: =IF(tblMatrizDistancias[[#This Row],[NodoOrigen \ NodoDestino]]="I4",0,IF(tblMatrizTradeOff[[#This Row],[I4]]=0,9999,1/tblMatrizTradeOff[[#This Row],[I4]])) -> 9999 | AJ12: =IF(tblMatrizDistancias[[#This Row],[NodoOrigen \ NodoDestino]]="I5",0,IF(tblMatrizTradeOff[[#This Row],[I5]]=0,9999,1/tblMatrizTradeOff[[#This Row],[I5]])) -> 9999 | AK12: =IF(tblMatrizDistancias[[#This Row],[NodoOrigen \ NodoDestino]]="I6",0,IF(tblMatrizTradeOff[[#This Row],[I6]]=0,9999,1/tblMatrizTradeOff[[#This Row],[I6]])) -> 9999 | AL12: =IF(tblMatrizDistancias[[#This Row],[NodoOrigen \ NodoDestino]]="I7",0,IF(tblMatrizTradeOff[[#This Row],[I7]]=0,9999,1/tblMatrizTradeOff[[#This Row],[I7]])) -> 9999 | AM12: =IF(tblMatrizDistancias[[#This Row],[NodoOrigen \ NodoDestino]]="I8",0,IF(tblMatrizTradeOff[[#This Row],[I8]]=0,9999,1/tblMatrizTradeOff[[#This Row],[I8]])) -> 9999 | AN12: =IF(tblMatrizDistancias[[#This Row],[NodoOrigen \ NodoDestino]]="I9",0,IF(tblMatrizTradeOff[[#This Row],[I9]]=0,9999,1/tblMatrizTradeOff[[#This Row],[I9]])) -> 9999 | AO12: =IF(tblMatrizDistancias[[#This Row],[NodoOrigen \ NodoDestino]]="G1",0,IF(tblMatrizTradeOff[[#This Row],[G1]]=0,9999,1/tblMatrizTradeOff[[#This Row],[G1]])) -> 9999 | AP12: =IF(tblMatrizDistancias[[#This Row],[NodoOrigen \ NodoDestino]]="G2",0,IF(tblMatrizTradeOff[[#This Row],[G2]]=0,9999,1/tblMatrizTradeOff[[#This Row],[G2]])) -> 0.2 | AQ12: =IF(tblMatrizDistancias[[#This Row],[NodoOrigen \ NodoDestino]]="G3",0,IF(tblMatrizTradeOff[[#This Row],[G3]]=0,9999,1/tblMatrizTradeOff[[#This Row],[G3]])) -> 0.21428571 | AR12: =IF(tblMatrizDistancias[[#This Row],[NodoOrigen \ NodoDestino]]="D",0,IF(tblMatrizTradeOff[[#This Row],[D]]=0,9999,1/tblMatrizTradeOff[[#This Row],[D]])) -> 0.21428571
B13: =VLOOKUP(tblMatrizTradeOff[[#This Row],[NodoOrigen \ NodoDestino]],tblNodos[#All],2,FALSE) -> Dinero móvil | C13: I4 | D13: =IF(OR(MatrizPonderadaCostes!D13=0,MatrizPonderadaValorOperativo!D13=0),0,MatrizPonderadaValorOperativo!D13/MatrizPonderadaCostes!D13) -> 0 | E13: =IF(OR(MatrizPonderadaCostes!E13=0,MatrizPonderadaValorOperativo!E13=0),0,MatrizPonderadaValorOperativo!E13/MatrizPonderadaCostes!E13) -> 0 | F13: =IF(OR(MatrizPonderadaCostes!F13=0,MatrizPonderadaValorOperativo!F13=0),0,MatrizPonderadaValorOperativo!F13/MatrizPonderadaCostes!F13) -> 0 | G13: =IF(OR(MatrizPonderadaCostes!G13=0,MatrizPonderadaValorOperativo!G13=0),0,MatrizPonderadaValorOperativo!G13/MatrizPonderadaCostes!G13) -> 0 | H13: =IF(OR(MatrizPonderadaCostes!H13=0,MatrizPonderadaValorOperativo!H13=0),0,MatrizPonderadaValorOperativo!H13/MatrizPonderadaCostes!H13) -> 0 | I13: =IF(OR(MatrizPonderadaCostes!I13=0,MatrizPonderadaValorOperativo!I13=0),0,MatrizPonderadaValorOperativo!I13/MatrizPonderadaCostes!I13) -> 0 | J13: =IF(OR(MatrizPonderadaCostes!J13=0,MatrizPonderadaValorOperativo!J13=0),0,MatrizPonderadaValorOperativo!J13/MatrizPonderadaCostes!J13) -> 0 | K13: =IF(OR(MatrizPonderadaCostes!K13=0,MatrizPonderadaValorOperativo!K13=0),0,MatrizPonderadaValorOperativo!K13/MatrizPonderadaCostes!K13) -> 0 | ... V13: =IF(OR(MatrizPonderadaCostes!V13=0,MatrizPonderadaValorOperativo!V13=0),0,MatrizPonderadaValorOperativo!V13/MatrizPonderadaCostes!V13) -> 0 | X13: =VLOOKUP(tblMatrizDistancias[[#This Row],[NodoOrigen \ NodoDestino]],tblNodos[#All],2,FALSE) -> Dinero móvil | Y13: I4 | Z13: =IF(tblMatrizDistancias[[#This Row],[NodoOrigen \ NodoDestino]]="O1",0,IF(tblMatrizTradeOff[[#This Row],[O1]]=0,9999,1/tblMatrizTradeOff[[#This Row],[O1]])) -> 9999 | AA13: =IF(tblMatrizDistancias[[#This Row],[NodoOrigen \ NodoDestino]]="O2",0,IF(tblMatrizTradeOff[[#This Row],[O2]]=0,9999,1/tblMatrizTradeOff[[#This Row],[O2]])) -> 9999 | AB13: =IF(tblMatrizDistancias[[#This Row],[NodoOrigen \ NodoDestino]]="O3",0,IF(tblMatrizTradeOff[[#This Row],[O3]]=0,9999,1/tblMatrizTradeOff[[#This Row],[O3]])) -> 9999 | AC13: =IF(tblMatrizDistancias[[#This Row],[NodoOrigen \ NodoDestino]]="O4",0,IF(tblMatrizTradeOff[[#This Row],[O4]]=0,9999,1/tblMatrizTradeOff[[#This Row],[O4]])) -> 9999 | AD13: =IF(tblMatrizDistancias[[#This Row],[NodoOrigen \ NodoDestino]]="O5",0,IF(tblMatrizTradeOff[[#This Row],[O5]]=0,9999,1/tblMatrizTradeOff[[#This Row],[O5]])) -> 9999 | AE13: =IF(tblMatrizDistancias[[#This Row],[NodoOrigen \ NodoDestino]]="O6",0,IF(tblMatrizTradeOff[[#This Row],[O6]]=0,9999,1/tblMatrizTradeOff[[#This Row],[O6]])) -> 9999 | AF13: =IF(tblMatrizDistancias[[#This Row],[NodoOrigen \ NodoDestino]]="I1",0,IF(tblMatrizTradeOff[[#This Row],[I1]]=0,9999,1/tblMatrizTradeOff[[#This Row],[I1]])) -> 9999 | AG13: =IF(tblMatrizDistancias[[#This Row],[NodoOrigen \ NodoDestino]]="I2",0,IF(tblMatrizTradeOff[[#This Row],[I2]]=0,9999,1/tblMatrizTradeOff[[#This Row],[I2]])) -> 9999 | AH13: =IF(tblMatrizDistancias[[#This Row],[NodoOrigen \ NodoDestino]]="I3",0,IF(tblMatrizTradeOff[[#This Row],[I3]]=0,9999,1/tblMatrizTradeOff[[#This Row],[I3]])) -> 9999 | AI13: =IF(tblMatrizDistancias[[#This Row],[NodoOrigen \ NodoDestino]]="I4",0,IF(tblMatrizTradeOff[[#This Row],[I4]]=0,9999,1/tblMatrizTradeOff[[#This Row],[I4]])) -> 0 | AJ13: =IF(tblMatrizDistancias[[#This Row],[NodoOrigen \ NodoDestino]]="I5",0,IF(tblMatrizTradeOff[[#This Row],[I5]]=0,9999,1/tblMatrizTradeOff[[#This Row],[I5]])) -> 9999 | AK13: =IF(tblMatrizDistancias[[#This Row],[NodoOrigen \ NodoDestino]]="I6",0,IF(tblMatrizTradeOff[[#This Row],[I6]]=0,9999,1/tblMatrizTradeOff[[#This Row],[I6]])) -> 9999 | AL13: =IF(tblMatrizDistancias[[#This Row],[NodoOrigen \ NodoDestino]]="I7",0,IF(tblMatrizTradeOff[[#This Row],[I7]]=0,9999,1/tblMatrizTradeOff[[#This Row],[I7]])) -> 9999 | AM13: =IF(tblMatrizDistancias[[#This Row],[NodoOrigen \ NodoDestino]]="I8",0,IF(tblMatrizTradeOff[[#This Row],[I8]]=0,9999,1/tblMatrizTradeOff[[#This Row],[I8]])) -> 9999 | AN13: =IF(tblMatrizDistancias[[#This Row],[NodoOrigen \ NodoDestino]]="I9",0,IF(tblMatrizTradeOff[[#This Row],[I9]]=0,9999,1/tblMatrizTradeOff[[#This Row],[I9]])) -> 9999 | AO13: =IF(tblMatrizDistancias[[#This Row],[NodoOrigen \ NodoDestino]]="G1",0,IF(tblMatrizTradeOff[[#This Row],[G1]]=0,9999,1/tblMatrizTradeOff[[#This Row],[G1]])) -> 9999 | AP13: =IF(tblMatrizDistancias[[#This Row],[NodoOrigen \ NodoDestino]]="G2",0,IF(tblMatrizTradeOff[[#This Row],[G2]]=0,9999,1/tblMatrizTradeOff[[#This Row],[G2]])) -> 0.28571429 | AQ13: =IF(tblMatrizDistancias[[#This Row],[NodoOrigen \ NodoDestino]]="G3",0,IF(tblMatrizTradeOff[[#This Row],[G3]]=0,9999,1/tblMatrizTradeOff[[#This Row],[G3]])) -> 9999 | AR13: =IF(tblMatrizDistancias[[#This Row],[NodoOrigen \ NodoDestino]]="D",0,IF(tblMatrizTradeOff[[#This Row],[D]]=0,9999,1/tblMatrizTradeOff[[#This Row],[D]])) -> 9999
B14: =VLOOKUP(tblMatrizTradeOff[[#This Row],[NodoOrigen \ NodoDestino]],tblNodos[#All],2,FALSE) -> Pagos online | C14: I5 | D14: =IF(OR(MatrizPonderadaCostes!D14=0,MatrizPonderadaValorOperativo!D14=0),0,MatrizPonderadaValorOperativo!D14/MatrizPonderadaCostes!D14) -> 0 | E14: =IF(OR(MatrizPonderadaCostes!E14=0,MatrizPonderadaValorOperativo!E14=0),0,MatrizPonderadaValorOperativo!E14/MatrizPonderadaCostes!E14) -> 0 | F14: =IF(OR(MatrizPonderadaCostes!F14=0,MatrizPonderadaValorOperativo!F14=0),0,MatrizPonderadaValorOperativo!F14/MatrizPonderadaCostes!F14) -> 0 | G14: =IF(OR(MatrizPonderadaCostes!G14=0,MatrizPonderadaValorOperativo!G14=0),0,MatrizPonderadaValorOperativo!G14/MatrizPonderadaCostes!G14) -> 0 | H14: =IF(OR(MatrizPonderadaCostes!H14=0,MatrizPonderadaValorOperativo!H14=0),0,MatrizPonderadaValorOperativo!H14/MatrizPonderadaCostes!H14) -> 0 | I14: =IF(OR(MatrizPonderadaCostes!I14=0,MatrizPonderadaValorOperativo!I14=0),0,MatrizPonderadaValorOperativo!I14/MatrizPonderadaCostes!I14) -> 0 | J14: =IF(OR(MatrizPonderadaCostes!J14=0,MatrizPonderadaValorOperativo!J14=0),0,MatrizPonderadaValorOperativo!J14/MatrizPonderadaCostes!J14) -> 0 | K14: =IF(OR(MatrizPonderadaCostes!K14=0,MatrizPonderadaValorOperativo!K14=0),0,MatrizPonderadaValorOperativo!K14/MatrizPonderadaCostes!K14) -> 0 | ... V14: =IF(OR(MatrizPonderadaCostes!V14=0,MatrizPonderadaValorOperativo!V14=0),0,MatrizPonderadaValorOperativo!V14/MatrizPonderadaCostes!V14) -> 0 | X14: =VLOOKUP(tblMatrizDistancias[[#This Row],[NodoOrigen \ NodoDestino]],tblNodos[#All],2,FALSE) -> Pagos online | Y14: I5 | Z14: =IF(tblMatrizDistancias[[#This Row],[NodoOrigen \ NodoDestino]]="O1",0,IF(tblMatrizTradeOff[[#This Row],[O1]]=0,9999,1/tblMatrizTradeOff[[#This Row],[O1]])) -> 9999 | AA14: =IF(tblMatrizDistancias[[#This Row],[NodoOrigen \ NodoDestino]]="O2",0,IF(tblMatrizTradeOff[[#This Row],[O2]]=0,9999,1/tblMatrizTradeOff[[#This Row],[O2]])) -> 9999 | AB14: =IF(tblMatrizDistancias[[#This Row],[NodoOrigen \ NodoDestino]]="O3",0,IF(tblMatrizTradeOff[[#This Row],[O3]]=0,9999,1/tblMatrizTradeOff[[#This Row],[O3]])) -> 9999 | AC14: =IF(tblMatrizDistancias[[#This Row],[NodoOrigen \ NodoDestino]]="O4",0,IF(tblMatrizTradeOff[[#This Row],[O4]]=0,9999,1/tblMatrizTradeOff[[#This Row],[O4]])) -> 9999 | AD14: =IF(tblMatrizDistancias[[#This Row],[NodoOrigen \ NodoDestino]]="O5",0,IF(tblMatrizTradeOff[[#This Row],[O5]]=0,9999,1/tblMatrizTradeOff[[#This Row],[O5]])) -> 9999 | AE14: =IF(tblMatrizDistancias[[#This Row],[NodoOrigen \ NodoDestino]]="O6",0,IF(tblMatrizTradeOff[[#This Row],[O6]]=0,9999,1/tblMatrizTradeOff[[#This Row],[O6]])) -> 9999 | AF14: =IF(tblMatrizDistancias[[#This Row],[NodoOrigen \ NodoDestino]]="I1",0,IF(tblMatrizTradeOff[[#This Row],[I1]]=0,9999,1/tblMatrizTradeOff[[#This Row],[I1]])) -> 9999 | AG14: =IF(tblMatrizDistancias[[#This Row],[NodoOrigen \ NodoDestino]]="I2",0,IF(tblMatrizTradeOff[[#This Row],[I2]]=0,9999,1/tblMatrizTradeOff[[#This Row],[I2]])) -> 9999 | AH14: =IF(tblMatrizDistancias[[#This Row],[NodoOrigen \ NodoDestino]]="I3",0,IF(tblMatrizTradeOff[[#This Row],[I3]]=0,9999,1/tblMatrizTradeOff[[#This Row],[I3]])) -> 9999 | AI14: =IF(tblMatrizDistancias[[#This Row],[NodoOrigen \ NodoDestino]]="I4",0,IF(tblMatrizTradeOff[[#This Row],[I4]]=0,9999,1/tblMatrizTradeOff[[#This Row],[I4]])) -> 9999 | AJ14: =IF(tblMatrizDistancias[[#This Row],[NodoOrigen \ NodoDestino]]="I5",0,IF(tblMatrizTradeOff[[#This Row],[I5]]=0,9999,1/tblMatrizTradeOff[[#This Row],[I5]])) -> 0 | AK14: =IF(tblMatrizDistancias[[#This Row],[NodoOrigen \ NodoDestino]]="I6",0,IF(tblMatrizTradeOff[[#This Row],[I6]]=0,9999,1/tblMatrizTradeOff[[#This Row],[I6]])) -> 9999 | AL14: =IF(tblMatrizDistancias[[#This Row],[NodoOrigen \ NodoDestino]]="I7",0,IF(tblMatrizTradeOff[[#This Row],[I7]]=0,9999,1/tblMatrizTradeOff[[#This Row],[I7]])) -> 9999 | AM14: =IF(tblMatrizDistancias[[#This Row],[NodoOrigen \ NodoDestino]]="I8",0,IF(tblMatrizTradeOff[[#This Row],[I8]]=0,9999,1/tblMatrizTradeOff[[#This Row],[I8]])) -> 9999 | AN14: =IF(tblMatrizDistancias[[#This Row],[NodoOrigen \ NodoDestino]]="I9",0,IF(tblMatrizTradeOff[[#This Row],[I9]]=0,9999,1/tblMatrizTradeOff[[#This Row],[I9]])) -> 9999 | AO14: =IF(tblMatrizDistancias[[#This Row],[NodoOrigen \ NodoDestino]]="G1",0,IF(tblMatrizTradeOff[[#This Row],[G1]]=0,9999,1/tblMatrizTradeOff[[#This Row],[G1]])) -> 9999 | AP14: =IF(tblMatrizDistancias[[#This Row],[NodoOrigen \ NodoDestino]]="G2",0,IF(tblMatrizTradeOff[[#This Row],[G2]]=0,9999,1/tblMatrizTradeOff[[#This Row],[G2]])) -> 0.30769231 | AQ14: =IF(tblMatrizDistancias[[#This Row],[NodoOrigen \ NodoDestino]]="G3",0,IF(tblMatrizTradeOff[[#This Row],[G3]]=0,9999,1/tblMatrizTradeOff[[#This Row],[G3]])) -> 0.23076923 | AR14: =IF(tblMatrizDistancias[[#This Row],[NodoOrigen \ NodoDestino]]="D",0,IF(tblMatrizTradeOff[[#This Row],[D]]=0,9999,1/tblMatrizTradeOff[[#This Row],[D]])) -> 9999
